Workbook

Sheet Overall
B2: SUMMARY
H3: Share price | K3: Profit Margins | T3: Valuations Multiples | AC3: Solvency | AL3: Efficiency | AU3: Risk
H4: CAGR | K4: GPM | N4: OM | Q4: NPM | T4: PE | W4: EPS | Z4: Dividend Yield | AC4: Debt Ratio | AF4: Debt - Equity | AI4: Debt - Revenue | AL4: IT | AO4: RT | AR4: PT | AU4: Sharpe Ratio | AX4: Sortino Ratio
B5: Base year | D5: Y/E | E5: Updated As At | F5: MC | G5: Share price at Y/E | H5: Current | I5: 3 years | J5: 5 years | K5: Current | L5: 3 years | M5: 5 years | N5: Current | O5: 3 years | P5: 5 years | Q5: Current | R5: 3 years | S5: 5 years | T5: Current | U5: 3 years | V5: 5 years | W5: Current | X5: 3 years | Y5: 5 years | Z5: Current | AA5: 3 years | AB5: 5 years | AC5: Current | AD5: 3 years | AE5: 5 years | AF5: Current | AG5: 3 years | AH5: 5 years | AI5: Current | AJ5: 3 years | AK5: 5 years | AL5: Current | AM5: 3 years | AN5: 5 years | AO5: Current | AP5: 3 years | AQ5: 5 years | AR5: Current | AS5: 3 years | AT5: 5 years | AU5: Current | AV5: 3 years | AW5: 5 years | AX5: Current | AY5: 3 years | AZ5: 5 years
B6: 2023 | D6: 31/12 | E6: 2023 | F6: =OFFSET(FS!P123,0,E$6-B$6) -> 1655842.1 | G6: =OFFSET(FS!P117,0,E$6-B$6) -> 151.94 | H6: =((OFFSET(FS!P$117,0,E$6-B$6)/OFFSET(FS!P$117,0,-1+E$6-B$6))^(1/1)-1)*100 -> 80.880952 | I6: =((OFFSET(FS!P$117,0,E$6-B$6)/OFFSET(FS!P$117,0,-2+E$6-B$6))^(1/3)-1)*100 -> -3.4162991 | J6: =((OFFSET(FS!P$117,0,E$6-B$6)/OFFSET(FS!P$117,0,-4+E$6-B$6))^(1/5)-1)*100 -> 10.473077 | K6: =OFFSET(FS!P$91,0,0+E$6-B$6) -> 46.982089 | L6: =AVERAGE(OFFSET(FS!P$91,0,-2+E$6-B$6):OFFSET(FS!P$91,0,E$6-B$6)) -> 44.273314 | M6: =AVERAGE(OFFSET(FS!P$91,0,-4+E$6-B$6):OFFSET(FS!P$91,0,E$6-B$6)) -> 42.675549 | N6: =OFFSET(FS!P$101,0,0+E$6-B$6) -> 6.4114408 | O6: =AVERAGE(OFFSET(FS!P$101,0,-2+E$6-B$6):OFFSET(FS!P$101,0,E$6-B$6)) -> 4.6966029 | P6: =AVERAGE(OFFSET(FS!P$101,0,-4+E$6-B$6):OFFSET(FS!P$101,0,E$6-B$6)) -> 5.0409519 | Q6: =OFFSET(FS!P$110,0,0+E$6-B$6) -> 5.2932836 | R6: =AVERAGE(OFFSET(FS!P$110,0,-2+E$6-B$6):OFFSET(FS!P$110,0,E$6-B$6)) -> 3.9550357 | S6: =AVERAGE(OFFSET(FS!P$110,0,-4+E$6-B$6):OFFSET(FS!P$110,0,E$6-B$6)) -> 4.3042454 | T6: =OFFSET(FS!P$119,0,0+E$6-B$6) -> 54.423734 | U6: =AVERAGE(OFFSET(FS!P$119,0,-2+E$6-B$6):OFFSET(FS!P$119,0,E$6-B$6)) -> 36.074788 | V6: =AVERAGE(OFFSET(FS!P$119,0,-4+E$6-B$6):OFFSET(FS!P$119,0,E$6-B$6)) -> 54.487092 | W6: =OFFSET(FS!P$118,0,0+E$6-B$6) -> 2.7917967 | X6: =AVERAGE(OFFSET(FS!P$118,0,-2+E$6-B$6):OFFSET(FS!P$118,0,E$6-B$6)) -> 1.891096 | Y6: =AVERAGE(OFFSET(FS!P$118,0,-4+E$6-B$6):OFFSET(FS!P$118,0,E$6-B$6)) -> 1.7618388 | Z6: =OFFSET(FS!P$129,0,0+E$6-B$6) -> 0 | AA6: =AVERAGE(OFFSET(FS!P$129,0,-2+E$6-B$6):OFFSET(FS!P$129,0,E$6-B$6)) -> 0 | AB6: =AVERAGE(OFFSET(FS!P$129,0,-4+E$6-B$6):OFFSET(FS!P$129,0,E$6-B$6)) -> 0 | AC6: =OFFSET(FS!P$175,0,0+E$6-B$6) -> 0.61755523 | AD6: =AVERAGE(OFFSET(FS!P$175,0,-2+E$6-B$6):OFFSET(FS!P$175,0,E$6-B$6)) -> 0.65772698 | AE6: =AVERAGE(OFFSET(FS!P$175,0,-4+E$6-B$6):OFFSET(FS!P$175,0,E$6-B$6)) -> 0.68137217 | AF6: =OFFSET(FS!P$176,0,0+E$6-B$6) -> 1.6147567 | AG6: =AVERAGE(OFFSET(FS!P$176,0,-2+E$6-B$6):OFFSET(FS!P$176,0,E$6-B$6)) -> 1.9416287 | AH6: =AVERAGE(OFFSET(FS!P$176,0,-4+E$6-B$6):OFFSET(FS!P$176,0,E$6-B$6)) -> 2.1786355 | AI6: =OFFSET(FS!P$177,0,0+E$6-B$6) -> 0.56713206 | AJ6: =AVERAGE(OFFSET(FS!P$177,0,-2+E$6-B$6):OFFSET(FS!P$177,0,E$6-B$6)) -> 0.59468079 | AK6: =AVERAGE(OFFSET(FS!P$177,0,-4+E$6-B$6):OFFSET(FS!P$177,0,E$6-B$6)) -> 0.59116129 | AL6: =OFFSET(FS!P$180,0,0+E$6-B$6) -> 9.1463773 | AM6: =AVERAGE(OFFSET(FS!P$180,0,-2+E$6-B$6):OFFSET(FS!P$180,0,E$6-B$6)) -> 8.6284266 | AN6: =AVERAGE(OFFSET(FS!P$180,0,-4+E$6-B$6):OFFSET(FS!P$180,0,E$6-B$6)) -> 8.7532527 | AO6: =OFFSET(FS!P$181,0,0+E$6-B$6) -> 11.000038 | AP6: =AVERAGE(OFFSET(FS!P$181,0,-2+E$6-B$6):OFFSET(FS!P$181,0,E$6-B$6)) -> 12.472646 | AQ6: =AVERAGE(OFFSET(FS!P$181,0,-4+E$6-B$6):OFFSET(FS!P$181,0,E$6-B$6)) -> 13.324991 | AR6: =OFFSET(FS!P$182,0,0+E$6-B$6) -> 3.5859663 | AS6: =AVERAGE(OFFSET(FS!P$182,0,-2+E$6-B$6):OFFSET(FS!P$182,0,E$6-B$6)) -> 3.5588713 | AT6: =AVERAGE(OFFSET(FS!P$182,0,-4+E$6-B$6):OFFSET(FS!P$182,0,E$6-B$6)) -> 3.4802587 | AU6: ='Sharpe, Sortino'!O23 -> 1.561188 | AV6: ='Sharpe, Sortino'!P23 -> -0.12295655 | AW6: ='Sharpe, Sortino'!Q23 -> 0.29297356 | AX6: ='Sharpe, Sortino'!O40 -> 24.748212 | AY6: ='Sharpe, Sortino'!P40 -> -0.22680311 | AZ6: ='Sharpe, Sortino'!Q40 -> 0.57295928

Sheet FS
F1: < Figures are in millions >
F2: Y/E 31/12 | U2: Annualized
F3: 2013 | G3: 2014 | H3: 2015 | I3: 2016 | J3: 2017 | K3: 2018 | L3: 2019 | M3: 2020 | N3: 2021 | O3: 2022 | P3: 2023 | R3: Average | S3: Median | T3: CAGR | U3: Std Dev
B5: Revenue by Geography
C6: United States | F6: 43959 | G6: 54717 | H6: 70537 | I6: 90349 | J6: 120486 | K6: 160146 | L6: 193636 | M6: 263520 | N6: 314006 | O6: 356113 | P6: 395637
C7: Germany | F7: 10535 | G7: 11919 | H7: 11816 | I7: 14148 | J7: 16951 | K7: 19881 | L7: 22232 | M7: 29565 | N7: 37326 | O7: 33598 | P7: 37588
C8: United Kingdom | F8: 7291 | G8: 8341 | H8: 9033 | I8: 9547 | J8: 11372 | K8: 14524 | L8: 17527 | M8: 26483 | N8: 31914 | O8: 30074 | P8: 33591
C9: Japan | F9: 7639 | G9: 7912 | H9: 8264 | I9: 10797 | J9: 11907 | K9: 13829 | L9: 16002 | M9: 20461 | N9: 23071 | O9: 24396 | P9: 26002
C10: Rest of World | F10: 5028 | G10: 6099 | H10: 7356 | I10: 11146 | J10: 17150 | K10: 24507 | L10: 31125 | M10: 46035 | N10: 63505 | O10: 69802 | P10: 81967
B11: Total Revenues | F11: =SUM(F6:F10) -> 74452 | G11: =SUM(G6:G10) -> 88988 | H11: =SUM(H6:H10) -> 107006 | I11: =SUM(I6:I10) -> 135987 | J11: =SUM(J6:J10) -> 177866 | K11: =SUM(K6:K10) -> 232887 | L11: =SUM(L6:L10) -> 280522 | M11: =SUM(M6:M10) -> 386064 | ... P11: =SUM(P6:P10) -> 574785
B13: Revenue By Specific Segments
C14: Online Stores | F14: =48802+21716 -> 70518 | G14: 68513 | H14: 76863 | I14: 91431 | J14: 108354 | K14: 122987 | L14: 141247 | M14: 197346 | N14: 222075 | O14: 220004 | P14: 231872
C15: Physical Stores | F15: 0 | G15: 0 | H15: 0 | I15: 0 | J15: 5798 | K15: 17224 | L15: 17192 | M15: 16227 | N15: 17075 | O15: 18963 | P15: 20030
C16: Third Party seller services | F16: 0 | G16: 11747 | H16: 16086 | I16: 22993 | J16: 31881 | K16: 42745 | L16: 53762 | M16: 80461 | N16: 103366 | O16: 117716 | P16: 140053
C17: Advertising services | F17: 826 | G17: 1322 | H17: 1710 | I17: 2950 | J17: 4653 | K17: 10108 | L17: 19210 | M17: 25207 | N17: 31160 | O17: 37739 | P17: 46906
C18: Subscription services | F18: 0 | G18: 2762 | H18: 4467 | I18: 6394 | J18: 9721 | K18: 14168 | L18: 12625 | M18: 19773 | N18: 31768 | O18: 35218 | P18: 40209
C19: AWS | F19: 3108 | G19: 4644 | H19: 7880 | I19: 12219 | J19: 17459 | K19: 25655 | L19: 35026 | M19: 45370 | N19: 62202 | O19: 80096 | P19: 90757
C20: Other | G20: 0 | H20: 0 | I20: 0 | J20: 0 | K20: 0 | L20: 1460 | M20: 1680 | N20: 2176 | O20: 4247 | P20: 4958
B21: Total Revenues | F21: =SUM(F14:F20) -> 74452 | G21: =SUM(G14:G20) -> 88988 | H21: =SUM(H14:H20) -> 107006 | I21: =SUM(I14:I20) -> 135987 | J21: =SUM(J14:J20) -> 177866 | K21: =SUM(K14:K20) -> 232887 | L21: =SUM(L14:L20) -> 280522 | M21: =SUM(M14:M20) -> 386064 | ... P21: =SUM(P14:P20) -> 574785
B23: Revenue By Broad Segments
C24: North America | F24: 41410 | G24: 50834 | H24: 63708 | I24: 79785 | J24: 106110 | K24: 141366 | L24: 170773 | M24: 236282 | N24: 279833 | O24: 315880 | P24: 352828
C25: International | F25: 29934 | G25: 33510 | H25: 35418 | I25: 43983 | J25: 54297 | K25: 65866 | L25: 74723 | M25: 104412 | N25: 127787 | O25: 118007 | P25: 131200
C26: AWS (Global) | F26: 3108 | G26: 4644 | H26: 7880 | I26: 12219 | J26: 17459 | K26: 25655 | L26: 35026 | M26: 45370 | N26: 62202 | O26: 80096 | P26: 90757
B27: Total Revenues | F27: =SUM(F24:F26) -> 74452 | G27: =SUM(G24:G26) -> 88988 | H27: =SUM(H24:H26) -> 107006 | I27: =SUM(I24:I26) -> 135987 | J27: =SUM(J24:J26) -> 177866 | K27: =SUM(K24:K26) -> 232887 | L27: =SUM(L24:L26) -> 280522 | M27: =SUM(M24:M26) -> 386064 | ... P27: =SUM(P24:P26) -> 574785
B29: Operating Income/(loss)
C30: North America | F30: =1166-731+350 -> 785 | G30: 360 | H30: 1425 | I30: 2361 | J30: 2837 | K30: 7267 | L30: 7033 | M30: 8651 | N30: 7271 | O30: -2847 | P30: 14877
C31: International | F31: =154-96-700 -> -642 | G31: -640 | H31: -699 | I31: -1283 | J31: -3062 | K31: -2142 | L31: -1693 | M31: 717 | N31: -924 | O31: -7746 | P31: -2656
C32: AWS (Global) | F32: =673-421+350 -> 602 | G32: 458 | H32: 1507 | I32: 3108 | J32: 4331 | K32: 7296 | L32: 9201 | M32: 13531 | N32: 18532 | O32: 22841 | P32: 24631
B33: Total Operating Income | F33: =SUM(F30:F32) -> 745 | G33: =SUM(G30:G32) -> 178 | H33: =SUM(H30:H32) -> 2233 | I33: =SUM(I30:I32) -> 4186 | J33: =SUM(J30:J32) -> 4106 | K33: =SUM(K30:K32) -> 12421 | L33: =SUM(L30:L32) -> 14541 | M33: =SUM(M30:M32) -> 22899 | ... P33: =SUM(P30:P32) -> 36852
F35: Guessed figures
C36: Composition By Geography
C37: United States | F37: =F6/F$11*100 -> 59.043411 | G37: =G6/G$11*100 -> 61.488066 | H37: =H6/H$11*100 -> 65.918734 | I37: =I6/I$11*100 -> 66.439439 | J37: =J6/J$11*100 -> 67.739759 | K37: =K6/K$11*100 -> 68.765539 | L37: =L6/L$11*100 -> 69.027028 | M37: =M6/M$11*100 -> 68.258113 | ... P37: =P6/P$11*100 -> 68.832172 | R37: =AVERAGEIF(E37:Q37,"<>0") -> 66.51203
C38: Germany | F38: =F7/F$11*100 -> 14.150056 | G38: =G7/G$11*100 -> 13.393941 | H38: =H7/H$11*100 -> 11.042371 | I38: =I7/I$11*100 -> 10.403936 | J38: =J7/J$11*100 -> 9.5302081 | K38: =K7/K$11*100 -> 8.5367582 | L38: =L7/L$11*100 -> 7.9252251 | M38: =M7/M$11*100 -> 7.6580567 | ... P38: =P7/P$11*100 -> 6.5394887 | R38: =AVERAGEIF(E38:Q38,"<>0") -> 9.4237767
C39: United Kingdom | F39: =F8/F$11*100 -> 9.7928867 | G39: =G8/G$11*100 -> 9.3731739 | H39: =H8/H$11*100 -> 8.4415827 | I39: =I8/I$11*100 -> 7.020524 | J39: =J8/J$11*100 -> 6.3935772 | K39: =K8/K$11*100 -> 6.236501 | L39: =L8/L$11*100 -> 6.2479948 | M39: =M8/M$11*100 -> 6.8597435 | ... P39: =P8/P$11*100 -> 5.8440982
C40: Japan | F40: =F9/F$11*100 -> 10.260302 | G40: =G9/G$11*100 -> 8.8910864 | H40: =H9/H$11*100 -> 7.7229314 | I40: =I9/I$11*100 -> 7.9397295 | J40: =J9/J$11*100 -> 6.6943654 | K40: =K9/K$11*100 -> 5.938073 | L40: =L9/L$11*100 -> 5.7043654 | M40: =M9/M$11*100 -> 5.2998985 | ... P40: =P9/P$11*100 -> 4.5237785 | R40: =AVERAGEIF(E40:Q40,"<>0") -> 6.6028703
C41: Rest of World | F41: =F10/F$11*100 -> 6.7533444 | G41: =G10/G$11*100 -> 6.8537331 | H41: =H10/H$11*100 -> 6.8743809 | I41: =I10/I$11*100 -> 8.1963717 | J41: =J10/J$11*100 -> 9.6420901 | K41: =K10/K$11*100 -> 10.523129 | L41: =L10/L$11*100 -> 11.095386 | M41: =M10/M$11*100 -> 11.924189 | ... P41: =P10/P$11*100 -> 14.260463 | R41: =AVERAGEIF(E41:Q41,"<>0") -> 10.292774
F42: =SUM(F37:F41) -> 100 | G42: =SUM(G37:G41) -> 100 | H42: =SUM(H37:H41) -> 100 | I42: =SUM(I37:I41) -> 100 | J42: =SUM(J37:J41) -> 100 | K42: =SUM(K37:K41) -> 100 | L42: =SUM(L37:L41) -> 100 | M42: =SUM(M37:M41) -> 100 | ... P42: =SUM(P37:P41) -> 100
C44: Composition By Specific Segments
C45: Online Stores | F45: =F14/F$21*100 -> 94.716059 | G45: =G14/G$21*100 -> 76.99128 | H45: =H14/H$21*100 -> 71.830552 | I45: =I14/I$21*100 -> 67.235103 | J45: =J14/J$21*100 -> 60.918894 | K45: =K14/K$21*100 -> 52.809732 | L45: =L14/L$21*100 -> 50.351488 | M45: =M14/M$21*100 -> 51.117431 | ... P45: =P14/P$21*100 -> 40.340649 | R45: =AVERAGEIF(E45:Q45,"<>0") -> 59.671167
C46: Physical Stores | F46: =F15/F$21*100 -> 0 | G46: =G15/G$21*100 -> 0 | H46: =H15/H$21*100 -> 0 | I46: =I15/I$21*100 -> 0 | J46: =J15/J$21*100 -> 3.2597573 | K46: =K15/K$21*100 -> 7.3958615 | L46: =L15/L$21*100 -> 6.1285746 | M46: =M15/M$21*100 -> 4.2031891 | ... P46: =P15/P$21*100 -> 3.4847813 | R46: =AVERAGEIF(E46:Q46,"<>0") -> 4.5422772
C47: Thrid Party seller services | F47: =F16/F$21*100 -> 0 | G47: =G16/G$21*100 -> 13.200656 | H47: =H16/H$21*100 -> 15.032802 | I47: =I16/I$21*100 -> 16.908234 | J47: =J16/J$21*100 -> 17.924168 | K47: =K16/K$21*100 -> 18.354395 | L47: =L16/L$21*100 -> 19.164985 | M47: =M16/M$21*100 -> 20.841363 | ... P47: =P16/P$21*100 -> 24.366154 | R47: =AVERAGEIF(E47:Q47,"<>0") -> 19.069656
C48: Advertising services | F48: =F17/F$21*100 -> 1.1094396 | G48: =G17/G$21*100 -> 1.4855936 | H48: =H17/H$21*100 -> 1.5980412 | I48: =I17/I$21*100 -> 2.169325 | J48: =J17/J$21*100 -> 2.6160143 | K48: =K17/K$21*100 -> 4.3403024 | L48: =L17/L$21*100 -> 6.8479478 | M48: =M17/M$21*100 -> 6.5292283 | ... P48: =P17/P$21*100 -> 8.1606166 | R48: =AVERAGEIF(E48:Q48,"<>0") -> 4.4392062
C49: Subscription services | F49: =F18/F$21*100 -> 0 | G49: =G18/G$21*100 -> 3.1037893 | H49: =H18/H$21*100 -> 4.1745323 | I49: =I18/I$21*100 -> 4.70192 | J49: =J18/J$21*100 -> 5.4653503 | K49: =K18/K$21*100 -> 6.0836371 | L49: =L18/L$21*100 -> 4.5005383 | M49: =M18/M$21*100 -> 5.1216897 | ... P49: =P18/P$21*100 -> 6.9954853 | R49: =AVERAGEIF(E49:Q49,"<>0") -> 5.376063
C50: AWS | F50: =F19/F$21*100 -> 4.1745017 | G50: =G19/G$21*100 -> 5.2186812 | H50: =H19/H$21*100 -> 7.364073 | I50: =I19/I$21*100 -> 8.9854177 | J50: =J19/J$21*100 -> 9.8158164 | K50: =K19/K$21*100 -> 11.016072 | L50: =L19/L$21*100 -> 12.486008 | M50: =M19/M$21*100 -> 11.751938 | ... P50: =P19/P$21*100 -> 15.78973 | R50: =AVERAGEIF(E50:Q50,"<>0") -> 10.493192
C51: Other | F51: =F20/F$21*100 -> 0 | G51: =G20/G$21*100 -> 0 | H51: =H20/H$21*100 -> 0 | I51: =I20/I$21*100 -> 0 | J51: =J20/J$21*100 -> 0 | K51: =K20/K$21*100 -> 0 | L51: =L20/L$21*100 -> 0.52045829 | M51: =M20/M$21*100 -> 0.43516101 | ... P51: =P20/P$21*100 -> 0.8625834 | R51: =AVERAGEIF(E51:Q51,"<>0") -> 0.62152975
F52: =SUM(F45:F51) -> 100 | G52: =SUM(G45:G51) -> 100 | H52: =SUM(H45:H51) -> 100 | I52: =SUM(I45:I51) -> 100 | J52: =SUM(J45:J51) -> 100 | K52: =SUM(K45:K51) -> 100 | L52: =SUM(L45:L51) -> 100 | M52: =SUM(M45:M51) -> 100 | ... P52: =SUM(P45:P51) -> 100
C54: Composition By Broad Segments
C55: North America | F55: =F24/F$27*100 -> 55.619728 | G55: =G24/G$27*100 -> 57.124556 | H55: =H24/H$27*100 -> 59.536848 | I55: =I24/I$27*100 -> 58.671049 | J55: =J24/J$27*100 -> 59.65727 | K55: =K24/K$27*100 -> 60.701542 | L55: =L24/L$27*100 -> 60.876865 | M55: =M24/M$27*100 -> 61.202806 | ... P55: =P24/P$27*100 -> 61.384344 | R55: =AVERAGEIF(E55:Q55,"<>0") -> 59.617617
C56: International | F56: =F25/F$27*100 -> 40.20577 | G56: =G25/G$27*100 -> 37.656763 | H56: =H25/H$27*100 -> 33.099079 | I56: =I25/I$27*100 -> 32.343533 | J56: =J25/J$27*100 -> 30.526914 | K56: =K25/K$27*100 -> 28.282386 | L56: =L25/L$27*100 -> 26.637126 | M56: =M25/M$27*100 -> 27.045257 | ... P56: =P25/P$27*100 -> 22.825926 | R56: =AVERAGEIF(E56:Q56,"<>0") -> 29.889191
C57: AWS (Global) | F57: =F26/F$27*100 -> 4.1745017 | G57: =G26/G$27*100 -> 5.2186812 | H57: =H26/H$27*100 -> 7.364073 | I57: =I26/I$27*100 -> 8.9854177 | J57: =J26/J$27*100 -> 9.8158164 | K57: =K26/K$27*100 -> 11.016072 | L57: =L26/L$27*100 -> 12.486008 | M57: =M26/M$27*100 -> 11.751938 | ... P57: =P26/P$27*100 -> 15.78973 | R57: =AVERAGEIF(E57:Q57,"<>0") -> 10.493192
F58: =SUM(F55:F57) -> 100 | G58: =SUM(G55:G57) -> 100 | H58: =SUM(H55:H57) -> 100 | I58: =SUM(I55:I57) -> 100 | J58: =SUM(J55:J57) -> 100 | K58: =SUM(K55:K57) -> 100 | L58: =SUM(L55:L57) -> 100 | M58: =SUM(M55:M57) -> 100 | ... P58: =SUM(P55:P57) -> 100
C60: Revenue Growth By Specific Segments (%)
C61: Online Stores | G61: =(G14-F14)/ABS(F14)*100 -> -2.8432457 | H61: =(H14-G14)/ABS(G14)*100 -> 12.187468 | I61: =(I14-H14)/ABS(H14)*100 -> 18.953202 | J61: =(J14-I14)/ABS(I14)*100 -> 18.50904 | K61: =(K14-J14)/ABS(J14)*100 -> 13.504808 | L61: =(L14-K14)/ABS(K14)*100 -> 14.847098 | M61: =(M14-L14)/ABS(L14)*100 -> 39.71695 | N61: =(N14-M14)/ABS(M14)*100 -> 12.530783 | ... P61: =(P14-O14)/ABS(O14)*100 -> 5.3944474 | R61: =AVERAGEIF(E61:Q61,"<>0") -> 13.186798
C62: Physical Stores | K62: =(K15-J15)/ABS(J15)*100 -> 197.06795 | L62: =(L15-K15)/ABS(K15)*100 -> -0.18578727 | M62: =(M15-L15)/ABS(L15)*100 -> -5.6130758 | N62: =(N15-M15)/ABS(M15)*100 -> 5.2258581 | O62: =(O15-N15)/ABS(N15)*100 -> 11.057101 | P62: =(P15-O15)/ABS(O15)*100 -> 5.6267468 | R62: =AVERAGEIF(E62:Q62,"<>0") -> 35.5298
C63: Thrid Party seller services | H63: =(H16-G16)/ABS(G16)*100 -> 36.93709 | I63: =(I16-H16)/ABS(H16)*100 -> 42.937958 | J63: =(J16-I16)/ABS(I16)*100 -> 38.655243 | K63: =(K16-J16)/ABS(J16)*100 -> 34.076723 | L63: =(L16-K16)/ABS(K16)*100 -> 25.773775 | M63: =(M16-L16)/ABS(L16)*100 -> 49.661471 | N63: =(N16-M16)/ABS(M16)*100 -> 28.467208 | O63: =(O16-N16)/ABS(N16)*100 -> 13.882708 | P63: =(P16-O16)/ABS(O16)*100 -> 18.97533 | R63: =AVERAGEIF(E63:Q63,"<>0") -> 32.151945
C64: Advertising services | G64: =(G17-F17)/ABS(F17)*100 -> 60.048426 | H64: =(H17-G17)/ABS(G17)*100 -> 29.34947 | I64: =(I17-H17)/ABS(H17)*100 -> 72.51462 | J64: =(J17-I17)/ABS(I17)*100 -> 57.728814 | K64: =(K17-J17)/ABS(J17)*100 -> 117.23619 | L64: =(L17-K17)/ABS(K17)*100 -> 90.047487 | M64: =(M17-L17)/ABS(L17)*100 -> 31.218116 | N64: =(N17-M17)/ABS(M17)*100 -> 23.616456 | ... P64: =(P17-O17)/ABS(O17)*100 -> 24.290522 | R64: =AVERAGEIF(E64:Q64,"<>0") -> 52.716371
C65: Subscription services | H65: =(H18-G18)/ABS(G18)*100 -> 61.73063 | I65: =(I18-H18)/ABS(H18)*100 -> 43.138572 | J65: =(J18-I18)/ABS(I18)*100 -> 52.033156 | K65: =(K18-J18)/ABS(J18)*100 -> 45.746322 | L65: =(L18-K18)/ABS(K18)*100 -> -10.89074 | M65: =(M18-L18)/ABS(L18)*100 -> 56.617822 | N65: =(N18-M18)/ABS(M18)*100 -> 60.663531 | O65: =(O18-N18)/ABS(N18)*100 -> 10.859985 | P65: =(P18-O18)/ABS(O18)*100 -> 14.17173 | R65: =AVERAGEIF(E65:Q65,"<>0") -> 37.119001
C66: AWS | G66: =(G19-F19)/ABS(F19)*100 -> 49.420849 | H66: =(H19-G19)/ABS(G19)*100 -> 69.681309 | I66: =(I19-H19)/ABS(H19)*100 -> 55.063452 | J66: =(J19-I19)/ABS(I19)*100 -> 42.884033 | K66: =(K19-J19)/ABS(J19)*100 -> 46.944269 | L66: =(L19-K19)/ABS(K19)*100 -> 36.526993 | M66: =(M19-L19)/ABS(L19)*100 -> 29.532347 | N66: =(N19-M19)/ABS(M19)*100 -> 37.099405 | ... P66: =(P19-O19)/ABS(O19)*100 -> 13.310278 | R66: =AVERAGEIF(E66:Q66,"<>0") -> 40.92305
C67: Other | M67: =(M20-L20)/ABS(L20)*100 -> 15.068493 | N67: =(N20-M20)/ABS(M20)*100 -> 29.52381 | O67: =(O20-N20)/ABS(N20)*100 -> 95.174632 | P67: =(P20-O20)/ABS(O20)*100 -> 16.741229 | R67: =AVERAGEIF(E67:Q67,"<>0") -> 39.127041
C69: Revenue Growth by Broad Segments (%)
C70: North America | G70: =(G24-F24)/ABS(F24)*100 -> 22.757788 | H70: =(H24-G24)/ABS(G24)*100 -> 25.32557 | I70: =(I24-H24)/ABS(H24)*100 -> 25.235449 | J70: =(J24-I24)/ABS(I24)*100 -> 32.994924 | K70: =(K24-J24)/ABS(J24)*100 -> 33.225898 | L70: =(L24-K24)/ABS(K24)*100 -> 20.802032 | M70: =(M24-L24)/ABS(L24)*100 -> 38.360279 | N70: =(N24-M24)/ABS(M24)*100 -> 18.431789 | ... P70: =(P24-O24)/ABS(O24)*100 -> 11.696847 | R70: =AVERAGEIF(E70:Q70,"<>0") -> 24.171219 | U70: {=_xlfn.STDEV.S(IF(E70:Q70<>0,E70:Q70))} -> 8.7749326
C71: International | G71: =(G25-F25)/ABS(F25)*100 -> 11.946282 | H71: =(H25-G25)/ABS(G25)*100 -> 5.6938227 | I71: =(I25-H25)/ABS(H25)*100 -> 24.182619 | J71: =(J25-I25)/ABS(I25)*100 -> 23.449969 | K71: =(K25-J25)/ABS(J25)*100 -> 21.306886 | L71: =(L25-K25)/ABS(K25)*100 -> 13.446998 | M71: =(M25-L25)/ABS(L25)*100 -> 39.732077 | N71: =(N25-M25)/ABS(M25)*100 -> 22.387273 | ... P71: =(P25-O25)/ABS(O25)*100 -> 11.179845 | R71: =AVERAGEIF(E71:Q71,"<>0") -> 16.567241 | U71: {=_xlfn.STDEV.S(IF(E71:Q71<>0,E71:Q71))} -> 12.751011
C72: AWS (Global) | G72: =(G26-F26)/ABS(F26)*100 -> 49.420849 | H72: =(H26-G26)/ABS(G26)*100 -> 69.681309 | I72: =(I26-H26)/ABS(H26)*100 -> 55.063452 | J72: =(J26-I26)/ABS(I26)*100 -> 42.884033 | K72: =(K26-J26)/ABS(J26)*100 -> 46.944269 | L72: =(L26-K26)/ABS(K26)*100 -> 36.526993 | M72: =(M26-L26)/ABS(L26)*100 -> 29.532347 | N72: =(N26-M26)/ABS(M26)*100 -> 37.099405 | ... P72: =(P26-O26)/ABS(O26)*100 -> 13.310278 | R72: =AVERAGEIF(E72:Q72,"<>0") -> 40.92305 | U72: {=_xlfn.STDEV.S(IF(E72:Q72<>0,E72:Q72))} -> 15.681611
C73: TOTAL REVENUE GROWTH (%) | G73: =(G27-F27)/ABS(F27)*100 -> 19.523989 | H73: =(H27-G27)/ABS(G27)*100 -> 20.247674 | I73: =(I27-H27)/ABS(H27)*100 -> 27.083528 | J73: =(J27-I27)/ABS(I27)*100 -> 30.796326 | K73: =(K27-J27)/ABS(J27)*100 -> 30.933962 | L73: =(L27-K27)/ABS(K27)*100 -> 20.454126 | M73: =(M27-L27)/ABS(L27)*100 -> 37.623431 | N73: =(N27-M27)/ABS(M27)*100 -> 21.695367 | ... P73: =(P27-O27)/ABS(O27)*100 -> 11.829574 | R73: =AVERAGEIF(E73:Q73,"<>0") -> 22.958749 | S73: =MEDIAN(E73:Q73) -> 21.074746 | U73: {=_xlfn.STDEV.S(IF(E73:Q73<>0,E73:Q73))} -> 8.767531 | V73: =R73-U73 -> 14.191218
C76: Operating Income Growth (%)
C77: North America | G77: =(G30-F30)/ABS(F30)*100 -> -54.140127 | H77: =(H30-G30)/ABS(G30)*100 -> 295.83333 | I77: =(I30-H30)/ABS(H30)*100 -> 65.684211 | J77: =(J30-I30)/ABS(I30)*100 -> 20.160949 | K77: =(K30-J30)/ABS(J30)*100 -> 156.15086 | L77: =(L30-K30)/ABS(K30)*100 -> -3.2200358 | M77: =(M30-L30)/ABS(L30)*100 -> 23.00583 | N77: =(N30-M30)/ABS(M30)*100 -> -15.951913 | ... P77: =(P30-O30)/ABS(O30)*100 -> 622.55005 | R77: =AVERAGEIF(E77:Q77,"<>0") -> 97.091761 | U77: {=_xlfn.STDEV.S(IF(E77:Q77<>0,E77:Q77))} -> 219.34532
C78: International | G78: =(G31-F31)/ABS(F31)*100 -> 0.31152648 | H78: =(H31-G31)/ABS(G31)*100 -> -9.21875 | I78: =(I31-H31)/ABS(H31)*100 -> -83.547926 | J78: =(J31-I31)/ABS(I31)*100 -> -138.65939 | K78: =(K31-J31)/ABS(J31)*100 -> 30.045722 | L78: =(L31-K31)/ABS(K31)*100 -> 20.961718 | M78: =(M31-L31)/ABS(L31)*100 -> 142.35086 | N78: =(N31-M31)/ABS(M31)*100 -> -228.87029 | ... P78: =(P31-O31)/ABS(O31)*100 -> 65.711335 | R78: =AVERAGEIF(E78:Q78,"<>0") -> -93.922689 | U78: {=_xlfn.STDEV.S(IF(E78:Q78<>0,E78:Q78))} -> 249.77472
C79: AWS (Global) | G79: =(G32-F32)/ABS(F32)*100 -> -23.920266 | H79: =(H32-G32)/ABS(G32)*100 -> 229.0393 | I79: =(I32-H32)/ABS(H32)*100 -> 106.23756 | J79: =(J32-I32)/ABS(I32)*100 -> 39.350064 | K79: =(K32-J32)/ABS(J32)*100 -> 68.45994 | L79: =(L32-K32)/ABS(K32)*100 -> 26.110197 | M79: =(M32-L32)/ABS(L32)*100 -> 47.060102 | N79: =(N32-M32)/ABS(M32)*100 -> 36.959574 | ... P79: =(P32-O32)/ABS(O32)*100 -> 7.8367847 | R79: =AVERAGEIF(E79:Q79,"<>0") -> 56.038493 | U79: {=_xlfn.STDEV.S(IF(E79:Q79<>0,E79:Q79))} -> 69.931812
C80: OPERATING INCOME GROWTH (%) | G80: =(G33-F33)/ABS(F33)*100 -> -76.107383 | H80: =(H33-G33)/ABS(G33)*100 -> 1154.4944 | I80: =(I33-H33)/ABS(H33)*100 -> 87.460815 | J80: =(J33-I33)/ABS(I33)*100 -> -1.9111323 | K80: =(K33-J33)/ABS(J33)*100 -> 202.50852 | L80: =(L33-K33)/ABS(K33)*100 -> 17.067869 | M80: =(M33-L33)/ABS(L33)*100 -> 57.478853 | N80: =(N33-M33)/ABS(M33)*100 -> 8.6466658 | ... P80: =(P33-O33)/ABS(O33)*100 -> 200.88178 | R80: =AVERAGEIF(E80:Q80,"<>0") -> 159.97506 | S80: =MEDIAN(E80:Q80) -> 37.273361 | U80: {=_xlfn.STDEV.S(IF(E80:Q80<>0,E80:Q80))} -> 361.78463
B84: P&L
B85: Revenue
C86: Net product sales | F86: 60903 | G86: 70080 | H86: 79268 | I86: 94665 | J86: 118573 | K86: 141915 | L86: 160408 | M86: 215915 | N86: 241787 | O86: 242901 | P86: 255887
C87: Net service sales | F87: 13549 | G87: 18908 | H87: 27738 | I87: 41322 | J87: 59293 | K87: 90972 | L87: 120114 | M87: 170149 | N87: 228035 | O87: 271082 | P87: 318898
F88: =SUM(F85:F87) -> 74452 | G88: =SUM(G85:G87) -> 88988 | H88: =SUM(H85:H87) -> 107006 | I88: =SUM(I85:I87) -> 135987 | J88: =SUM(J85:J87) -> 177866 | K88: =SUM(K85:K87) -> 232887 | L88: =SUM(L85:L87) -> 280522 | M88: =SUM(M85:M87) -> 386064 | ... P88: =SUM(P85:P87) -> 574785
B89: Cost of sales | F89: 54181 | G89: 62752 | H89: 71651 | I89: 88265 | J89: 111934 | K89: 139156 | L89: 165536 | M89: 233307 | N89: 272344 | O89: 288831 | P89: 304739
B90: Gross Profit | F90: =F88-F89 -> 20271 | G90: =G88-G89 -> 26236 | H90: =H88-H89 -> 35355 | I90: =I88-I89 -> 47722 | J90: =J88-J89 -> 65932 | K90: =K88-K89 -> 93731 | L90: =L88-L89 -> 114986 | M90: =M88-M89 -> 152757 | ... P90: =P88-P89 -> 270046
C91: GP margin (%) | F91: =IFERROR(F90/F88*100,0) -> 27.226938 | G91: =IFERROR(G90/G88*100,0) -> 29.482627 | H91: =IFERROR(H90/H88*100,0) -> 33.040203 | I91: =IFERROR(I90/I88*100,0) -> 35.09306 | J91: =IFERROR(J90/J88*100,0) -> 37.068355 | K91: =IFERROR(K90/K88*100,0) -> 40.247416 | L91: =IFERROR(L90/L88*100,0) -> 40.990011 | M91: =IFERROR(M90/M88*100,0) -> 39.567792 | ... P91: =IFERROR(P90/P88*100,0) -> 46.982089 | R91: =AVERAGE(E91:Q91) -> 37.776031
B93: Fulfillment | F93: 8585 | G93: 10766 | H93: 13410 | I93: 17619 | J93: 25249 | K93: 34027 | L93: 40232 | M93: 58517 | N93: 75111 | O93: 84299 | P93: 90619
B94: Technology & Infrastructure | F94: 3133 | G94: 4332 | H94: 5254 | I94: 7233 | J94: 22620 | K94: 28837 | L94: 35931 | M94: 42740 | N94: 56052 | O94: 73213 | P94: 85622
B95: Sales & marketing | F95: 6565 | G95: 9275 | H95: 12540 | I95: 16085 | J95: 10069 | K95: 13814 | L95: 18878 | M95: 22008 | N95: 32551 | O95: 42238 | P95: 44370
B96: General & administrative | F96: 1129 | G96: 1552 | H96: 1747 | I96: 2432 | J96: 3674 | K96: 4336 | L96: 5203 | M96: 6668 | N96: 8823 | O96: 11891 | P96: 11816
B97: Other operating expense / (income) | F97: 114 | G97: 133 | H97: 171 | I97: 167 | J97: 214 | K97: 296 | L97: 201 | M97: -75 | N97: 62 | O97: 1263 | P97: 767
B98: Total Cost & Expenses | F98: =SUM(F93:F97) -> 19526 | G98: =SUM(G93:G97) -> 26058 | H98: =SUM(H93:H97) -> 33122 | I98: =SUM(I93:I97) -> 43536 | J98: =SUM(J93:J97) -> 61826 | K98: =SUM(K93:K97) -> 81310 | L98: =SUM(L93:L97) -> 100445 | M98: =SUM(M93:M97) -> 129858 | ... P98: =SUM(P93:P97) -> 233194
B100: Operating Income | F100: =F90-F98 -> 745 | G100: =G90-G98 -> 178 | H100: =H90-H98 -> 2233 | I100: =I90-I98 -> 4186 | J100: =J90-J98 -> 4106 | K100: =K90-K98 -> 12421 | L100: =L90-L98 -> 14541 | M100: =M90-M98 -> 22899 | ... P100: =P90-P98 -> 36852
C101: Operating margin (%) | F101: =IFERROR(F100/F88*100,0) -> 1.0006447 | G101: =IFERROR(G100/G88*100,0) -> 0.20002697 | H101: =IFERROR(H100/H88*100,0) -> 2.0867989 | I101: =IFERROR(I100/I88*100,0) -> 3.0782354 | J101: =IFERROR(J100/J88*100,0) -> 2.3084794 | K101: =IFERROR(K100/K88*100,0) -> 5.3334879 | L101: =IFERROR(L100/L88*100,0) -> 5.1835507 | M101: =IFERROR(M100/M88*100,0) -> 5.9314 | ... P101: =IFERROR(P100/P88*100,0) -> 6.4114408 | R101: =AVERAGE(E101:Q101) -> 3.5647666
B103: Other Income / (expense), Net | F103: =38-141-136-71 -> -310 | G103: =39-210-118+37 -> -252 | H103: =50-459-256-22 -> -687 | I103: =100-484+90-96 -> -390 | J103: =202-848+346-4 -> -304 | K103: =440-1417-183+9 -> -1151 | L103: =832-1600+203-14 -> -579 | M103: =555-1647+2371+16 -> 1295 | N103: =448-1809+14633+4 -> 13276 | O103: =989-2367-16806-3 -> -18187 | P103: =2949-3182+938-12 -> 693 | R103: =AVERAGE(E103:Q103)/AVERAGE(E85:Q85)*100 -> #DIV/0!
B105: Income before taxation | F105: =F100+F103 -> 435 | G105: =G100+G103 -> -74 | H105: =H100+H103 -> 1546 | I105: =I100+I103 -> 3796 | J105: =J100+J103 -> 3802 | K105: =K100+K103 -> 11270 | L105: =L100+L103 -> 13962 | M105: =M100+M103 -> 24194 | ... P105: =P100+P103 -> 37545
B107: Income tax benefit / (provision) | F107: =-161 -> -161 | G107: -167 | H107: -950 | I107: -1425 | J107: -769 | K107: -1197 | L107: -2374 | M107: -2863 | N107: -4791 | O107: 3217 | P107: -7120 | R107: =AVERAGE(E107:Q107)/AVERAGE(E105:Q105)*100 -> -14.453113
B109: Net Income / (Loss) | F109: =F105+F107 -> 274 | G109: =G105+G107 -> -241 | H109: =H105+H107 -> 596 | I109: =I105+I107 -> 2371 | J109: =J105+J107 -> 3033 | K109: =K105+K107 -> 10073 | L109: =L105+L107 -> 11588 | M109: =M105+M107 -> 21331 | ... P109: =P105+P107 -> 30425
C110: Net income margin (%) | F110: =IFERROR(F109/F88*100,0) -> 0.36802235 | G110: =IFERROR(G109/G88*100,0) -> -0.27082303 | H110: =IFERROR(H109/H88*100,0) -> 0.55697811 | I110: =IFERROR(I109/I88*100,0) -> 1.743549 | J110: =IFERROR(J109/J88*100,0) -> 1.7052163 | K110: =IFERROR(K109/K88*100,0) -> 4.3252736 | L110: =IFERROR(L109/L88*100,0) -> 4.1308703 | M110: =IFERROR(M109/M88*100,0) -> 5.5252497 | ... P110: =IFERROR(P109/P88*100,0) -> 5.2932836 | R110: =AVERAGE(E110:Q110) -> 2.7226767
C114: Valuation Multiples / Shareholder ratios
C115: No. of Shares (Pre-Split) | F115: 483 | G115: 488 | H115: 494 | I115: 500 | J115: 507 | K115: 514 | L115: 521 | M115: 527 | N115: 10644 | O115: 10757 | P115: 10898
C116: No. of Shares (Splited) | F116: =F115*20 -> 9660 | G116: =G115*20 -> 9760 | H116: =H115*20 -> 9880 | I116: =I115*20 -> 10000 | J116: =J115*20 -> 10140 | K116: =K115*20 -> 10280 | L116: =L115*20 -> 10420 | M116: =M115*20 -> 10540 | N116: =N115*1 -> 10644 | O116: =O115*1 -> 10757 | P116: =P115*1 -> 10898
C117: Share Price | F117: 19.67 | G117: 15.52 | H117: 34.45 | I117: 37.49 | J117: 58.47 | K117: 73.9 | L117: 92.34 | M117: 164.29 | N117: 168.64 | O117: 84 | P117: 151.94 | T117: =((P117/F117)^(1/4)-1)*100 -> 66.71203
C118: EPS | F118: =IFERROR(F109/F116,0) -> 0.028364389 | G118: =IFERROR(G109/G116,0) -> -0.024692623 | H118: =IFERROR(H109/H116,0) -> 0.060323887 | I118: =IFERROR(I109/I116,0) -> 0.2371 | J118: =IFERROR(J109/J116,0) -> 0.29911243 | K118: =IFERROR(K109/K116,0) -> 0.97986381 | L118: =IFERROR(L109/L116,0) -> 1.1120921 | M118: =IFERROR(M109/M116,0) -> 2.023814 | ... P118: =IFERROR(P109/P116,0) -> 2.7917967
C119: P/E | F119: =IF(F117/F118>0,F117/F118,0) -> 693.47518 | G119: =IF(G117/G118>0,G117/G118,0) -> 0 | H119: =IF(H117/H118>0,H117/H118,0) -> 571.08389 | I119: =IF(I117/I118>0,I117/I118,0) -> 158.11894 | J119: =IF(J117/J118>0,J117/J118,0) -> 195.47834 | K119: =IF(K117/K118>0,K117/K118,0) -> 75.418644 | L119: =IF(L117/L118>0,L117/L118,0) -> 83.032689 | M119: =IF(M117/M118>0,M117/M118,0) -> 81.178407 | ... P119: =IF(P117/P118>0,P117/P118,0) -> 54.423734 | R119: =AVERAGE(E119:Q119) -> 178.72822 | U119: =_xlfn.STDEV.S(E119:Q119) -> 233.21776 | V119: =R119-U119 -> -54.48954
C120: Sales per share | F120: =F88/F116 -> 7.7072464 | G120: =G88/G116 -> 9.117623 | H120: =H88/H116 -> 10.830567 | I120: =I88/I116 -> 13.5987 | J120: =J88/J116 -> 17.541026 | K120: =K88/K116 -> 22.654377 | L120: =L88/L116 -> 26.921497 | M120: =M88/M116 -> 36.628463 | ... P120: =P88/P116 -> 52.742246
C121: Price / Sales | F121: =F117/F120 -> 2.5521437 | G121: =G117/G120 -> 1.702198 | H121: =H117/H120 -> 3.1808123 | I121: =I117/I120 -> 2.7568812 | J121: =J117/J120 -> 3.3333285 | K121: =K117/K120 -> 3.2620627 | L121: =L117/L120 -> 3.4299727 | M121: =M117/M120 -> 4.4853097 | ... P121: =P117/P120 -> 2.8808026 | R121: =AVERAGE(E121:Q121) -> 3.0147389 | U121: =_xlfn.STDEV.S(E121:Q121) -> 0.82311708 | V121: =R121-U121 -> 2.1916218
C123: Market Cap | F123: =F116*F117 -> 190012.2 | G123: =G116*G117 -> 151475.2 | H123: =H116*H117 -> 340366 | I123: =I116*I117 -> 374900 | J123: =J116*J117 -> 592885.8 | K123: =K116*K117 -> 759692 | L123: =L116*L117 -> 962182.8 | M123: =M116*M117 -> 1731616.6 | ... P123: =P116*P117 -> 1655842.1
C124: Enterprise Value (EV) MC+Debt-Cash | F124: =F123+F158-(F135+F136) -> 180756.2 | G124: =G123+G158-(G135+G136) -> 142324.2 | H124: =H123+H158-(H135+H136) -> 328785 | I124: =I123+I158-(I135+I136) -> 356613 | J124: =J123+J158-(J135+J136) -> 586642.8 | K124: =K123+K158-(K135+K136) -> 741937 | L124: =L123+L158-(L135+L136) -> 930575.8 | M124: =M123+M158-(M135+M136) -> 1679036.6 | ... P124: =P123+P158-(P135+P136) -> 1627376.1
...

Sheet Sharpe, Sortino
B3: AMZN Monthly Price Changes (5 years) | L3: United States 10-Year Bond Yield
B4: https://www.investing.com/equities/amazon-com-inc-historical-data | L4: https://www.investing.com/rates-bonds/u.s.-10-year-bond-yield-historical-data
B5: Jan'19 - Dec'23 | L5: Risk free rate average | O5: =[1]Sheet1!$E$6 -> 0.0246945 | S5: TEST (Manual calculation of Monthly Std Dev of Excess Returns - 5 Years)
F7: [1] | G7: [2] | H7: [1] - [2] | J7: [1] - [2] | S7: Sharpe | X7: Sortino
B8: Date | C8: Price | D8: Change % | F8: Change | G8: Monthly Risk free rate | H8: Monthly Excess returns | J8: Monthly Excess negative returns | S8: Average Monthly Excess Returns | U8: Difference Squared | V8: Monthly Std Dev of excess returns (σ) | X8: Average Monthly Excess Negative Returns | Y8: Difference Squared | Z8: Monthly Std Dev of excess returns (σ)
A9: 1 | B9: 45261 | C9: 151.94 | D9: 0.04 | F9: =D9 -> 0.04 | G9: =O$5/12 -> 0.002057875 | H9: =F9-G9 -> 0.037942125 | J9: =IF(H9<0,H9,"") | L9: Sharpe Ratio | O9: 1 Year | P9: 3 Years | Q9: 5 Years | S9: =AVERAGE(H9:H68) -> 0.014112125 | T9: 1 | U9: =(H9-S$9)^2 -> 0.0005678689 | V9: =(U70/T68)^(1/2) -> 0.094612146 | X9: =AVERAGE(J9:J68) -> -0.067606023 | Y9: =IF(J9="","",(J9-X$9)^2) | Z9: =(Y70/(COUNT(Y9:Y69)-1))^(1/2) -> 0.048378407
A10: 2 | B10: 45231 | C10: 146.09 | D10: 0.0977 | F10: =D10 -> 0.0977 | G10: =O$5/12 -> 0.002057875 | H10: =F10-G10 -> 0.095642125 | J10: =IF(H10<0,H10,"") | T10: 2 | U10: =(H10-S$9)^2 -> 0.0066471409 | Y10: =IF(J10="","",(J10-X$9)^2)
A11: 3 | B11: 45200 | C11: 133.09 | D11: 0.047 | F11: =D11 -> 0.047 | G11: =O$5/12 -> 0.002057875 | H11: =F11-G11 -> 0.044942125 | J11: =IF(H11<0,H11,"") | L11: Monthly Std Dev of excess returns (σ) | O11: =STDEV.P(H9:H20) -> 0.08294789 | P11: =STDEV.P(H9:H44) -> 0.099570071 | Q11: =STDEV.P(H9:H68) -> 0.094612146 | T11: 3 | U11: =(H11-S$9)^2 -> 0.0009504889 | Y11: =IF(J11="","",(J11-X$9)^2)
A12: 4 | B12: 45170 | C12: 127.12 | D12: -0.0789 | F12: =D12 -> -0.0789 | G12: =O$5/12 -> 0.002057875 | H12: =F12-G12 -> -0.080957875 | J12: =IF(H12<0,H12,"") -> -0.080957875 | L12: Monthly Portfolio return (Rp) | O12: =(1+O19)^(1/12)-1 -> 0.032818302 | P12: =(1+P19)^(1/12)-1 -> -0.0014884394 | Q12: =(1+Q19)^(1/12)-1 -> 0.0095425143 | T12: 4 | U12: =(H12-S$9)^2 -> 0.0090383049 | Y12: =IF(J12="","",(J12-X$9)^2) -> 0.00017827195
A13: 5 | B13: 45139 | C13: 138.01 | D13: 0.0324 | F13: =D13 -> 0.0324 | G13: =O$5/12 -> 0.002057875 | H13: =F13-G13 -> 0.030342125 | J13: =IF(H13<0,H13,"") | L13: Monthly Risk-free return - US 10Yr Yield (Rf) | O13: =O20/12 -> 0.002057875 | P13: =P20/12 -> 0.002057875 | Q13: =Q20/12 -> 0.002057875 | T13: 5 | U13: =(H13-S$9)^2 -> 0.0002634129 | Y13: =IF(J13="","",(J13-X$9)^2)
A14: 6 | B14: 45108 | C14: 133.68 | D14: 0.0255 | F14: =D14 -> 0.0255 | G14: =O$5/12 -> 0.002057875 | H14: =F14-G14 -> 0.023442125 | J14: =IF(H14<0,H14,"") | L14: Excess return (Rp - Rf) | O14: =O12-O13 -> 0.030760427 | P14: =P12-P13 -> -0.0035463144 | Q14: =Q12-Q13 -> 0.0074846393 | T14: 6 | U14: =(H14-S$9)^2 -> 8.70489e-05 | Y14: =IF(J14="","",(J14-X$9)^2)
A15: 7 | B15: 45078 | C15: 130.36 | D15: 0.0811 | F15: =D15 -> 0.0811 | G15: =O$5/12 -> 0.002057875 | H15: =F15-G15 -> 0.079042125 | J15: =IF(H15<0,H15,"") | T15: 7 | U15: =(H15-S$9)^2 -> 0.0042159049 | Y15: =IF(J15="","",(J15-X$9)^2)
A16: 8 | B16: 45047 | C16: 120.58 | D16: 0.1435 | F16: =D16 -> 0.1435 | G16: =O$5/12 -> 0.002057875 | H16: =F16-G16 -> 0.14144213 | J16: =IF(H16<0,H16,"") | L16: Monthly Sharpe Ratio ( [Rp - Rf] / σ ) | O16: =O14/O11 -> 0.37084038 | P16: =P14/P11 -> -0.035616268 | Q16: =Q14/Q11 -> 0.079108652 | T16: 8 | U16: =(H16-S$9)^2 -> 0.016212929 | Y16: =IF(J16="","",(J16-X$9)^2)
A17: 9 | B17: 45017 | C17: 105.45 | D17: 0.0209 | F17: =D17 -> 0.0209 | G17: =O$5/12 -> 0.002057875 | H17: =F17-G17 -> 0.018842125 | J17: =IF(H17<0,H17,"") | T17: 9 | U17: =(H17-S$9)^2 -> 2.23729e-05 | Y17: =IF(J17="","",(J17-X$9)^2)
A18: 10 | B18: 44986 | C18: 103.29 | D18: 0.0961 | F18: =D18 -> 0.0961 | G18: =O$5/12 -> 0.002057875 | H18: =F18-G18 -> 0.094042125 | J18: =IF(H18<0,H18,"") | L18: Annualized Std Dev of excess returns (σ) | O18: =O11*12^(1/2) -> 0.28733992 | P18: =P11*12^(1/2) -> 0.34492084 | Q18: =Q11*12^(1/2) -> 0.32774609 | T18: 10 | U18: =(H18-S$9)^2 -> 0.0063888049 | Y18: =IF(J18="","",(J18-X$9)^2)
A19: 11 | B19: 44958 | C19: 94.23 | D19: -0.0863 | F19: =D19 -> -0.0863 | G19: =O$5/12 -> 0.002057875 | H19: =F19-G19 -> -0.088357875 | J19: =IF(H19<0,H19,"") -> -0.088357875 | L19: Annualized Portfolio return (Rp) | O19: =($C$9/$C$20)^(1/($A$20/12))-1 -> 0.47328614 | P19: =($C$9/$C$44)^(1/($A$44/12))-1 -> -0.017715776 | Q19: =($C$9/$C$68)^(1/($A$68/12))-1 -> 0.12071544 | T19: 11 | U19: =(H19-S$9)^2 -> 0.010500101 | Y19: =IF(J19="","",(J19-X$9)^2) -> 0.00043063936
A20: 12 | B20: 44927 | C20: 103.13 | D20: 0.2277 | F20: =D20 -> 0.2277 | G20: =O$5/12 -> 0.002057875 | H20: =F20-G20 -> 0.22564212 | J20: =IF(H20<0,H20,"") | L20: Annualized Risk-free return - US 10Yr Yield (Rf) | O20: =$O$5 -> 0.0246945 | P20: =$O$5 -> 0.0246945 | Q20: =$O$5 -> 0.0246945 | T20: 12 | U20: =(H20-S$9)^2 -> 0.044744941 | Y20: =IF(J20="","",(J20-X$9)^2)
A21: 13 | B21: 44896 | C21: 84 | D21: -0.1299 | F21: =D21 -> -0.1299 | G21: =O$5/12 -> 0.002057875 | H21: =F21-G21 -> -0.13195788 | J21: =IF(H21<0,H21,"") -> -0.13195788 | L21: Excess return (Rp - Rf) | O21: =O19-O20 -> 0.44859164 | P21: =P19-P20 -> -0.042410276 | Q21: =Q19-Q20 -> 0.096020938 | T21: 13 | U21: =(H21-S$9)^2 -> 0.021336445 | Y21: =IF(J21="","",(J21-X$9)^2) -> 0.0041411608
A22: 14 | B22: 44866 | C22: 96.54 | D22: -0.0576 | F22: =D22 -> -0.0576 | G22: =O$5/12 -> 0.002057875 | H22: =F22-G22 -> -0.059657875 | J22: =IF(H22<0,H22,"") -> -0.059657875 | T22: 14 | U22: =(H22-S$9)^2 -> 0.0054420129 | Y22: =IF(J22="","",(J22-X$9)^2) -> 6.3173059e-05
A23: 15 | B23: 44835 | C23: 102.44 | D23: -0.0935 | F23: =D23 -> -0.0935 | G23: =O$5/12 -> 0.002057875 | H23: =F23-G23 -> -0.095557875 | J23: =IF(H23<0,H23,"") -> -0.095557875 | L23: Annualized Sharpe Ratio ( [Rp - Rf] / σ ) | O23: =O21/O18 -> 1.561188 | P23: =P21/P18 -> -0.12295655 | Q23: =Q21/Q18 -> 0.29297356 | T23: 15 | U23: =(H23-S$9)^2 -> 0.012027509 | Y23: =IF(J23="","",(J23-X$9)^2) -> 0.00078130602
A24: 16 | B24: 44805 | C24: 113 | D24: -0.1086 | F24: =D24 -> -0.1086 | G24: =O$5/12 -> 0.002057875 | H24: =F24-G24 -> -0.11065788 | J24: =IF(H24<0,H24,"") -> -0.11065788 | T24: 16 | U24: =(H24-S$9)^2 -> 0.015567553 | Y24: =IF(J24="","",(J24-X$9)^2) -> 0.0018534619
A25: 17 | B25: 44774 | C25: 126.77 | D25: -0.0606 | F25: =D25 -> -0.0606 | G25: =O$5/12 -> 0.002057875 | H25: =F25-G25 -> -0.062657875 | J25: =IF(H25<0,H25,"") -> -0.062657875 | T25: 17 | U25: =(H25-S$9)^2 -> 0.0058936329 | Y25: =IF(J25="","",(J25-X$9)^2) -> 2.448417e-05
A26: 18 | B26: 44743 | C26: 134.95 | D26: 0.2706 | F26: =D26 -> 0.2706 | G26: =O$5/12 -> 0.002057875 | H26: =F26-G26 -> 0.26854213 | J26: =IF(H26<0,H26,"") | L26: Sortino Ratio | O26: 1 Year | P26: 3 Years | Q26: 5 Years | T26: 18 | U26: =(H26-S$9)^2 -> 0.064734625 | Y26: =IF(J26="","",(J26-X$9)^2)
A27: 19 | B27: 44713 | C27: 106.21 | D27: -0.1165 | F27: =D27 -> -0.1165 | G27: =O$5/12 -> 0.002057875 | H27: =F27-G27 -> -0.11855787 | J27: =IF(H27<0,H27,"") -> -0.11855787 | T27: 19 | U27: =(H27-S$9)^2 -> 0.017601329 | Y27: =IF(J27="","",(J27-X$9)^2) -> 0.0025960912
A28: 20 | B28: 44682 | C28: 120.21 | D28: -0.0328 | F28: =D28 -> -0.0328 | G28: =O$5/12 -> 0.002057875 | H28: =F28-G28 -> -0.034857875 | J28: =IF(H28<0,H28,"") -> -0.034857875 | L28: Monthly Std Dev of excess negative returns (σd) | O28: =_xlfn.STDEV.S(J9:J20) -> 0.0052325902 | P28: =_xlfn.STDEV.S(J9:J44) -> 0.053979823 | Q28: =_xlfn.STDEV.S(J9:J68) -> 0.048378407 | T28: 20 | U28: =(H28-S$9)^2 -> 0.0023980609 | Y28: =IF(J28="","",(J28-X$9)^2) -> 0.0010724412
A29: 21 | B29: 44652 | C29: 124.28 | D29: -0.2375 | F29: =D29 -> -0.2375 | G29: =O$5/12 -> 0.002057875 | H29: =F29-G29 -> -0.23955788 | J29: =IF(H29<0,H29,"") -> -0.23955788 | L29: Monthly Portfolio return (Rp) | O29: =(1+O36)^(1/12)-1 -> 0.032818302 | P29: =(1+P36)^(1/12)-1 -> -0.0014884394 | Q29: =(1+Q36)^(1/12)-1 -> 0.0095425143 | T29: 21 | U29: =(H29-S$9)^2 -> 0.064348469 | Y29: =IF(J29="","",(J29-X$9)^2) -> 0.029567439
A30: 22 | B30: 44621 | C30: 163 | D30: 0.0614 | F30: =D30 -> 0.0614 | G30: =O$5/12 -> 0.002057875 | H30: =F30-G30 -> 0.059342125 | J30: =IF(H30<0,H30,"") | L30: Monthly Risk-free return - US 10Yr Yield (Rf) | O30: =O37/12 -> 0.002057875 | P30: =P37/12 -> 0.002057875 | Q30: =Q37/12 -> 0.002057875 | T30: 22 | U30: =(H30-S$9)^2 -> 0.0020457529 | Y30: =IF(J30="","",(J30-X$9)^2)
A31: 23 | B31: 44593 | C31: 153.56 | D31: 0.0267 | F31: =D31 -> 0.0267 | G31: =O$5/12 -> 0.002057875 | H31: =F31-G31 -> 0.024642125 | J31: =IF(H31<0,H31,"") | L31: Excess return (Rp - Rf) | O31: =O29-O30 -> 0.030760427 | P31: =P29-P30 -> -0.0035463144 | Q31: =Q29-Q30 -> 0.0074846393 | T31: 23 | U31: =(H31-S$9)^2 -> 0.0001108809 | Y31: =IF(J31="","",(J31-X$9)^2)
A32: 24 | B32: 44562 | C32: 149.57 | D32: -0.1028 | F32: =D32 -> -0.1028 | G32: =O$5/12 -> 0.002057875 | H32: =F32-G32 -> -0.10485788 | J32: =IF(H32<0,H32,"") -> -0.10485788 | T32: 24 | U32: =(H32-S$9)^2 -> 0.014153861 | Y32: =IF(J32="","",(J32-X$9)^2) -> 0.0013877005
A33: 25 | B33: 44531 | C33: 166.72 | D33: -0.0493 | F33: =D33 -> -0.0493 | G33: =O$5/12 -> 0.002057875 | H33: =F33-G33 -> -0.051357875 | J33: =IF(H33<0,H33,"") -> -0.051357875 | L33: Monthly Sortino Ratio ( [Rp - Rf] / σ ) | O33: =O31/O28 -> 5.8786234 | P33: =P31/P28 -> -0.065697035 | Q33: =Q31/Q28 -> 0.15471033 | T33: 25 | U33: =(H33-S$9)^2 -> 0.0042863209 | Y33: =IF(J33="","",(J33-X$9)^2) -> 0.00026400232
A34: 26 | B34: 44501 | C34: 175.35 | D34: 0.0399 | F34: =D34 -> 0.0399 | G34: =O$5/12 -> 0.002057875 | H34: =F34-G34 -> 0.037842125 | J34: =IF(H34<0,H34,"") | T34: 26 | U34: =(H34-S$9)^2 -> 0.0005631129 | Y34: =IF(J34="","",(J34-X$9)^2)
A35: 27 | B35: 44470 | C35: 168.62 | D35: 0.0266 | F35: =D35 -> 0.0266 | G35: =O$5/12 -> 0.002057875 | H35: =F35-G35 -> 0.024542125 | J35: =IF(H35<0,H35,"") | L35: Annualized Std Dev of excess negative returns (σ) | O35: =O28*12^(1/2) -> 0.018126224 | P35: =P28*12^(1/2) -> 0.18699159 | Q35: =Q28*12^(1/2) -> 0.16758772 | T35: 27 | U35: =(H35-S$9)^2 -> 0.0001087849 | Y35: =IF(J35="","",(J35-X$9)^2)
A36: 28 | B36: 44440 | C36: 164.25 | D36: -0.0535 | F36: =D36 -> -0.0535 | G36: =O$5/12 -> 0.002057875 | H36: =F36-G36 -> -0.055557875 | J36: =IF(H36<0,H36,"") -> -0.055557875 | L36: Annualized Portfolio return (Rp) | O36: =($C$9/$C$20)^(1/($A$20/12))-1 -> 0.47328614 | P36: =($C$9/$C$44)^(1/($A$44/12))-1 -> -0.017715776 | Q36: =($C$9/$C$68)^(1/($A$68/12))-1 -> 0.12071544 | T36: 28 | U36: =(H36-S$9)^2 -> 0.0048539089 | Y36: =IF(J36="","",(J36-X$9)^2) -> 0.00014515787
A37: 29 | B37: 44409 | C37: 173.54 | D37: 0.043 | F37: =D37 -> 0.043 | G37: =O$5/12 -> 0.002057875 | H37: =F37-G37 -> 0.040942125 | J37: =IF(H37<0,H37,"") | L37: Annualized Risk-free return - US 10Yr Yield (Rf) | O37: =$O$5 -> 0.0246945 | P37: =$O$5 -> 0.0246945 | Q37: =$O$5 -> 0.0246945 | T37: 29 | U37: =(H37-S$9)^2 -> 0.0007198489 | Y37: =IF(J37="","",(J37-X$9)^2)
A38: 30 | B38: 44378 | C38: 166.38 | D38: -0.0327 | F38: =D38 -> -0.0327 | G38: =O$5/12 -> 0.002057875 | H38: =F38-G38 -> -0.034757875 | J38: =IF(H38<0,H38,"") -> -0.034757875 | L38: Excess return (Rp - Rf) | O38: =O36-O37 -> 0.44859164 | P38: =P36-P37 -> -0.042410276 | Q38: =Q36-Q37 -> 0.096020938 | T38: 30 | U38: =(H38-S$9)^2 -> 0.0023882769 | Y38: =IF(J38="","",(J38-X$9)^2) -> 0.0010790008
A39: 31 | B39: 44348 | C39: 172.01 | D39: 0.0674 | F39: =D39 -> 0.0674 | G39: =O$5/12 -> 0.002057875 | H39: =F39-G39 -> 0.065342125 | J39: =IF(H39<0,H39,"") | T39: 31 | U39: =(H39-S$9)^2 -> 0.0026245129 | Y39: =IF(J39="","",(J39-X$9)^2)
A40: 32 | B40: 44317 | C40: 161.15 | D40: -0.0705 | F40: =D40 -> -0.0705 | G40: =O$5/12 -> 0.002057875 | H40: =F40-G40 -> -0.072557875 | J40: =IF(H40<0,H40,"") -> -0.072557875 | L40: Annualized Sortino Ratio ( [Rp - Rf] / σd ) | O40: =O38/O35 -> 24.748212 | P40: =P38/P35 -> -0.22680311 | Q40: =Q38/Q35 -> 0.57295928 | T40: 32 | U40: =(H40-S$9)^2 -> 0.0075116889 | Y40: =IF(J40="","",(J40-X$9)^2) -> 2.4520837e-05
A41: 33 | B41: 44287 | C41: 173.37 | D41: 0.1207 | F41: =D41 -> 0.1207 | G41: =O$5/12 -> 0.002057875 | H41: =F41-G41 -> 0.11864213 | J41: =IF(H41<0,H41,"") | T41: 33 | U41: =(H41-S$9)^2 -> 0.010926521 | Y41: =IF(J41="","",(J41-X$9)^2)
A42: 34 | B42: 44256 | C42: 154.7 | D42: 0.0004 | F42: =D42 -> 0.0004 | G42: =O$5/12 -> 0.002057875 | H42: =F42-G42 -> -0.001657875 | J42: =IF(H42<0,H42,"") -> -0.001657875 | T42: 34 | U42: =(H42-S$9)^2 -> 0.0002486929 | Y42: =IF(J42="","",(J42-X$9)^2) -> 0.0043491582
A43: 35 | B43: 44228 | C43: 154.65 | D43: -0.0353 | F43: =D43 -> -0.0353 | G43: =O$5/12 -> 0.002057875 | H43: =F43-G43 -> -0.037357875 | J43: =IF(H43<0,H43,"") -> -0.037357875 | T43: 35 | U43: =(H43-S$9)^2 -> 0.0026491609 | Y43: =IF(J43="","",(J43-X$9)^2) -> 0.00091495047
A44: 36 | B44: 44197 | C44: 160.31 | D44: -0.0156 | F44: =D44 -> -0.0156 | G44: =O$5/12 -> 0.002057875 | H44: =F44-G44 -> -0.017657875 | J44: =IF(H44<0,H44,"") -> -0.017657875 | T44: 36 | U44: =(H44-S$9)^2 -> 0.0010093329 | Y44: =IF(J44="","",(J44-X$9)^2) -> 0.0024948175
A45: 37 | B45: 44166 | C45: 162.85 | D45: 0.0281 | F45: =D45 -> 0.0281 | G45: =O$5/12 -> 0.002057875 | H45: =F45-G45 -> 0.026042125 | J45: =IF(H45<0,H45,"") | T45: 37 | U45: =(H45-S$9)^2 -> 0.0001423249 | Y45: =IF(J45="","",(J45-X$9)^2)
A46: 38 | B46: 44136 | C46: 158.4 | D46: 0.0434 | F46: =D46 -> 0.0434 | G46: =O$5/12 -> 0.002057875 | H46: =F46-G46 -> 0.041342125 | J46: =IF(H46<0,H46,"") | T46: 38 | U46: =(H46-S$9)^2 -> 0.0007414729 | Y46: =IF(J46="","",(J46-X$9)^2)
A47: 39 | B47: 44105 | C47: 151.81 | D47: -0.0358 | F47: =D47 -> -0.0358 | G47: =O$5/12 -> 0.002057875 | H47: =F47-G47 -> -0.037857875 | J47: =IF(H47<0,H47,"") -> -0.037857875 | T47: 39 | U47: =(H47-S$9)^2 -> 0.0027008809 | Y47: =IF(J47="","",(J47-X$9)^2) -> 0.00088495232
A48: 40 | B48: 44075 | C48: 157.44 | D48: -0.0876 | F48: =D48 -> -0.0876 | G48: =O$5/12 -> 0.002057875 | H48: =F48-G48 -> -0.089657875 | J48: =IF(H48<0,H48,"") -> -0.089657875 | T48: 40 | U48: =(H48-S$9)^2 -> 0.010768213 | Y48: =IF(J48="","",(J48-X$9)^2) -> 0.00048628417
A49: 41 | B49: 44044 | C49: 172.55 | D49: 0.0905 | F49: =D49 -> 0.0905 | G49: =O$5/12 -> 0.002057875 | H49: =F49-G49 -> 0.088442125 | J49: =IF(H49<0,H49,"") | T49: 41 | U49: =(H49-S$9)^2 -> 0.0055249489 | Y49: =IF(J49="","",(J49-X$9)^2)
A50: 42 | B50: 44013 | C50: 158.23 | D50: 0.1471 | F50: =D50 -> 0.1471 | G50: =O$5/12 -> 0.002057875 | H50: =F50-G50 -> 0.14504212 | J50: =IF(H50<0,H50,"") | T50: 42 | U50: =(H50-S$9)^2 -> 0.017142665 | Y50: =IF(J50="","",(J50-X$9)^2)
A51: 43 | B51: 43983 | C51: 137.94 | D51: 0.1296 | F51: =D51 -> 0.1296 | G51: =O$5/12 -> 0.002057875 | H51: =F51-G51 -> 0.12754213 | J51: =IF(H51<0,H51,"") | T51: 43 | U51: =(H51-S$9)^2 -> 0.012866365 | Y51: =IF(J51="","",(J51-X$9)^2)
A52: 44 | B52: 43952 | C52: 122.12 | D52: -0.0128 | F52: =D52 -> -0.0128 | G52: =O$5/12 -> 0.002057875 | H52: =F52-G52 -> -0.014857875 | J52: =IF(H52<0,H52,"") -> -0.014857875 | T52: 44 | U52: =(H52-S$9)^2 -> 0.0008392609 | Y52: =IF(J52="","",(J52-X$9)^2) -> 0.0027823671
... A68: 60 | B68: 43466 | C68: 85.94 | D68: 0.1443 | F68: =D68 -> 0.1443 | G68: =O$5/12 -> 0.002057875 | H68: =F68-G68 -> 0.14224212 | J68: =IF(H68<0,H68,"") | T68: 60 | U68: =(H68-S$9)^2 -> 0.016417297 | Y68: =IF(J68="","",(J68-X$9)^2)
U70: =SUM(U9:U69) -> 0.53708749 | Y70: =SUM(Y9:Y69) -> 0.060852227
