Workbook

Sheet Overall
B2: SUMMARY
H3: Share price | K3: Profit Margins | T3: Valuations Multiples | AC3: Solvency | AL3: Efficiency | AU3: Risk
H4: CAGR | K4: GPM | N4: OM | Q4: NPM | T4: PE | W4: EPS | Z4: Dividend Yield | AC4: Debt Ratio | AF4: Debt - Equity | AI4: Debt - Revenue | AL4: IT | AO4: RT | AR4: PT | AU4: Sharpe Ratio | AX4: Sortino Ratio
B5: Base year | D5: Y/E | E5: Updated As At | F5: MC | G5: Share price at Y/E | H5: Current | I5: 3 years | J5: 5 years | K5: Current | L5: 3 years | M5: 5 years | N5: Current | O5: 3 years | P5: 5 years | Q5: Current | R5: 3 years | S5: 5 years | T5: Current | U5: 3 years | V5: 5 years | W5: Current | X5: 3 years | Y5: 5 years | Z5: Current | AA5: 3 years | AB5: 5 years | AC5: Current | AD5: 3 years | AE5: 5 years | AF5: Current | AG5: 3 years | AH5: 5 years | AI5: Current | AJ5: 3 years | AK5: 5 years | AL5: Current | AM5: 3 years | AN5: 5 years | AO5: Current | AP5: 3 years | AQ5: 5 years | AR5: Current | AS5: 3 years | AT5: 5 years | AU5: Current | AV5: 3 years | AW5: 5 years | AX5: Current | AY5: 3 years | AZ5: 5 years
B6: 2023 | D6: 31/12 | E6: 2023 | F6: =OFFSET(FS!P85,0,E$6-B$6) -> 994857 | G6: =OFFSET(FS!P79,0,E$6-B$6) -> 390.14 | H6: =((OFFSET(FS!P79,0,E$6-B$6)/OFFSET(FS!P79,0,-1+E$6-B$6))^(1/1)-1)*100 -> 161.89166 | I6: =((OFFSET(FS!P79,0,E$6-B$6)/OFFSET(FS!P79,0,-2+E$6-B$6))^(1/3)-1)*100 -> 7.5899846 | J6: =((OFFSET(FS!P79,0,E$6-B$6)/OFFSET(FS!P79,0,-4+E$6-B$6))^(1/5)-1)*100 -> 14.080793 | K6: =OFFSET(FS!P55,0,0+E$6-B$6) -> 80.757142 | L6: =AVERAGE(OFFSET(FS!P55,0,-2+E$6-B$6):OFFSET(FS!P55,0,E$6-B$6)) -> 79.966272 | M6: =AVERAGE(OFFSET(FS!P55,0,-4+E$6-B$6):OFFSET(FS!P55,0,E$6-B$6)) -> 80.483722 | N6: =OFFSET(FS!P63,0,0+E$6-B$6) -> 34.655528 | O6: =AVERAGE(OFFSET(FS!P63,0,-2+E$6-B$6):OFFSET(FS!P63,0,E$6-B$6)) -> 33.04066 | P6: =AVERAGE(OFFSET(FS!P63,0,-4+E$6-B$6):OFFSET(FS!P63,0,E$6-B$6)) -> 34.210974 | Q6: =OFFSET(FS!P72,0,0+E$6-B$6) -> 28.982521 | R6: =AVERAGE(OFFSET(FS!P72,0,-2+E$6-B$6):OFFSET(FS!P72,0,E$6-B$6)) -> 27.420854 | S6: =AVERAGE(OFFSET(FS!P72,0,-4+E$6-B$6):OFFSET(FS!P72,0,E$6-B$6)) -> 28.462771 | T6: =OFFSET(FS!P81,0,0+E$6-B$6) -> 25.445215 | U6: =AVERAGE(OFFSET(FS!P81,0,-2+E$6-B$6):OFFSET(FS!P81,0,E$6-B$6)) -> 21.346556 | V6: =AVERAGE(OFFSET(FS!P81,0,-4+E$6-B$6):OFFSET(FS!P81,0,E$6-B$6)) -> 24.088675 | W6: =OFFSET(FS!P80,0,0+E$6-B$6) -> 15.332549 | X6: =AVERAGE(OFFSET(FS!P80,0,-2+E$6-B$6):OFFSET(FS!P80,0,E$6-B$6)) -> 12.857069 | Y6: =AVERAGE(OFFSET(FS!P80,0,-4+E$6-B$6):OFFSET(FS!P80,0,E$6-B$6)) -> 11.056576 | Z6: =OFFSET(FS!P91,0,0+E$6-B$6) -> 0 | AA6: =AVERAGE(OFFSET(FS!P91,0,-2+E$6-B$6):OFFSET(FS!P91,0,E$6-B$6)) -> 0 | AB6: =AVERAGE(OFFSET(FS!P91,0,-4+E$6-B$6):OFFSET(FS!P91,0,E$6-B$6)) -> 0 | AC6: =OFFSET(FS!P139,0,0+E$6-B$6) -> 0.33295881 | AD6: =AVERAGE(OFFSET(FS!P139,0,-2+E$6-B$6):OFFSET(FS!P139,0,E$6-B$6)) -> 0.30124898 | AE6: =AVERAGE(OFFSET(FS!P139,0,-4+E$6-B$6):OFFSET(FS!P139,0,E$6-B$6)) -> 0.26816589 | AF6: =OFFSET(FS!P140,0,0+E$6-B$6) -> 0.49915779 | AG6: =AVERAGE(OFFSET(FS!P140,0,-2+E$6-B$6):OFFSET(FS!P140,0,E$6-B$6)) -> 0.43524314 | AH6: =AVERAGE(OFFSET(FS!P140,0,-4+E$6-B$6):OFFSET(FS!P140,0,E$6-B$6)) -> 0.37348418 | AI6: =OFFSET(FS!P141,0,0+E$6-B$6) -> 0.56674475 | AJ6: =AVERAGE(OFFSET(FS!P141,0,-2+E$6-B$6):OFFSET(FS!P141,0,E$6-B$6)) -> 0.47666249 | AK6: =AVERAGE(OFFSET(FS!P141,0,-4+E$6-B$6):OFFSET(FS!P141,0,E$6-B$6)) -> 0.44961847 | AL6: =OFFSET(FS!P144,0,0+E$6-B$6) -> 0 | AM6: =AVERAGE(OFFSET(FS!P144,0,-2+E$6-B$6):OFFSET(FS!P144,0,E$6-B$6)) -> 0 | AN6: =AVERAGE(OFFSET(FS!P144,0,-4+E$6-B$6):OFFSET(FS!P144,0,E$6-B$6)) -> 0 | AO6: =OFFSET(FS!P145,0,0+E$6-B$6) -> 8.3432494 | AP6: =AVERAGE(OFFSET(FS!P145,0,-2+E$6-B$6):OFFSET(FS!P145,0,E$6-B$6)) -> 8.4676207 | AQ6: =AVERAGE(OFFSET(FS!P145,0,-4+E$6-B$6):OFFSET(FS!P145,0,E$6-B$6)) -> 8.0829219 | AR6: =OFFSET(FS!P146,0,0+E$6-B$6) -> 5.3534749 | AS6: =AVERAGE(OFFSET(FS!P146,0,-2+E$6-B$6):OFFSET(FS!P146,0,E$6-B$6)) -> 5.3201805 | AT6: =AVERAGE(OFFSET(FS!P146,0,-4+E$6-B$6):OFFSET(FS!P146,0,E$6-B$6)) -> 7.5741054 | AU6: ='Sharpe, Sortino'!O23 -> 4.6388042 | AV6: ='Sharpe, Sortino'!P23 -> 0.19257892 | AW6: ='Sharpe, Sortino'!Q23 -> 0.33712067 | AX6: ='Sharpe, Sortino'!O40 -> 5.3177986 | AY6: ='Sharpe, Sortino'!P40 -> 0.23695669 | AZ6: ='Sharpe, Sortino'!Q40 -> 0.45326146

Sheet FS
F1: < Figures are in millions >
F2: Y/E 31/12 | U2: Annualized
F3: 2013 | G3: 2014 | H3: 2015 | I3: 2016 | J3: 2017 | K3: 2018 | L3: 2019 | M3: 2020 | N3: 2021 | O3: 2022 | P3: 2023 | R3: Average | S3: Median | T3: CAGR | U3: Std Dev
B5: Revenue By Geography
C6: United States & Canada | F6: 3613 | G6: 5649 | H6: 8513 | I6: 13432 | J6: 19065 | K6: 25727 | L6: 32206 | M6: 38433 | N6: 51541 | O6: 50150 | P6: 52888
C7: Europe | F7: 4259 | G7: 6817 | H7: 9415 | I7: 6792 | J7: 10126 | K7: 13631 | L7: 16826 | M7: 20349 | N7: 29057 | O7: 26681 | P7: 31210
C8: Asia Pacific | I8: 5037 | J8: 7921 | K8: 11733 | L8: 15406 | M8: 19848 | N8: 26739 | O8: 27760 | P8: 36154
C9: Rest of World | I9: 2377 | J9: 3541 | K9: 4747 | L9: 6529 | M9: 7335 | N9: 10592 | O9: 12018 | P9: 14650
B10: Total Revenues | F10: =SUM(F6:F9) -> 7872 | G10: =SUM(G6:G9) -> 12466 | H10: =SUM(H6:H9) -> 17928 | I10: =SUM(I6:I9) -> 27638 | J10: =SUM(J6:J9) -> 40653 | K10: =SUM(K6:K9) -> 55838 | L10: =SUM(L6:L9) -> 70967 | M10: =SUM(M6:M9) -> 85965 | ... P10: =SUM(P6:P9) -> 134902
B12: Revenue by Segments
C13: Advertising | F13: 6986 | G13: 11492 | H13: 17079 | I13: 26885 | J13: 39942 | K13: 55013 | L13: 69655 | M13: 84169 | N13: 114934 | O13: 113642 | P13: 131948
C14: Others | F14: 886 | G14: 974 | H14: 849 | I14: 753 | J14: 711 | K14: 825 | L14: 541 | M14: 657 | N14: 721 | O14: 808 | P14: 1058
C15: Reality Labs | L15: 501 | M15: 1139 | N15: 2274 | O15: 2159 | P15: 1896
B16: Total Revenues | F16: =SUM(F13:F15) -> 7872 | G16: =SUM(G13:G15) -> 12466 | H16: =SUM(H13:H15) -> 17928 | I16: =SUM(I13:I15) -> 27638 | J16: =SUM(J13:J15) -> 40653 | K16: =SUM(K13:K15) -> 55838 | L16: =SUM(L13:L15) -> 70697 | M16: =SUM(M13:M15) -> 85965 | ... P16: =SUM(P13:P15) -> 134902
B18: Operating Income/(loss) Breakdown | F18: Undisclosed
C19: Advertising & Others ("Family of Apps") | L19: 28489 | M19: 39294 | N19: 59946 | O19: 42661 | P19: 62871
C20: Reality Labs | L20: -4503 | M20: -6623 | N20: -10193 | O20: -13717 | P20: -16120
B21: Total Operating Income | F21: =SUM(F19:F20) -> 0 | G21: =SUM(G19:G20) -> 0 | H21: =SUM(H19:H20) -> 0 | I21: =SUM(I19:I20) -> 0 | J21: =SUM(J19:J20) -> 0 | K21: =SUM(K19:K20) -> 0 | L21: =SUM(L19:L20) -> 23986 | M21: =SUM(M19:M20) -> 32671 | ... P21: =SUM(P19:P20) -> 46751
C24: Composition By Geography
C25: United States & Canada | F25: =F6/F$10*100 -> 45.89685 | G25: =G6/G$10*100 -> 45.315258 | H25: =H6/H$10*100 -> 47.484382 | I25: =I6/I$10*100 -> 48.599754 | J25: =J6/J$10*100 -> 46.896908 | K25: =K6/K$10*100 -> 46.074358 | L25: =L6/L$10*100 -> 45.381656 | M25: =M6/M$10*100 -> 44.70773 | ... P25: =P6/P$10*100 -> 39.204756 | R25: =AVERAGEIF(E25:Q25,"<>0") -> 45.115794
C26: Europe | I26: =I7/I$10*100 -> 24.574861 | J26: =J7/J$10*100 -> 24.908371 | K26: =K7/K$10*100 -> 24.411691 | L26: =L7/L$10*100 -> 23.709612 | M26: =M7/M$10*100 -> 23.671262 | N26: =N7/N$10*100 -> 24.639402 | O26: =O7/O$10*100 -> 22.880738 | P26: =P7/P$10*100 -> 23.135313 | R26: =AVERAGEIF(E26:Q26,"<>0") -> 23.991406
C27: Asia Pacific | I27: =I8/I$10*100 -> 18.224908 | J27: =J8/J$10*100 -> 19.484417 | K27: =K8/K$10*100 -> 21.012572 | L27: =L8/L$10*100 -> 21.708681 | M27: =M8/M$10*100 -> 23.088466 | N27: =N8/N$10*100 -> 22.673812 | O27: =O8/O$10*100 -> 23.806053 | P27: =P8/P$10*100 -> 26.800196 | R27: =AVERAGEIF(E27:Q27,"<>0") -> 22.099888
C28: Rest of World | I28: =I9/I$10*100 -> 8.6004776 | J28: =J9/J$10*100 -> 8.7103043 | K28: =K9/K$10*100 -> 8.501379 | L28: =L9/L$10*100 -> 9.2000507 | M28: =M9/M$10*100 -> 8.5325423 | N28: =N9/N$10*100 -> 8.9816754 | O28: =O9/O$10*100 -> 10.306237 | P28: =P9/P$10*100 -> 10.859735 | R28: =AVERAGEIF(E28:Q28,"<>0") -> 9.2115502
F29: =SUM(F25:F28) -> 45.89685 | G29: =SUM(G25:G28) -> 45.315258 | H29: =SUM(H25:H28) -> 47.484382 | I29: =SUM(I25:I28) -> 100 | J29: =SUM(J25:J28) -> 100 | K29: =SUM(K25:K28) -> 100 | L29: =SUM(L25:L28) -> 100 | M29: =SUM(M25:M28) -> 100 | ... P29: =SUM(P25:P28) -> 100
C31: Composition By Segments
C32: Advertising | F32: =F13/F$16*100 -> 88.744919 | G32: =G13/G$16*100 -> 92.186748 | H32: =H13/H$16*100 -> 95.264391 | I32: =I13/I$16*100 -> 97.27549 | J32: =J13/J$16*100 -> 98.251052 | K32: =K13/K$16*100 -> 98.522512 | L32: =L13/L$16*100 -> 98.526104 | M32: =M13/M$16*100 -> 97.910778 | ... P32: =P13/P$16*100 -> 97.810262 | R32: =AVERAGEIF(E32:Q32,"<>0") -> 96.309836
C33: Others | F33: =F14/F$16*100 -> 11.255081 | G33: =G14/G$16*100 -> 7.813252 | H33: =H14/H$16*100 -> 4.7356091 | I33: =I14/I$16*100 -> 2.7245097 | J33: =J14/J$16*100 -> 1.7489484 | K33: =K14/K$16*100 -> 1.4774884 | L33: =L14/L$16*100 -> 0.76523756 | M33: =M14/M$16*100 -> 0.76426453 | ... P33: =P14/P$16*100 -> 0.78427303 | R33: =AVERAGEIF(E33:Q33,"<>0") -> 3.0339057
C34: Reality Labs | L34: =L15/L$16*100 -> 0.70865808 | M34: =M15/M$16*100 -> 1.3249578 | N34: =N15/N$16*100 -> 1.9282789 | O34: =O15/O$16*100 -> 1.8514866 | P34: =P15/P$16*100 -> 1.4054647 | R34: =AVERAGEIF(E34:Q34,"<>0") -> 1.4437692
F35: =SUM(F32:F34) -> 100 | G35: =SUM(G32:G34) -> 100 | H35: =SUM(H32:H34) -> 100 | I35: =SUM(I32:I34) -> 100 | J35: =SUM(J32:J34) -> 100 | K35: =SUM(K32:K34) -> 100 | L35: =SUM(L32:L34) -> 100 | M35: =SUM(M32:M34) -> 100 | ... P35: =SUM(P32:P34) -> 100
C37: Revenue Growth by Segments (%)
C38: Advertising | G38: =(G13-F13)/ABS(F13)*100 -> 64.500429 | H38: =(H13-G13)/ABS(G13)*100 -> 48.616429 | I38: =(I13-H13)/ABS(H13)*100 -> 57.41554 | J38: =(J13-I13)/ABS(I13)*100 -> 48.566115 | K38: =(K13-J13)/ABS(J13)*100 -> 37.732212 | L38: =(L13-K13)/ABS(K13)*100 -> 26.615527 | M38: =(M13-L13)/ABS(L13)*100 -> 20.836982 | N38: =(N13-M13)/ABS(M13)*100 -> 36.551462 | ... P38: =(P13-O13)/ABS(O13)*100 -> 16.108481 | R38: =AVERAGEIF(E38:Q38,"<>0") -> 35.581905 | U38: {=_xlfn.STDEV.S(IF(E38:Q38<>0,E38:Q38))} -> 20.224838
C39: Others | G39: =(G14-F14)/ABS(F14)*100 -> 9.9322799 | H39: =(H14-G14)/ABS(G14)*100 -> -12.833676 | I39: =(I14-H14)/ABS(H14)*100 -> -11.30742 | J39: =(J14-I14)/ABS(I14)*100 -> -5.5776892 | K39: =(K14-J14)/ABS(J14)*100 -> 16.033755 | M39: =(M14-L14)/ABS(L14)*100 -> 21.441774 | N39: =(N14-M14)/ABS(M14)*100 -> 9.7412481 | O39: =(O14-N14)/ABS(N14)*100 -> 12.066574 | P39: =(P14-O14)/ABS(O14)*100 -> 30.940594 | R39: =AVERAGEIF(E39:Q39,"<>0") -> 7.8263823 | U39: {=_xlfn.STDEV.S(IF(E39:Q39<>0,E39:Q39))} -> 14.940285
C40: Reality Labs | M40: =(M15-L15)/ABS(L15)*100 -> 127.34531 | N40: =(N15-M15)/ABS(M15)*100 -> 99.648815 | O40: =(O15-N15)/ABS(N15)*100 -> -5.057168 | P40: =(P15-O15)/ABS(O15)*100 -> -12.181566 | R40: =AVERAGEIF(E40:Q40,"<>0") -> 52.438848 | U40: {=_xlfn.STDEV.S(IF(E40:Q40<>0,E40:Q40))} -> 71.46409
C41: TOTAL REVENUE GROWTH (%) | G41: =(G16-F16)/ABS(F16)*100 -> 58.35874 | H41: =(H16-G16)/ABS(G16)*100 -> 43.815177 | I41: =(I16-H16)/ABS(H16)*100 -> 54.161089 | J41: =(J16-I16)/ABS(I16)*100 -> 47.090962 | K41: =(K16-J16)/ABS(J16)*100 -> 37.352717 | L41: =(L16-K16)/ABS(K16)*100 -> 26.61091 | M41: =(M16-L16)/ABS(L16)*100 -> 21.59639 | N41: =(N16-M16)/ABS(M16)*100 -> 37.182574 | ... P41: =(P16-O16)/ABS(O16)*100 -> 15.687468 | R41: =AVERAGEIF(E41:Q41,"<>0") -> 34.073671 | S41: =MEDIAN(E41:Q41) -> 37.267646 | U41: {=_xlfn.STDEV.S(IF(E41:Q41<>0,E41:Q41))} -> 18.45718 | V41: =R41-U41 -> 15.616491
C44: Operating Income Growth (%)
C45: Advertising | M45: =(M19-L19)/ABS(L19)*100 -> 37.926919 | N45: =(N19-M19)/ABS(M19)*100 -> 52.557642 | O45: =(O19-N19)/ABS(N19)*100 -> -28.834284 | P45: =(P19-O19)/ABS(O19)*100 -> 47.373479 | R45: =AVERAGEIF(E45:Q45,"<>0") -> 27.255939 | U45: {=_xlfn.STDEV.S(IF(E45:Q45<>0,E45:Q45))} -> 37.880842
C46: Reality Labs | M46: =(M20-L20)/ABS(L20)*100 -> -47.079725 | N46: =(N20-M20)/ABS(M20)*100 -> -53.903065 | O46: =(O20-N20)/ABS(N20)*100 -> -34.572746 | P46: =(P20-O20)/ABS(O20)*100 -> -17.518408 | R46: =AVERAGEIF(E46:Q46,"<>0") -> -38.268486 | U46: {=_xlfn.STDEV.S(IF(E46:Q46<>0,E46:Q46))} -> 15.982305
C47: OPERATING INCOME GROWTH (%) | M47: =(M21-L21)/ABS(L21)*100 -> 36.208622 | N47: =(N21-M21)/ABS(M21)*100 -> 52.284901 | O47: =(O21-N21)/ABS(N21)*100 -> -41.824614 | P47: =(P21-O21)/ABS(O21)*100 -> 61.52225 | R47: =AVERAGEIF(E47:Q47,"<>0") -> 27.04779 | S47: =MEDIAN(E47:Q47) -> 44.246761 | U47: {=_xlfn.STDEV.S(IF(E47:Q47<>0,E47:Q47))} -> 47.091149
B51: P&L
B52: Revenue | F52: 7872 | G52: 12466 | H52: 17928 | I52: 27638 | J52: 40653 | K52: 55838 | L52: 70697 | M52: 85965 | N52: 117929 | O52: 116609 | P52: 134902
B53: Cost of Revenue | F53: 1875 | G53: 2153 | H53: 2867 | I53: 3789 | J53: 5454 | K53: 9355 | L53: 12770 | M53: 16692 | N53: 22649 | O53: 25249 | P53: 25959
B54: Gross Profit | F54: =F52-F53 -> 5997 | G54: =G52-G53 -> 10313 | H54: =H52-H53 -> 15061 | I54: =I52-I53 -> 23849 | J54: =J52-J53 -> 35199 | K54: =K52-K53 -> 46483 | L54: =L52-L53 -> 57927 | M54: =M52-M53 -> 69273 | ... P54: =P52-P53 -> 108943
C55: GP margin (%) | F55: =IFERROR(F54/F52*100,0) -> 76.181402 | G55: =IFERROR(G54/G52*100,0) -> 82.729023 | H55: =IFERROR(H54/H52*100,0) -> 84.008255 | I55: =IFERROR(I54/I52*100,0) -> 86.290614 | J55: =IFERROR(J54/J52*100,0) -> 86.584016 | K55: =IFERROR(K54/K52*100,0) -> 83.246176 | L55: =IFERROR(L54/L52*100,0) -> 81.936999 | M55: =IFERROR(M54/M52*100,0) -> 80.582795 | ... P55: =IFERROR(P54/P52*100,0) -> 80.757142 | R55: =AVERAGE(E55:Q55) -> 81.950736
B57: Research & Development | F57: 1415 | G57: 2666 | H57: 4816 | I57: 5919 | J57: 7754 | K57: 10273 | L57: 13600 | M57: 18447 | N57: 24655 | O57: 35338 | P57: 38483 | R57: =AVERAGE(E57:Q57)/AVERAGE($E$52:$Q$52)*100 -> 23.727917
B58: Marketing and Sales | F58: 997 | G58: 1680 | H58: 2725 | I58: 3772 | J58: 4725 | K58: 7846 | L58: 9876 | M58: 11591 | N58: 14043 | O58: 15262 | P58: 12301 | R58: =AVERAGE(E58:Q58)/AVERAGE($E$52:$Q$52)*100 -> 12.319298
B59: Genral and Administrative | F59: 781 | G59: 973 | H59: 1295 | I59: 1731 | J59: 2517 | K59: 3451 | L59: 10465 | M59: 6564 | N59: 9829 | O59: 11816 | P59: 11408
B60: Total Cost & Expenses | F60: =SUM(F57:F59) -> 3193 | G60: =SUM(G57:G59) -> 5319 | H60: =SUM(H57:H59) -> 8836 | I60: =SUM(I57:I59) -> 11422 | J60: =SUM(J57:J59) -> 14996 | K60: =SUM(K57:K59) -> 21570 | L60: =SUM(L57:L59) -> 33941 | M60: =SUM(M57:M59) -> 36602 | ... P60: =SUM(P57:P59) -> 62192
B62: Operating Income | F62: =F54-F60 -> 2804 | G62: =G54-G60 -> 4994 | H62: =H54-H60 -> 6225 | I62: =I54-I60 -> 12427 | J62: =J54-J60 -> 20203 | K62: =K54-K60 -> 24913 | L62: =L54-L60 -> 23986 | M62: =M54-M60 -> 32671 | ... P62: =P54-P60 -> 46751
C63: Operating margin (%) | F63: =IFERROR(F62/F52*100,0) -> 35.619919 | G63: =IFERROR(G62/G52*100,0) -> 40.060966 | H63: =IFERROR(H62/H52*100,0) -> 34.722222 | I63: =IFERROR(I62/I52*100,0) -> 44.963456 | J63: =IFERROR(J62/J52*100,0) -> 49.696209 | K63: =IFERROR(K62/K52*100,0) -> 44.616569 | L63: =IFERROR(L62/L52*100,0) -> 33.927889 | M63: =IFERROR(M62/M52*100,0) -> 38.005002 | ... P63: =IFERROR(P62/P52*100,0) -> 34.655528 | R63: =AVERAGE(E63:Q63) -> 38.248565
B65: Other Income / (expense), Net | F65: -50 | G65: -84 | H65: -31 | I65: 91 | J65: 391 | K65: =448 -> 448 | L65: 826 | M65: 509 | N65: 531 | O65: -125 | P65: 677 | R65: =AVERAGE(E65:Q65)/AVERAGE(E52:Q52)*100 -> 0.46231138
B67: Income before provision for income taxes | F67: =F62+F65 -> 2754 | G67: =G62+G65 -> 4910 | H67: =H62+H65 -> 6194 | I67: =I62+I65 -> 12518 | J67: =J62+J65 -> 20594 | K67: =K62+K65 -> 25361 | L67: =L62+L65 -> 24812 | M67: =M62+M65 -> 33180 | ... P67: =P62+P65 -> 47428
B69: Provision for income taxes | F69: 1254 | G69: 1970 | H69: 2506 | I69: 2301 | J69: 4660 | K69: 3249 | L69: 6327 | M69: 4034 | N69: 7914 | O69: 5619 | P69: 8330 | R69: =AVERAGE(E69:Q69)/AVERAGE(E67:Q67)*100 -> 18.973111
B71: Net Income | F71: =F67-F69 -> 1500 | G71: =G67-G69 -> 2940 | H71: =H67-H69 -> 3688 | I71: =I67-I69 -> 10217 | J71: =J67-J69 -> 15934 | K71: =K67-K69 -> 22112 | L71: =L67-L69 -> 18485 | M71: =M67-M69 -> 29146 | ... P71: =P67-P69 -> 39098
C72: Net income margin (%) | F72: =IFERROR(F71/F52*100,0) -> 19.054878 | G72: =IFERROR(G71/G52*100,0) -> 23.584149 | H72: =IFERROR(H71/H52*100,0) -> 20.571174 | I72: =IFERROR(I71/I52*100,0) -> 36.967219 | J72: =IFERROR(J71/J52*100,0) -> 39.195139 | K72: =IFERROR(K71/K52*100,0) -> 39.600272 | L72: =IFERROR(L71/L52*100,0) -> 26.146795 | M72: =IFERROR(M71/M52*100,0) -> 33.904496 | ... P72: =IFERROR(P71/P52*100,0) -> 28.982521 | R72: =AVERAGE(E72:Q72) -> 29.207881
C76: Valuation Multiples / Shareholder ratios
C77: No. of Shares (Pre-Split) | F77: =1970+577 -> 2547 | G77: =2234+563 -> 2797 | H77: =2293+552 -> 2845 | I77: =2354+538 -> 2892 | J77: =2397+509 -> 2906 | K77: =2385+469 -> 2854 | L77: =2407+445 -> 2852 | M77: =2406+443 -> 2849 | N77: =2328+413 -> 2741 | O77: =2247+367 -> 2614 | P77: =2200+350 -> 2550
C78: No. of Shares (Splited) | F78: =F77 -> 2547 | G78: =G77 -> 2797 | H78: =H77 -> 2845 | I78: =I77 -> 2892 | J78: =J77 -> 2906 | K78: =K77 -> 2854 | L78: =L77 -> 2852 | M78: =M77 -> 2849 | ... P78: =P77 -> 2550
C79: Share Price | F79: 62.57 | G79: 75.91 | H79: 112.21 | I79: 130.32 | J79: 186.89 | K79: 166.69 | L79: 201.91 | M79: 258.33 | N79: 313.26 | O79: 148.97 | P79: 390.14 | T79: =((P79/F79)^(1/4)-1)*100 -> 58.020554
C80: EPS | F80: =IFERROR(F71/F78,0) -> 0.58892815 | G80: =IFERROR(G71/G78,0) -> 1.0511262 | H80: =IFERROR(H71/H78,0) -> 1.2963093 | I80: =IFERROR(I71/I78,0) -> 3.5328492 | J80: =IFERROR(J71/J78,0) -> 5.4831383 | K80: =IFERROR(K71/K78,0) -> 7.7477225 | L80: =IFERROR(L71/L78,0) -> 6.4814165 | M80: =IFERROR(M71/M78,0) -> 10.230256 | ... P80: =IFERROR(P71/P78,0) -> 15.332549
C81: P/E | F81: =F79/F80 -> 106.24386 | G81: =G79/G80 -> 72.217779 | H81: =H79/H80 -> 86.561131 | I81: =I79/I80 -> 36.888073 | J81: =J79/J80 -> 34.084495 | K81: =K79/K80 -> 21.51471 | L81: =L79/L80 -> 31.152141 | M81: =M79/M80 -> 25.251567 | ... P81: =P79/P80 -> 25.445215 | R81: =AVERAGE(E81:Q81) -> 43.450311 | U81: =_xlfn.STDEV.S(E81:Q81) -> 30.376113 | V81: =R81-U81 -> 13.074199
C82: Sales per share | F82: =F52/F78 -> 3.0906949 | G82: =G52/G78 -> 4.4569181 | H82: =H52/H78 -> 6.3015817 | I82: =I52/I78 -> 9.5567082 | J82: =J52/J78 -> 13.989332 | K82: =K52/K78 -> 19.564821 | L82: =L52/L78 -> 24.788569 | M82: =M52/M78 -> 30.173745 | ... P82: =P52/P78 -> 52.902745
C83: Price / Sales | F83: =F79/F82 -> 20.244638 | G83: =G79/G82 -> 17.031948 | H83: =H79/H82 -> 17.80664 | I83: =I79/I82 -> 13.636495 | J83: =J79/J82 -> 13.359465 | K83: =K79/K82 -> 8.5198836 | L83: =L79/L82 -> 8.1452865 | M83: =M79/M82 -> 8.5614165 | ... P83: =P79/P82 -> 7.3746646 | R83: =AVERAGE(E83:Q83) -> 11.390992 | U83: =_xlfn.STDEV.S(E83:Q83) -> 5.3377876 | V83: =R83-U83 -> 6.0532039
C85: Market Cap | F85: =F78*F79 -> 159365.79 | G85: =G78*G79 -> 212320.27 | H85: =H78*H79 -> 319237.45 | I85: =I78*I79 -> 376885.44 | J85: =J78*J79 -> 543102.34 | K85: =K78*K79 -> 475733.26 | L85: =L78*L79 -> 575847.32 | M85: =M78*M79 -> 735982.17 | ... P85: =P78*P79 -> 994857
C86: Enterprise Value (EV) MC+Debt-Cash | F86: =F85+F123-(F97+F98+F104) -> 147916.79 | G86: =G85+G123-(G97+G98+G104) -> 201121.27 | H86: =H85+H123-(H97+H98+H104) -> 300803.45 | I86: =I85+I123-(I97+I98+I104) -> 347436.44 | J86: =J85+J123-(J97+J98+J104) -> 501391.34 | K86: =K85+K123-(K97+K98+K104) -> 434619.26 | L86: =L85+L123-(L97+L98+L104) -> 520906.32 | M86: =M85+M123-(M97+M98+M104) -> 667794.17 | ... P86: =P85+P123-(P97+P98+P104) -> 941698
C87: EV / EBITDA | F87: =F86/(F152+F153+F69) -> 39.287328 | G87: =G86/(G152+G153+G69) -> 32.686701 | H87: =H86/(H152+H153+H69) -> 36.958281 | I87: =I86/(I152+I153+I69) -> 23.380649 | J87: =J86/(J152+J153+J69) -> 21.228305 | K87: =K86/(K152+K153+K69) -> 14.64548 | L87: =L86/(L152+L153+L69) -> 17.049269 | M87: =M86/(M152+M153+M69) -> 16.677343 | ... P87: =P86/(P152+P153+P69) -> 16.068287 | R87: =AVERAGE(E87:Q87) -> 21.993361
C88: EV / Revenue | F88: =F86/F52 -> 18.790243 | G88: =G86/G52 -> 16.133585 | H88: =H86/H52 -> 16.778416 | I88: =I86/I52 -> 12.570969 | J88: =J86/J52 -> 12.33344 | K88: =K86/K52 -> 7.783575 | L88: =L86/L52 -> 7.3681531 | M88: =M86/M52 -> 7.76821 | ... P88: =P86/P52 -> 6.9806081 | R88: =AVERAGE(E88:Q88) -> 10.576889
C90: Dividend / Share | F90: =ABS(F177/F78) -> 0 | G90: =ABS(G177/G78) -> 0 | H90: =ABS(H177/H78) -> 0 | I90: =ABS(I177/I78) -> 0 | J90: =ABS(J177/J78) -> 0 | K90: =ABS(K177/K78) -> 0 | L90: =ABS(L177/L78) -> 0 | M90: =ABS(M177/M78) -> 0 | ... P90: =ABS(P177/P78) -> 0 | R90: =AVERAGE(E90:Q90) -> 0 | S90: =MEDIAN(E90:Q90) -> 0
C91: Dividend yield | F91: =F90/F79 -> 0 | G91: =G90/G79 -> 0 | H91: =H90/H79 -> 0 | I91: =I90/I79 -> 0 | J91: =J90/J79 -> 0 | K91: =K90/K79 -> 0 | L91: =L90/L79 -> 0 | M91: =M90/M79 -> 0 | ... P91: =P90/P79 -> 0 | R91: =AVERAGE(E91:Q91) -> 0 | S91: =MEDIAN(E91:Q91) -> 0
B95: Balance Sheet
B96: Current Assets
C97: Cash & Cash Equivalents | F97: 3323 | G97: 4315 | H97: 4907 | I97: 8903 | J97: 8079 | K97: 10019 | L97: 19079 | M97: 17576 | N97: 16601 | O97: 14681 | P97: 41862
C98: Marketable Securities | F98: 8126 | G98: 6884 | H98: 13527 | I98: 20546 | J98: 33632 | K98: 31095 | L98: 35776 | M98: 44378 | N98: 31397 | O98: 26057 | P98: 23541
C99: Accounts Receivables | F99: 1109 | G99: 1678 | H99: 2559 | I99: 3993 | J99: 5832 | K99: 7587 | L99: 9518 | M99: 11335 | N99: 14039 | O99: 13466 | P99: 16169
C100: Prepayments & other current assets | F100: 512 | G100: 513 | H100: 659 | I100: 959 | J100: 1020 | K100: 1779 | L100: 1852 | M100: 2381 | N100: 4629 | O100: 5345 | P100: 3793
B101: Total Current Assets | F101: =SUM(F97:F100) -> 13070 | G101: =SUM(G97:G100) -> 13390 | H101: =SUM(H97:H100) -> 21652 | I101: =SUM(I97:I100) -> 34401 | J101: =SUM(J97:J100) -> 48563 | K101: =SUM(K97:K100) -> 50480 | L101: =SUM(L97:L100) -> 66225 | M101: =SUM(M97:M100) -> 75670 | ... P101: =SUM(P97:P100) -> 85365
B103: Non-Current Assets
C104: Non-Marketable Securities | F104: 0 | G104: 0 | H104: 0 | I104: 0 | J104: 0 | K104: 0 | L104: 86 | M104: 6234 | N104: 6775 | O104: 6201 | P104: 6141
C105: Property & Equipment | F105: 2882 | G105: 3967 | H105: 5687 | I105: 8591 | J105: 13721 | K105: 24683 | L105: 35323 | M105: 45633 | N105: 57809 | O105: 79518 | P105: 96587
C106: Operating Lease Assets | F106: 0 | G106: 0 | H106: 0 | I106: 0 | J106: 0 | K106: 0 | L106: 9460 | M106: 9348 | N106: 12155 | O106: 12673 | P106: 13294
C107: Intangible Assets, net | F107: 883 | G107: 3929 | H107: 3246 | I107: 2535 | J107: 1884 | K107: 1294 | L107: 894 | M107: 623 | N107: 634 | O107: 897 | P107: 788
C108: Goodwill | F108: 839 | G108: 17981 | H108: 18026 | I108: 18122 | J108: 18221 | K108: 18301 | L108: 18715 | M108: 19050 | N108: 19197 | O108: 20306 | P108: 20654
C109: Other Non-Current Assets | F109: 221 | G109: 699 | H109: 796 | I109: 1312 | J109: 2135 | K109: 2576 | L109: 2673 | M109: 2758 | N109: 2751 | O109: 6583 | P109: 6794
B110: Total Non-Current Assets | F110: =SUM(F104:F109) -> 4825 | G110: =SUM(G104:G109) -> 26576 | H110: =SUM(H104:H109) -> 27755 | I110: =SUM(I104:I109) -> 30560 | J110: =SUM(J104:J109) -> 35961 | K110: =SUM(K104:K109) -> 46854 | L110: =SUM(L104:L109) -> 67151 | M110: =SUM(M104:M109) -> 83646 | ... P110: =SUM(P104:P109) -> 144258
B112: Total Assets | F112: =F101+F110 -> 17895 | G112: =G101+G110 -> 39966 | H112: =H101+H110 -> 49407 | I112: =I101+I110 -> 64961 | J112: =J101+J110 -> 84524 | K112: =K101+K110 -> 97334 | L112: =L101+L110 -> 133376 | M112: =M101+M110 -> 159316 | ... P112: =P101+P110 -> 229623
B114: Current Liabilities
C115: Accounts Payable | F115: 87 | G115: 176 | H115: 196 | I115: 302 | J115: 380 | K115: 820 | L115: 1363 | M115: 1331 | N115: 4083 | O115: 4990 | P115: 4849
C116: Partners payable | F116: 181 | G116: 202 | H116: 217 | I116: 280 | J116: 390 | K116: 541 | L116: 886 | M116: 1093 | N116: 1052 | O116: 1117 | P116: 863
C117: Operating Lease Liabilities | F117: 0 | G117: 0 | H117: 0 | I117: 0 | J117: 0 | K117: 0 | L117: 800 | M117: 1023 | N117: 1127 | O117: 1367 | P117: 1623
C118: Accrued and other current liabilities | F118: =555+38+239 -> 832 | G118: =866+66+114 -> 1046 | H118: =1449+56+7 -> 1512 | I118: =2203+90 -> 2293 | J118: =2892+98 -> 2990 | K118: =5509+147 -> 5656 | L118: =11735+269 -> 12004 | M118: =11152+382 -> 11534 | N118: 14873 | O118: 19552 | P118: 24625
B119: Total Current Liabilities | F119: =SUM(F115:F118) -> 1100 | G119: =SUM(G115:G118) -> 1424 | H119: =SUM(H115:H118) -> 1925 | I119: =SUM(I115:I118) -> 2875 | J119: =SUM(J115:J118) -> 3760 | K119: =SUM(K115:K118) -> 7017 | L119: =SUM(L115:L118) -> 15053 | M119: =SUM(M115:M118) -> 14981 | ... P119: =SUM(P115:P118) -> 31960
B121: Non-Current Liabilities
C122: Operating Lease Liabilities | F122: 0 | G122: 0 | H122: 0 | I122: 0 | J122: 0 | K122: 0 | L122: 9524 | M122: 9631 | N122: 12746 | O122: 15301 | P122: 17226
C123: Long-Term Debt | F123: 0 | G123: 0 | H123: 0 | I123: 0 | J123: 0 | K123: 0 | L123: 0 | M123: 0 | N123: 0 | O123: 9923 | P123: 18385
C124: Other long-term liabilities | F124: =237+1088 -> 1325 | G124: =119+2327 -> 2446 | H124: =107+3157 -> 3264 | I124: 2892 | J124: 6417 | K124: 6190 | L124: 7745 | M124: 6414 | N124: 7227 | O124: 7764 | P124: 8884
B125: Total Non-Current Liabilities | F125: =SUM(F122:F124) -> 1325 | G125: =SUM(G122:G124) -> 2446 | H125: =SUM(H122:H124) -> 3264 | I125: =SUM(I122:I124) -> 2892 | J125: =SUM(J122:J124) -> 6417 | K125: =SUM(K122:K124) -> 6190 | L125: =SUM(L122:L124) -> 17269 | M125: =SUM(M122:M124) -> 16045 | ... P125: =SUM(P122:P124) -> 44495
B127: Total Liabilities | F127: =F119+F125 -> 2425 | G127: =G119+G125 -> 3870 | H127: =H119+H125 -> 5189 | I127: =I119+I125 -> 5767 | J127: =J119+J125 -> 10177 | K127: =K119+K125 -> 13207 | L127: =L119+L125 -> 32322 | M127: =M119+M125 -> 31026 | ... P127: =P119+P125 -> 76455
B129: Equity
C130: Share Capital | F130: 0 | G130: 0 | H130: 0 | I130: 0 | J130: 0 | K130: 0 | L130: 0 | M130: 0 | N130: 0 | O130: 0 | P130: 0
C131: Additional paid-in capital (share premium) | F131: 12297 | G131: 30225 | H131: 34886 | I131: 38227 | J131: 40584 | K131: 42906 | L131: 45851 | M131: 50018 | N131: 55811 | O131: 64444 | P131: 73253
C132: Accumulated other comprehensive income / (loss) | F132: 14 | G132: -228 | H132: -455 | I132: -703 | J132: -227 | K132: -760 | L132: -489 | M132: 927 | N132: -693 | O132: -3530 | P132: -2155
...

Sheet Sharpe, Sortino
B3: META Monthly Price Changes (5 years) | L3: United States 10-Year Bond Yield
B4: https://www.investing.com/equities/nvidia-corp-historical-data | L4: https://www.investing.com/rates-bonds/u.s.-10-year-bond-yield-historical-data
B5: Jan'19 - Dec'23 | L5: Risk free rate average | O5: =[1]Sheet1!$E$6 -> 0.0246945 | S5: TEST (Manual calculation of Monthly Std Dev of Excess Returns - 5 Years)
F7: [1] | G7: [2] | H7: [1] - [2] | J7: [1] - [2] | S7: Sharpe | X7: Sortino
B8: Date | C8: Price | D8: Change % | F8: Change | G8: Monthly Risk free rate | H8: Monthly Excess returns | J8: Monthly Excess negative returns | S8: Average Monthly Excess Returns | U8: Difference Squared | V8: Monthly Std Dev of excess returns (σ) | X8: Average Monthly Excess Negative Returns | Y8: Difference Squared | Z8: Monthly Std Dev of excess returns (σ)
A9: 1 | B9: 45261 | C9: 353.96 | D9: 0.082 | F9: =D9 -> 0.082 | G9: =O$5/12 -> 0.002057875 | H9: =F9-G9 -> 0.079942125 | J9: =IF(H9<0,H9,"") | L9: Sharpe Ratio | O9: 1 Year | P9: 3 Years | Q9: 5 Years | S9: =AVERAGE(H9:H68) -> 0.021845458 | T9: 1 | U9: =(H9-S$9)^2 -> 0.0033752227 | V9: =(U70/T68)^(1/2) -> 0.11803892 | X9: =AVERAGE(J9:J68) -> -0.092276057 | Y9: =IF(J9="","",(J9-X$9)^2) | Z9: =(Y70/(COUNT(Y9:Y69)-1))^(1/2) -> 0.087793386
A10: 2 | B10: 45231 | C10: 327.15 | D10: 0.0859 | F10: =D10 -> 0.0859 | G10: =O$5/12 -> 0.002057875 | H10: =F10-G10 -> 0.083842125 | J10: =IF(H10<0,H10,"") | T10: 2 | U10: =(H10-S$9)^2 -> 0.0038435867 | Y10: =IF(J10="","",(J10-X$9)^2)
A11: 3 | B11: 45200 | C11: 301.27 | D11: 0.0035 | F11: =D11 -> 0.0035 | G11: =O$5/12 -> 0.002057875 | H11: =F11-G11 -> 0.001442125 | J11: =IF(H11<0,H11,"") | L11: Monthly Std Dev of excess returns (σ) | O11: =STDEV.P(H9:H20) -> 0.084095466 | P11: =STDEV.P(H9:H44) -> 0.12890792 | Q11: =STDEV.P(H9:H68) -> 0.11803892 | T11: 3 | U11: =(H11-S$9)^2 -> 0.00041629601 | Y11: =IF(J11="","",(J11-X$9)^2)
A12: 4 | B12: 45170 | C12: 300.21 | D12: 0.0146 | F12: =D12 -> 0.0146 | G12: =O$5/12 -> 0.002057875 | H12: =F12-G12 -> 0.012542125 | J12: =IF(H12<0,H12,"") | L12: Monthly Portfolio return (Rp) | O12: =(1+O19)^(1/12)-1 -> 0.074784218 | P12: =(1+P19)^(1/12)-1 -> 0.0087868821 | Q12: =(1+Q19)^(1/12)-1 -> 0.012629894 | T12: 4 | U12: =(H12-S$9)^2 -> 8.6552011e-05 | Y12: =IF(J12="","",(J12-X$9)^2)
A13: 5 | B13: 45139 | C13: 295.89 | D13: -0.0713 | F13: =D13 -> -0.0713 | G13: =O$5/12 -> 0.002057875 | H13: =F13-G13 -> -0.073357875 | J13: =IF(H13<0,H13,"") -> -0.073357875 | L13: Monthly Risk-free return - US 10Yr Yield (Rf) | O13: =O20/12 -> 0.002057875 | P13: =P20/12 -> 0.002057875 | Q13: =Q20/12 -> 0.002057875 | T13: 5 | U13: =(H13-S$9)^2 -> 0.0090636747 | Y13: =IF(J13="","",(J13-X$9)^2) -> 0.0003578976
A14: 6 | B14: 45108 | C14: 318.6 | D14: 0.1102 | F14: =D14 -> 0.1102 | G14: =O$5/12 -> 0.002057875 | H14: =F14-G14 -> 0.10814213 | J14: =IF(H14<0,H14,"") | L14: Excess return (Rp - Rf) | O14: =O12-O13 -> 0.072726343 | P14: =P12-P13 -> 0.0067290071 | Q14: =Q12-Q13 -> 0.010572019 | T14: 6 | U14: =(H14-S$9)^2 -> 0.0074471147 | Y14: =IF(J14="","",(J14-X$9)^2)
A15: 7 | B15: 45078 | C15: 286.98 | D15: 0.0841 | F15: =D15 -> 0.0841 | G15: =O$5/12 -> 0.002057875 | H15: =F15-G15 -> 0.082042125 | J15: =IF(H15<0,H15,"") | T15: 7 | U15: =(H15-S$9)^2 -> 0.0036236387 | Y15: =IF(J15="","",(J15-X$9)^2)
A16: 8 | B16: 45047 | C16: 264.72 | D16: 0.1015 | F16: =D16 -> 0.1015 | G16: =O$5/12 -> 0.002057875 | H16: =F16-G16 -> 0.099442125 | J16: =IF(H16<0,H16,"") | L16: Monthly Sharpe Ratio ( [Rp - Rf] / σ ) | O16: =O14/O11 -> 0.86480694 | P16: =P14/P11 -> 0.052200104 | Q16: =Q14/Q11 -> 0.08956384 | T16: 8 | U16: =(H16-S$9)^2 -> 0.0060212427 | Y16: =IF(J16="","",(J16-X$9)^2)
A17: 9 | B17: 45017 | C17: 240.32 | D17: 0.1339 | F17: =D17 -> 0.1339 | G17: =O$5/12 -> 0.002057875 | H17: =F17-G17 -> 0.13184213 | J17: =IF(H17<0,H17,"") | T17: 9 | U17: =(H17-S$9)^2 -> 0.012099267 | Y17: =IF(J17="","",(J17-X$9)^2)
A18: 10 | B18: 44986 | C18: 211.94 | D18: 0.2115 | F18: =D18 -> 0.2115 | G18: =O$5/12 -> 0.002057875 | H18: =F18-G18 -> 0.20944213 | J18: =IF(H18<0,H18,"") | L18: Annualized Std Dev of excess returns (σ) | O18: =O11*12^(1/2) -> 0.29131524 | P18: =P11*12^(1/2) -> 0.44655015 | Q18: =Q11*12^(1/2) -> 0.4088988 | T18: 10 | U18: =(H18-S$9)^2 -> 0.035192509 | Y18: =IF(J18="","",(J18-X$9)^2)
A19: 11 | B19: 44958 | C19: 174.94 | D19: 0.1743 | F19: =D19 -> 0.1743 | G19: =O$5/12 -> 0.002057875 | H19: =F19-G19 -> 0.17224212 | J19: =IF(H19<0,H19,"") | L19: Annualized Portfolio return (Rp) | O19: =($C$9/$C$20)^(1/($A$20/12))-1 -> 1.3760489 | P19: =($C$9/$C$44)^(1/($A$44/12))-1 -> 0.11069065 | Q19: =($C$9/$C$68)^(1/($A$68/12))-1 -> 0.16254274 | T19: 11 | U19: =(H19-S$9)^2 -> 0.022619157 | Y19: =IF(J19="","",(J19-X$9)^2)
A20: 12 | B20: 44927 | C20: 148.97 | D20: 0.2379 | F20: =D20 -> 0.2379 | G20: =O$5/12 -> 0.002057875 | H20: =F20-G20 -> 0.23584213 | J20: =IF(H20<0,H20,"") | L20: Annualized Risk-free return - US 10Yr Yield (Rf) | O20: =$O$5 -> 0.0246945 | P20: =$O$5 -> 0.0246945 | Q20: =$O$5 -> 0.0246945 | T20: 12 | U20: =(H20-S$9)^2 -> 0.045794573 | Y20: =IF(J20="","",(J20-X$9)^2)
A21: 13 | B21: 44896 | C21: 120.34 | D21: 0.019 | F21: =D21 -> 0.019 | G21: =O$5/12 -> 0.002057875 | H21: =F21-G21 -> 0.016942125 | J21: =IF(H21<0,H21,"") | L21: Excess return (Rp - Rf) | O21: =O19-O20 -> 1.3513544 | P21: =P19-P20 -> 0.085996146 | Q21: =Q19-Q20 -> 0.13784824 | T21: 13 | U21: =(H21-S$9)^2 -> 2.4042678e-05 | Y21: =IF(J21="","",(J21-X$9)^2)
A22: 14 | B22: 44866 | C22: 118.1 | D22: 0.2677 | F22: =D22 -> 0.2677 | G22: =O$5/12 -> 0.002057875 | H22: =F22-G22 -> 0.26564213 | J22: =IF(H22<0,H22,"") | T22: 14 | U22: =(H22-S$9)^2 -> 0.059436815 | Y22: =IF(J22="","",(J22-X$9)^2)
A23: 15 | B23: 44835 | C23: 93.16 | D23: -0.3134 | F23: =D23 -> -0.3134 | G23: =O$5/12 -> 0.002057875 | H23: =F23-G23 -> -0.31545787 | J23: =IF(H23<0,H23,"") -> -0.31545787 | L23: Annualized Sharpe Ratio ( [Rp - Rf] / σ ) | O23: =O21/O18 -> 4.6388042 | P23: =P21/P18 -> 0.19257892 | Q23: =Q21/Q18 -> 0.33712067 | T23: 15 | U23: =(H23-S$9)^2 -> 0.11377354 | Y23: =IF(J23="","",(J23-X$9)^2) -> 0.049810124
A24: 16 | B24: 44805 | C24: 135.68 | D24: -0.1672 | F24: =D24 -> -0.1672 | G24: =O$5/12 -> 0.002057875 | H24: =F24-G24 -> -0.16925788 | J24: =IF(H24<0,H24,"") -> -0.16925788 | T24: 16 | U24: =(H24-S$9)^2 -> 0.036520484 | Y24: =IF(J24="","",(J24-X$9)^2) -> 0.0059262003
A25: 17 | B25: 44774 | C25: 162.93 | D25: 0.0241 | F25: =D25 -> 0.0241 | G25: =O$5/12 -> 0.002057875 | H25: =F25-G25 -> 0.022042125 | J25: =IF(H25<0,H25,"") | T25: 17 | U25: =(H25-S$9)^2 -> 3.8677778e-08 | Y25: =IF(J25="","",(J25-X$9)^2)
A26: 18 | B26: 44743 | C26: 159.1 | D26: -0.0133 | F26: =D26 -> -0.0133 | G26: =O$5/12 -> 0.002057875 | H26: =F26-G26 -> -0.015357875 | J26: =IF(H26<0,H26,"") -> -0.015357875 | L26: Sortino Ratio | O26: 1 Year | P26: 3 Years | Q26: 5 Years | T26: 18 | U26: =(H26-S$9)^2 -> 0.001384088 | Y26: =IF(J26="","",(J26-X$9)^2) -> 0.0059164067
A27: 19 | B27: 44713 | C27: 161.25 | D27: -0.1673 | F27: =D27 -> -0.1673 | G27: =O$5/12 -> 0.002057875 | H27: =F27-G27 -> -0.16935787 | J27: =IF(H27<0,H27,"") -> -0.16935787 | T27: 19 | U27: =(H27-S$9)^2 -> 0.036558715 | Y27: =IF(J27="","",(J27-X$9)^2) -> 0.0059416067
A28: 20 | B28: 44682 | C28: 193.64 | D28: -0.0341 | F28: =D28 -> -0.0341 | G28: =O$5/12 -> 0.002057875 | H28: =F28-G28 -> -0.036157875 | J28: =IF(H28<0,H28,"") -> -0.036157875 | L28: Monthly Std Dev of excess negative returns (σd) | O28: =IFERROR(_xlfn.STDEV.S(J9:J20),ABS(J13)) -> 0.073357875 | P28: =_xlfn.STDEV.S(J9:J44) -> 0.10476577 | Q28: =_xlfn.STDEV.S(J9:J68) -> 0.087793386 | T28: 20 | U28: =(H28-S$9)^2 -> 0.0033643867 | Y28: =IF(J28="","",(J28-X$9)^2) -> 0.0031492503
A29: 21 | B29: 44652 | C29: 200.47 | D29: -0.0984 | F29: =D29 -> -0.0984 | G29: =O$5/12 -> 0.002057875 | H29: =F29-G29 -> -0.10045788 | J29: =IF(H29<0,H29,"") -> -0.10045788 | L29: Monthly Portfolio return (Rp) | O29: =(1+O36)^(1/12)-1 -> 0.074784218 | P29: =(1+P36)^(1/12)-1 -> 0.0087868821 | Q29: =(1+Q36)^(1/12)-1 -> 0.012629894 | T29: 21 | U29: =(H29-S$9)^2 -> 0.014958105 | Y29: =IF(J29="","",(J29-X$9)^2) -> 6.6942149e-05
A30: 22 | B30: 44621 | C30: 222.36 | D30: 0.0537 | F30: =D30 -> 0.0537 | G30: =O$5/12 -> 0.002057875 | H30: =F30-G30 -> 0.051642125 | J30: =IF(H30<0,H30,"") | L30: Monthly Risk-free return - US 10Yr Yield (Rf) | O30: =O37/12 -> 0.002057875 | P30: =P37/12 -> 0.002057875 | Q30: =Q37/12 -> 0.002057875 | T30: 22 | U30: =(H30-S$9)^2 -> 0.00088784134 | Y30: =IF(J30="","",(J30-X$9)^2)
A31: 23 | B31: 44593 | C31: 211.03 | D31: -0.3263 | F31: =D31 -> -0.3263 | G31: =O$5/12 -> 0.002057875 | H31: =F31-G31 -> -0.32835788 | J31: =IF(H31<0,H31,"") -> -0.32835788 | L31: Excess return (Rp - Rf) | O31: =O29-O30 -> 0.072726343 | P31: =P29-P30 -> 0.0067290071 | Q31: =Q29-Q30 -> 0.010572019 | T31: 23 | U31: =(H31-S$9)^2 -> 0.12264237 | Y31: =IF(J31="","",(J31-X$9)^2) -> 0.055734625
A32: 24 | B32: 44562 | C32: 313.26 | D32: -0.0686 | F32: =D32 -> -0.0686 | G32: =O$5/12 -> 0.002057875 | H32: =F32-G32 -> -0.070657875 | J32: =IF(H32<0,H32,"") -> -0.070657875 | T32: 24 | U32: =(H32-S$9)^2 -> 0.0085568667 | Y32: =IF(J32="","",(J32-X$9)^2) -> 0.00046734579
A33: 25 | B33: 44531 | C33: 336.35 | D33: 0.0366 | F33: =D33 -> 0.0366 | G33: =O$5/12 -> 0.002057875 | H33: =F33-G33 -> 0.034542125 | J33: =IF(H33<0,H33,"") | L33: Monthly Sortino Ratio ( [Rp - Rf] / σ ) | O33: =O31/O28 -> 0.99139108 | P33: =P31/P28 -> 0.064229064 | Q33: =Q31/Q28 -> 0.12041931 | T33: 25 | U33: =(H33-S$9)^2 -> 0.00016120534 | Y33: =IF(J33="","",(J33-X$9)^2)
A34: 26 | B34: 44501 | C34: 324.46 | D34: 0.0028 | F34: =D34 -> 0.0028 | G34: =O$5/12 -> 0.002057875 | H34: =F34-G34 -> 0.000742125 | J34: =IF(H34<0,H34,"") | T34: 26 | U34: =(H34-S$9)^2 -> 0.00044535068 | Y34: =IF(J34="","",(J34-X$9)^2)
A35: 27 | B35: 44470 | C35: 323.57 | D35: -0.0466 | F35: =D35 -> -0.0466 | G35: =O$5/12 -> 0.002057875 | H35: =F35-G35 -> -0.048657875 | J35: =IF(H35<0,H35,"") -> -0.048657875 | L35: Annualized Std Dev of excess negative returns (σ) | O35: =O28*12^(1/2) -> 0.25411913 | P35: =P28*12^(1/2) -> 0.36291926 | Q35: =Q28*12^(1/2) -> 0.30412521 | T35: 27 | U35: =(H35-S$9)^2 -> 0.00497072 | Y35: =IF(J35="","",(J35-X$9)^2) -> 0.0019025458
A36: 28 | B36: 44440 | C36: 339.39 | D36: -0.1054 | F36: =D36 -> -0.1054 | G36: =O$5/12 -> 0.002057875 | H36: =F36-G36 -> -0.10745787 | J36: =IF(H36<0,H36,"") -> -0.10745787 | L36: Annualized Portfolio return (Rp) | O36: =($C$9/$C$20)^(1/($A$20/12))-1 -> 1.3760489 | P36: =($C$9/$C$44)^(1/($A$44/12))-1 -> 0.11069065 | Q36: =($C$9/$C$68)^(1/($A$68/12))-1 -> 0.16254274 | T36: 28 | U36: =(H36-S$9)^2 -> 0.016719352 | Y36: =IF(J36="","",(J36-X$9)^2) -> 0.0002304876
A37: 29 | B37: 44409 | C37: 379.38 | D37: 0.0648 | F37: =D37 -> 0.0648 | G37: =O$5/12 -> 0.002057875 | H37: =F37-G37 -> 0.062742125 | J37: =IF(H37<0,H37,"") | L37: Annualized Risk-free return - US 10Yr Yield (Rf) | O37: =$O$5 -> 0.0246945 | P37: =$O$5 -> 0.0246945 | Q37: =$O$5 -> 0.0246945 | T37: 29 | U37: =(H37-S$9)^2 -> 0.0016725373 | Y37: =IF(J37="","",(J37-X$9)^2)
A38: 30 | B38: 44378 | C38: 356.3 | D38: 0.0247 | F38: =D38 -> 0.0247 | G38: =O$5/12 -> 0.002057875 | H38: =F38-G38 -> 0.022642125 | J38: =IF(H38<0,H38,"") | L38: Excess return (Rp - Rf) | O38: =O36-O37 -> 1.3513544 | P38: =P36-P37 -> 0.085996146 | Q38: =Q36-Q37 -> 0.13784824 | T38: 30 | U38: =(H38-S$9)^2 -> 6.3467778e-07 | Y38: =IF(J38="","",(J38-X$9)^2)
A39: 31 | B39: 44348 | C39: 347.71 | D39: 0.0577 | F39: =D39 -> 0.0577 | G39: =O$5/12 -> 0.002057875 | H39: =F39-G39 -> 0.055642125 | J39: =IF(H39<0,H39,"") | T39: 31 | U39: =(H39-S$9)^2 -> 0.0011422147 | Y39: =IF(J39="","",(J39-X$9)^2)
A40: 32 | B40: 44317 | C40: 328.73 | D40: 0.0112 | F40: =D40 -> 0.0112 | G40: =O$5/12 -> 0.002057875 | H40: =F40-G40 -> 0.009142125 | J40: =IF(H40<0,H40,"") | L40: Annualized Sortino Ratio ( [Rp - Rf] / σd ) | O40: =O38/O35 -> 5.3177986 | P40: =P38/P35 -> 0.23695669 | Q40: =Q38/Q35 -> 0.45326146 | T40: 32 | U40: =(H40-S$9)^2 -> 0.00016137468 | Y40: =IF(J40="","",(J40-X$9)^2)
A41: 33 | B41: 44287 | C41: 325.08 | D41: 0.1037 | F41: =D41 -> 0.1037 | G41: =O$5/12 -> 0.002057875 | H41: =F41-G41 -> 0.10164212 | J41: =IF(H41<0,H41,"") | T41: 33 | U41: =(H41-S$9)^2 -> 0.006367508 | Y41: =IF(J41="","",(J41-X$9)^2)
A42: 34 | B42: 44256 | C42: 294.53 | D42: 0.1433 | F42: =D42 -> 0.1433 | G42: =O$5/12 -> 0.002057875 | H42: =F42-G42 -> 0.14124212 | J42: =IF(H42<0,H42,"") | T42: 34 | U42: =(H42-S$9)^2 -> 0.014255564 | Y42: =IF(J42="","",(J42-X$9)^2)
A43: 35 | B43: 44228 | C43: 257.62 | D43: -0.0027 | F43: =D43 -> -0.0027 | G43: =O$5/12 -> 0.002057875 | H43: =F43-G43 -> -0.004757875 | J43: =IF(H43<0,H43,"") -> -0.004757875 | T43: 35 | U43: =(H43-S$9)^2 -> 0.00070773734 | Y43: =IF(J43="","",(J43-X$9)^2) -> 0.0076594321
A44: 36 | B44: 44197 | C44: 258.33 | D44: -0.0543 | F44: =D44 -> -0.0543 | G44: =O$5/12 -> 0.002057875 | H44: =F44-G44 -> -0.056357875 | J44: =IF(H44<0,H44,"") -> -0.056357875 | T44: 36 | U44: =(H44-S$9)^2 -> 0.0061157613 | Y44: =IF(J44="","",(J44-X$9)^2) -> 0.0012901158
A45: 37 | B45: 44166 | C45: 273.16 | D45: -0.0138 | F45: =D45 -> -0.0138 | G45: =O$5/12 -> 0.002057875 | H45: =F45-G45 -> -0.015857875 | J45: =IF(H45<0,H45,"") -> -0.015857875 | T45: 37 | U45: =(H45-S$9)^2 -> 0.0014215413 | Y45: =IF(J45="","",(J45-X$9)^2) -> 0.0058397385
A46: 38 | B46: 44136 | C46: 276.97 | D46: 0.0527 | F46: =D46 -> 0.0527 | G46: =O$5/12 -> 0.002057875 | H46: =F46-G46 -> 0.050642125 | J46: =IF(H46<0,H46,"") | T46: 38 | U46: =(H46-S$9)^2 -> 0.00082924801 | Y46: =IF(J46="","",(J46-X$9)^2)
A47: 39 | B47: 44105 | C47: 263.11 | D47: 0.0046 | F47: =D47 -> 0.0046 | G47: =O$5/12 -> 0.002057875 | H47: =F47-G47 -> 0.002542125 | J47: =IF(H47<0,H47,"") | T47: 39 | U47: =(H47-S$9)^2 -> 0.00037261868 | Y47: =IF(J47="","",(J47-X$9)^2)
A48: 40 | B48: 44075 | C48: 261.9 | D48: -0.1068 | F48: =D48 -> -0.1068 | G48: =O$5/12 -> 0.002057875 | H48: =F48-G48 -> -0.10885788 | J48: =IF(H48<0,H48,"") -> -0.10885788 | T48: 40 | U48: =(H48-S$9)^2 -> 0.017083361 | Y48: =IF(J48="","",(J48-X$9)^2) -> 0.00027495669
A49: 41 | B49: 44044 | C49: 293.2 | D49: 0.1558 | F49: =D49 -> 0.1558 | G49: =O$5/12 -> 0.002057875 | H49: =F49-G49 -> 0.15374213 | J49: =IF(H49<0,H49,"") | T49: 41 | U49: =(H49-S$9)^2 -> 0.017396731 | Y49: =IF(J49="","",(J49-X$9)^2)
A50: 42 | B50: 44013 | C50: 253.67 | D50: 0.1171 | F50: =D50 -> 0.1171 | G50: =O$5/12 -> 0.002057875 | H50: =F50-G50 -> 0.11504212 | J50: =IF(H50<0,H50,"") | T50: 42 | U50: =(H50-S$9)^2 -> 0.0086856187 | Y50: =IF(J50="","",(J50-X$9)^2)
A51: 43 | B51: 43983 | C51: 227.07 | D51: 0.0088 | F51: =D51 -> 0.0088 | G51: =O$5/12 -> 0.002057875 | H51: =F51-G51 -> 0.006742125 | J51: =IF(H51<0,H51,"") | T51: 43 | U51: =(H51-S$9)^2 -> 0.00022811068 | Y51: =IF(J51="","",(J51-X$9)^2)
A52: 44 | B52: 43952 | C52: 225.09 | D52: 0.0996 | F52: =D52 -> 0.0996 | G52: =O$5/12 -> 0.002057875 | H52: =F52-G52 -> 0.097542125 | J52: =IF(H52<0,H52,"") | T52: 44 | U52: =(H52-S$9)^2 -> 0.0057299853 | Y52: =IF(J52="","",(J52-X$9)^2)
... A68: 60 | B68: 43466 | C68: 166.69 | D68: 0.2716 | F68: =D68 -> 0.2716 | G68: =O$5/12 -> 0.002057875 | H68: =F68-G68 -> 0.26954213 | J68: =IF(H68<0,H68,"") | T68: 60 | U68: =(H68-S$9)^2 -> 0.061353639 | Y68: =IF(J68="","",(J68-X$9)^2)
U70: =SUM(U9:U69) -> 0.83599116 | Y70: =SUM(Y9:Y69) -> 0.16186125
B74: 45261 | C74: 353.96 | D74: 0.082
B75: 45231 | C75: 327.15 | D75: 0.0859
B76: 45200 | C76: 301.27 | D76: 0.0035
B77: 45170 | C77: 300.21 | D77: 0.0146
B78: 45139 | C78: 295.89 | D78: -0.0713
B79: 45108 | C79: 318.6 | D79: 0.1102
B80: 45078 | C80: 286.98 | D80: 0.0841
B81: 45047 | C81: 264.72 | D81: 0.1015
B82: 45017 | C82: 240.32 | D82: 0.1339
B83: 44986 | C83: 211.94 | D83: 0.2115
B84: 44958 | C84: 174.94 | D84: 0.1743
B85: 44927 | C85: 148.97 | D85: 0.2379
... B133: 43466 | C133: 166.69 | D133: 0.2716
