Workbook

Sheet Overall
B2: SUMMARY
H3: Share price | K3: Profit Margins | T3: Valuations Multiples | AC3: Solvency | AL3: Efficiency | AU3: Risk
H4: CAGR | K4: GPM | N4: OM | Q4: NPM | T4: PE | W4: EPS | Z4: Dividend Yield | AC4: Debt Ratio | AF4: Debt - Equity | AI4: Debt - Revenue | AL4: IT | AO4: RT | AR4: PT | AU4: Sharpe Ratio | AX4: Sortino Ratio
B5: Base year | D5: Y/E | E5: Updated As At | F5: MC | G5: Share price at Y/E | H5: Current | I5: 3 years | J5: 5 years | K5: Current | L5: 3 years | M5: 5 years | N5: Current | O5: 3 years | P5: 5 years | Q5: Current | R5: 3 years | S5: 5 years | T5: Current | U5: 3 years | V5: 5 years | W5: Current | X5: 3 years | Y5: 5 years | Z5: Current | AA5: 3 years | AB5: 5 years | AC5: Current | AD5: 3 years | AE5: 5 years | AF5: Current | AG5: 3 years | AH5: 5 years | AI5: Current | AJ5: 3 years | AK5: 5 years | AL5: Current | AM5: 3 years | AN5: 5 years | AO5: Current | AP5: 3 years | AQ5: 5 years | AR5: Current | AS5: 3 years | AT5: 5 years | AU5: Current | AV5: 3 years | AW5: 5 years | AX5: Current | AY5: 3 years | AZ5: 5 years
B6: 2024 | D6: 30/06 | E6: 2024 | F6: =OFFSET(FS!P127,0,E$6-B$6) -> 3110013.9 | G6: =OFFSET(FS!P121,0,E$6-B$6) -> 418.35 | H6: =((OFFSET(FS!P121,0,E$6-B$6)/OFFSET(FS!P121,0,-1+E$6-B$6))^(1/1)-1)*100 -> 24.538581 | I6: =((OFFSET(FS!P121,0,E$6-B$6)/OFFSET(FS!P121,0,-2+E$6-B$6))^(1/3)-1)*100 -> 14.22079 | J6: =((OFFSET(FS!P121,0,E$6-B$6)/OFFSET(FS!P121,0,-4+E$6-B$6))^(1/5)-1)*100 -> 15.332829 | K6: =OFFSET(FS!P98,0,0+E$6-B$6) -> 69.764444 | L6: =AVERAGE(OFFSET(FS!P98,0,-2+E$6-B$6):OFFSET(FS!P98,0,E$6-B$6)) -> 69.028735 | M6: =AVERAGE(OFFSET(FS!P98,0,-4+E$6-B$6):OFFSET(FS!P98,0,E$6-B$6)) -> 68.758601 | N6: =OFFSET(FS!P107,0,0+E$6-B$6) -> 44.6443 | O6: =AVERAGE(OFFSET(FS!P107,0,-2+E$6-B$6):OFFSET(FS!P107,0,E$6-B$6)) -> 42.824153 | P6: =AVERAGE(OFFSET(FS!P107,0,-4+E$6-B$6):OFFSET(FS!P107,0,E$6-B$6)) -> 41.419544 | Q6: =OFFSET(FS!P116,0,0+E$6-B$6) -> 35.955973 | R6: =AVERAGE(OFFSET(FS!P116,0,-2+E$6-B$6):OFFSET(FS!P116,0,E$6-B$6)) -> 35.596183 | S6: =AVERAGE(OFFSET(FS!P116,0,-4+E$6-B$6):OFFSET(FS!P116,0,E$6-B$6)) -> 34.840555 | T6: =OFFSET(FS!P123,0,0+E$6-B$6) -> 35.286533 | U6: =AVERAGE(OFFSET(FS!P123,0,-2+E$6-B$6):OFFSET(FS!P123,0,E$6-B$6)) -> 32.865351 | V6: =AVERAGE(OFFSET(FS!P123,0,-4+E$6-B$6):OFFSET(FS!P123,0,E$6-B$6)) -> 33.722246 | W6: =OFFSET(FS!P122,0,0+E$6-B$6) -> 11.855798 | X6: =AVERAGE(OFFSET(FS!P122,0,-2+E$6-B$6):OFFSET(FS!P122,0,E$6-B$6)) -> 10.445795 | Y6: =AVERAGE(OFFSET(FS!P122,0,-4+E$6-B$6):OFFSET(FS!P122,0,E$6-B$6)) -> 9.0669945 | Z6: =OFFSET(FS!P133,0,0+E$6-B$6) -> 0.0070002903 | AA6: =AVERAGE(OFFSET(FS!P133,0,-2+E$6-B$6):OFFSET(FS!P133,0,E$6-B$6)) -> 0.0078619015 | AB6: =AVERAGE(OFFSET(FS!P133,0,-4+E$6-B$6):OFFSET(FS!P133,0,E$6-B$6)) -> 0.0082100264 | AC6: =OFFSET(FS!P187,0,0+E$6-B$6) -> 0.47579774 | AD6: =AVERAGE(OFFSET(FS!P187,0,-2+E$6-B$6):OFFSET(FS!P187,0,E$6-B$6)) -> 0.50624926 | AE6: =AVERAGE(OFFSET(FS!P187,0,-4+E$6-B$6):OFFSET(FS!P187,0,E$6-B$6)) -> 0.54014433 | AF6: =OFFSET(FS!P188,0,0+E$6-B$6) -> 0.90766062 | AG6: =AVERAGE(OFFSET(FS!P188,0,-2+E$6-B$6):OFFSET(FS!P188,0,E$6-B$6)) -> 1.1192224 | AH6: =AVERAGE(OFFSET(FS!P188,0,-4+E$6-B$6):OFFSET(FS!P188,0,E$6-B$6)) -> 1.2510688 | AI6: =OFFSET(FS!P189,0,0+E$6-B$6) -> 0.99414169 | AJ6: =AVERAGE(OFFSET(FS!P189,0,-2+E$6-B$6):OFFSET(FS!P189,0,E$6-B$6)) -> 0.98840174 | AK6: =AVERAGE(OFFSET(FS!P189,0,-4+E$6-B$6):OFFSET(FS!P189,0,E$6-B$6)) -> 1.0771711 | AL6: =OFFSET(FS!P192,0,0+E$6-B$6) -> 12.256822 | AM6: =AVERAGE(OFFSET(FS!P192,0,-2+E$6-B$6):OFFSET(FS!P192,0,E$6-B$6)) -> 8.1576745 | AN6: =AVERAGE(OFFSET(FS!P192,0,-4+E$6-B$6):OFFSET(FS!P192,0,E$6-B$6)) -> 7.967375 | AO6: =OFFSET(FS!P193,0,0+E$6-B$6) -> 4.3061275 | AP6: =AVERAGE(OFFSET(FS!P193,0,-2+E$6-B$6):OFFSET(FS!P193,0,E$6-B$6)) -> 4.3794006 | AQ6: =AVERAGE(OFFSET(FS!P193,0,-4+E$6-B$6):OFFSET(FS!P193,0,E$6-B$6)) -> 4.4048507 | AR6: =OFFSET(FS!P194,0,0+E$6-B$6) -> 3.3694308 | AS6: =AVERAGE(OFFSET(FS!P194,0,-2+E$6-B$6):OFFSET(FS!P194,0,E$6-B$6)) -> 3.4355482 | AT6: =AVERAGE(OFFSET(FS!P194,0,-4+E$6-B$6):OFFSET(FS!P194,0,E$6-B$6)) -> 3.4857519 | AU6: ='Sharpe, Sortino'!O23 -> 1.6192866 | AV6: ='Sharpe, Sortino'!P23 -> 0.57403401 | AW6: ='Sharpe, Sortino'!Q23 -> 1.1263274 | AX6: ='Sharpe, Sortino'!O40 -> 3.3209408 | AY6: ='Sharpe, Sortino'!P40 -> 1.1697852 | AZ6: ='Sharpe, Sortino'!Q40 -> 2.1946566

Sheet FS
F1: < Figures are in millions >
F2: Y/E 30/06 | U2: Annualized
F3: 2014 | G3: 2015 | H3: 2016 | I3: 2017 | J3: 2018 | K3: 2019 | L3: 2020 | M3: 2021 | N3: 2022 | O3: 2023 | P3: 2024 | R3: Average | S3: Median | T3: CAGR | U3: Std Dev
B5: Revenue By Geography
C6: United States | F6: 43474 | G6: 42941 | H6: 46416 | I6: 51078 | J6: 55926 | K6: 64199 | L6: 73160 | M6: 83953 | N6: 100218 | O6: 106744 | P6: 124704
C7: Other Countries | F7: 43359 | G7: 50639 | H7: 44738 | I7: 45493 | J7: 54434 | K7: 61644 | L7: 69855 | M7: 84135 | N7: 98052 | O7: 105171 | P7: 120418
B8: Total Revenues | F8: =SUM(F6:F7) -> 86833 | G8: =SUM(G6:G7) -> 93580 | H8: =SUM(H6:H7) -> 91154 | I8: =SUM(I6:I7) -> 96571 | J8: =SUM(J6:J7) -> 110360 | K8: =SUM(K6:K7) -> 125843 | L8: =SUM(L6:L7) -> 143015 | M8: =SUM(M6:M7) -> 168088 | ... P8: =SUM(P6:P7) -> 245122
B10: Revenue By Product / Service Offering
C11: Server products & cloud services | F11: 17055 | G11: 18612 | H11: 23868 | I11: 21649 | J11: 26129 | K11: 32622 | L11: 41379 | M11: 52589 | N11: 67350 | O11: 79970 | P11: 97726
C12: Office products & cloud services | F12: 24323 | G12: 23538 | H12: 19062 | I12: 25573 | J12: 28316 | K12: 31769 | L12: 35316 | M12: 39872 | N12: 44970 | O12: 48848 | P12: 54875
C13: Windows | F13: 16856 | G13: 14826 | H13: 17548 | I13: 18593 | J13: 19518 | K13: 20395 | L13: 21510 | M13: 22488 | N13: 24732 | O13: 21507 | P13: 23244
C14: Gaming | F14: 8643 | G14: 9121 | H14: 9202 | I14: 9051 | J14: 10353 | K14: 11386 | L14: 11575 | M14: 15370 | N14: 16230 | O14: 15466 | P14: 21503
C15: LinkedIn | F15: 0 | G15: 0 | H15: 0 | I15: 6219 | J15: 5259 | K15: 6754 | L15: 8077 | M15: 10289 | N15: 13631 | O15: 14989 | P15: 16372
C16: Search & news advertising | F16: 4016 | G16: 4557 | H16: 5428 | I16: 2271 | J16: 7012 | K16: 7628 | L16: 8524 | M16: 9267 | N16: 11526 | O16: 12158 | P16: 12576
C17: Enterprise & partner services | F17: 4767 | G17: 5090 | H17: 5659 | I17: 5542 | J17: 5134 | K17: 6124 | L17: 6409 | M17: 6943 | N17: 7605 | O17: 7900 | P17: 7594
C18: Dynamics products & cloud services | F18: 0 | G18: 0 | H18: 0 | I18: 0 | J18: 0 | K18: 0 | L18: 0 | M18: 7143 | N18: 4687 | O18: 5437 | P18: 6481
C19: Devices | F19: =1883+3073 -> 4956 | G19: 11602 | H19: 7888 | I19: 5062 | J19: 5846 | K19: 6095 | L19: 6457 | M19: 3754 | N19: 7306 | O19: 5521 | P19: 4706
C20: Other | F20: 6217 | G20: 6234 | H20: 2499 | I20: 2611 | J20: 2793 | K20: 3070 | L20: 3768 | M20: 373 | N20: 233 | O20: 119 | P20: 45
B21: Total Revenues | F21: =SUM(F11:F20) -> 86833 | G21: =SUM(G11:G20) -> 93580 | H21: =SUM(H11:H20) -> 91154 | I21: =SUM(I11:I20) -> 96571 | J21: =SUM(J11:J20) -> 110360 | K21: =SUM(K11:K20) -> 125843 | L21: =SUM(L11:L20) -> 143015 | M21: =SUM(M11:M20) -> 168088 | ... P21: =SUM(P11:P20) -> 245122
B23: Revenue by Segments
C24: Productivity & business processes | F24: 26976 | G24: 26430 | H24: 25792 | I24: 29870 | J24: 35865 | K24: 41160 | L24: 46398 | M24: 53915 | N24: 63364 | O24: 69274 | P24: 77728
C25: Intelligent Cloud | F25: 21735 | G25: 23715 | H25: 24952 | I25: 27407 | J25: 32219 | K25: 38985 | L25: 48366 | M25: 59728 | N25: 74965 | O25: 87907 | P25: 105362
C26: More personal computing | F26: =38460-338 -> 38122 | G26: 43435 | H26: 40410 | I26: 39294 | J26: 42276 | K26: 45698 | L26: 48251 | M26: 54445 | N26: 59941 | O26: 54734 | P26: 62032
B27: Total Revenues | F27: =SUM(F24:F26) -> 86833 | G27: =SUM(G24:G26) -> 93580 | H27: =SUM(H24:H26) -> 91154 | I27: =SUM(I24:I26) -> 96571 | J27: =SUM(J24:J26) -> 110360 | K27: =SUM(K24:K26) -> 125843 | L27: =SUM(L24:L26) -> 143015 | M27: =SUM(M24:M26) -> 168088 | ... P27: =SUM(P24:P26) -> 245122
B29: Operating Income/(loss) Breakdown
C30: Productivity & business processes | F30: 14173 | G30: 13274 | H30: 11756 | I30: 11389 | J30: 12924 | K30: 16219 | L30: 18724 | M30: 24351 | N30: 29690 | O30: 34189 | P30: 40540
C31: Intelligent Cloud | F31: 8446 | G31: 9803 | H31: 9249 | I31: 9127 | J31: 11524 | K31: 13920 | L31: 18324 | M31: 26471 | N31: 33203 | O31: 37884 | P31: 49584
C32: More personal computing | F32: 5605 | G32: 5095 | H32: 6183 | I32: 8815 | J32: 10610 | K32: 12820 | L32: 15911 | M32: 19094 | N32: 20490 | O32: 16450 | P32: 19309
C33: Corporate & Other (Impairment & restructuring) | F33: -465 | G33: -10011 | H33: -1110 | I33: -306 | J33: 0 | K33: 0 | L33: 0 | M33: 0 | N33: 0 | O33: 0 | P33: 0
B34: Total Operating Income | F34: =SUM(F30:F33) -> 27759 | G34: =SUM(G30:G33) -> 18161 | H34: =SUM(H30:H33) -> 26078 | I34: =SUM(I30:I33) -> 29025 | J34: =SUM(J30:J33) -> 35058 | K34: =SUM(K30:K33) -> 42959 | L34: =SUM(L30:L33) -> 52959 | M34: =SUM(M30:M33) -> 69916 | ... P34: =SUM(P30:P33) -> 109433
C37: Composition By Geography
C38: United States % | F38: =F6/F$8*100 -> 50.066219 | G38: =G6/G$8*100 -> 45.886942 | H38: =H6/H$8*100 -> 50.92042 | I38: =I6/I$8*100 -> 52.891655 | J38: =J6/J$8*100 -> 50.67597 | K38: =K6/K$8*100 -> 51.015154 | L38: =L6/L$8*100 -> 51.155473 | M38: =M6/M$8*100 -> 49.945862 | ... P38: =P6/P$8*100 -> 50.874259 | R38: =AVERAGEIF(E38:Q38,"<>0") -> 50.395392
C39: Other Countries % | F39: =F7/F$8*100 -> 49.933781 | G39: =G7/G$8*100 -> 54.113058 | H39: =H7/H$8*100 -> 49.07958 | I39: =I7/I$8*100 -> 47.108345 | J39: =J7/J$8*100 -> 49.32403 | K39: =K7/K$8*100 -> 48.984846 | L39: =L7/L$8*100 -> 48.844527 | M39: =M7/M$8*100 -> 50.054138 | ... P39: =P7/P$8*100 -> 49.125741 | R39: =AVERAGEIF(E39:Q39,"<>0") -> 49.604608
F40: =SUM(F38:F39) -> 100 | G40: =SUM(G38:G39) -> 100 | H40: =SUM(H38:H39) -> 100 | I40: =SUM(I38:I39) -> 100 | J40: =SUM(J38:J39) -> 100 | K40: =SUM(K38:K39) -> 100 | L40: =SUM(L38:L39) -> 100 | M40: =SUM(M38:M39) -> 100 | ... P40: =SUM(P38:P39) -> 100
C42: Composition By Product / Service Offering
C43: Server products & cloud services % | F43: =IFERROR(F11/F$21*100,0) -> 19.64115 | G43: =IFERROR(G11/G$21*100,0) -> 19.888865 | H43: =IFERROR(H11/H$21*100,0) -> 26.18426 | I43: =IFERROR(I11/I$21*100,0) -> 22.417703 | J43: =IFERROR(J11/J$21*100,0) -> 23.676151 | K43: =IFERROR(K11/K$21*100,0) -> 25.922777 | L43: =IFERROR(L11/L$21*100,0) -> 28.933329 | M43: =IFERROR(M11/M$21*100,0) -> 31.286588 | ... P43: =IFERROR(P11/P$21*100,0) -> 39.86831 | R43: =AVERAGEIF(E43:Q43,"<>0") -> 28.138617
C44: Office products & cloud services % | F44: =IFERROR(F12/F$21*100,0) -> 28.01124 | G44: =IFERROR(G12/G$21*100,0) -> 25.15281 | H44: =IFERROR(H12/H$21*100,0) -> 20.911863 | I44: =IFERROR(I12/I$21*100,0) -> 26.481035 | J44: =IFERROR(J12/J$21*100,0) -> 25.657847 | K44: =IFERROR(K12/K$21*100,0) -> 25.244948 | L44: =IFERROR(L12/L$21*100,0) -> 24.693913 | M44: =IFERROR(M12/M$21*100,0) -> 23.720908 | ... P44: =IFERROR(P12/P$21*100,0) -> 22.386811 | R44: =AVERAGEIF(E44:Q44,"<>0") -> 24.363029
C45: Windows % | F45: =IFERROR(F13/F$21*100,0) -> 19.411975 | G45: =IFERROR(G13/G$21*100,0) -> 15.843129 | H45: =IFERROR(H13/H$21*100,0) -> 19.250938 | I45: =IFERROR(I13/I$21*100,0) -> 19.253192 | J45: =IFERROR(J13/J$21*100,0) -> 17.685756 | K45: =IFERROR(K13/K$21*100,0) -> 16.206702 | L45: =IFERROR(L13/L$21*100,0) -> 15.04038 | M45: =IFERROR(M13/M$21*100,0) -> 13.378706 | ... P45: =IFERROR(P13/P$21*100,0) -> 9.482625 | R45: =AVERAGEIF(E45:Q45,"<>0") -> 15.288744
C46: Gaming % | F46: =IFERROR(F14/F$21*100,0) -> 9.9535891 | G46: =IFERROR(G14/G$21*100,0) -> 9.7467408 | H46: =IFERROR(H14/H$21*100,0) -> 10.095004 | I46: =IFERROR(I14/I$21*100,0) -> 9.3723789 | J46: =IFERROR(J14/J$21*100,0) -> 9.3811163 | K46: =IFERROR(K14/K$21*100,0) -> 9.0477818 | L46: =IFERROR(L14/L$21*100,0) -> 8.0935566 | M46: =IFERROR(M14/M$21*100,0) -> 9.1440198 | ... P46: =IFERROR(P14/P$21*100,0) -> 8.7723664 | R46: =AVERAGEIF(E46:Q46,"<>0") -> 9.0082336
C47: LinkedIn % | F47: =IFERROR(F15/F$21*100,0) -> 0 | G47: =IFERROR(G15/G$21*100,0) -> 0 | H47: =IFERROR(H15/H$21*100,0) -> 0 | I47: =IFERROR(I15/I$21*100,0) -> 6.4398215 | J47: =IFERROR(J15/J$21*100,0) -> 4.7653135 | K47: =IFERROR(K15/K$21*100,0) -> 5.3670049 | L47: =IFERROR(L15/L$21*100,0) -> 5.6476593 | M47: =IFERROR(M15/M$21*100,0) -> 6.1211984 | ... P47: =IFERROR(P15/P$21*100,0) -> 6.679123 | R47: =AVERAGEIF(E47:Q47,"<>0") -> 6.121026
C48: Search & news advertising % | F48: =IFERROR(F16/F$21*100,0) -> 4.6249698 | G48: =IFERROR(G16/G$21*100,0) -> 4.8696303 | H48: =IFERROR(H16/H$21*100,0) -> 5.9547579 | I48: =IFERROR(I16/I$21*100,0) -> 2.3516377 | J48: =IFERROR(J16/J$21*100,0) -> 6.3537514 | K48: =IFERROR(K16/K$21*100,0) -> 6.0615211 | L48: =IFERROR(L16/L$21*100,0) -> 5.960214 | M48: =IFERROR(M16/M$21*100,0) -> 5.5131836 | ... P48: =IFERROR(P16/P$21*100,0) -> 5.1305064 | R48: =AVERAGEIF(E48:Q48,"<>0") -> 5.3064239
C49: Enterprise & partner services % | F49: =IFERROR(F17/F$21*100,0) -> 5.4898483 | G49: =IFERROR(G17/G$21*100,0) -> 5.4391964 | H49: =IFERROR(H17/H$21*100,0) -> 6.2081752 | I49: =IFERROR(I17/I$21*100,0) -> 5.7387829 | J49: =IFERROR(J17/J$21*100,0) -> 4.6520478 | K49: =IFERROR(K17/K$21*100,0) -> 4.8663811 | L49: =IFERROR(L17/L$21*100,0) -> 4.4813481 | M49: =IFERROR(M17/M$21*100,0) -> 4.1305745 | ... P49: =IFERROR(P17/P$21*100,0) -> 3.0980491 | R49: =AVERAGEIF(E49:Q49,"<>0") -> 4.6970902
C50: Dynamics products & cloud services % | F50: =IFERROR(F18/F$21*100,0) -> 0 | G50: =IFERROR(G18/G$21*100,0) -> 0 | H50: =IFERROR(H18/H$21*100,0) -> 0 | I50: =IFERROR(I18/I$21*100,0) -> 0 | J50: =IFERROR(J18/J$21*100,0) -> 0 | K50: =IFERROR(K18/K$21*100,0) -> 0 | L50: =IFERROR(L18/L$21*100,0) -> 0 | M50: =IFERROR(M18/M$21*100,0) -> 4.2495598 | ... P50: =IFERROR(P18/P$21*100,0) -> 2.6439895 | R50: =AVERAGEIF(E50:Q50,"<>0") -> 2.9557872
C51: Devices % | F51: =IFERROR(F19/F$21*100,0) -> 5.7075075 | G51: =IFERROR(G19/G$21*100,0) -> 12.397948 | H51: =IFERROR(H19/H$21*100,0) -> 8.6534875 | I51: =IFERROR(I19/I$21*100,0) -> 5.2417392 | J51: =IFERROR(J19/J$21*100,0) -> 5.2972091 | K51: =IFERROR(K19/K$21*100,0) -> 4.8433365 | L51: =IFERROR(L19/L$21*100,0) -> 4.514911 | M51: =IFERROR(M19/M$21*100,0) -> 2.233354 | ... P51: =IFERROR(P19/P$21*100,0) -> 1.9198603 | R51: =AVERAGEIF(E51:Q51,"<>0") -> 5.1908652
C52: Other % | F52: =IFERROR(F20/F$21*100,0) -> 7.1597204 | G52: =IFERROR(G20/G$21*100,0) -> 6.6616798 | H52: =IFERROR(H20/H$21*100,0) -> 2.7415144 | I52: =IFERROR(I20/I$21*100,0) -> 2.7037102 | J52: =IFERROR(J20/J$21*100,0) -> 2.5308083 | K52: =IFERROR(K20/K$21*100,0) -> 2.4395477 | L52: =IFERROR(L20/L$21*100,0) -> 2.6346887 | M52: =IFERROR(M20/M$21*100,0) -> 0.22190757 | ... P52: =IFERROR(P20/P$21*100,0) -> 0.018358205 | R52: =AVERAGEIF(E52:Q52,"<>0") -> 2.4805097
F53: =SUM(F43:F52) -> 100 | G53: =SUM(G43:G52) -> 100 | H53: =SUM(H43:H52) -> 100 | I53: =SUM(I43:I52) -> 100 | J53: =SUM(J43:J52) -> 100 | K53: =SUM(K43:K52) -> 100 | L53: =SUM(L43:L52) -> 100 | M53: =SUM(M43:M52) -> 100 | ... P53: =SUM(P43:P52) -> 100
C55: Composition By Segments
C56: Productivity & business processes % | F56: =IFERROR(F24/F$27*100,0) -> 31.06653 | G56: =IFERROR(G24/G$27*100,0) -> 28.243214 | H56: =IFERROR(H24/H$27*100,0) -> 28.294973 | I56: =IFERROR(I24/I$27*100,0) -> 30.930611 | J56: =IFERROR(J24/J$27*100,0) -> 32.498188 | K56: =IFERROR(K24/K$27*100,0) -> 32.707421 | L56: =IFERROR(L24/L$27*100,0) -> 32.442751 | M56: =IFERROR(M24/M$27*100,0) -> 32.07546 | ... P56: =IFERROR(P24/P$27*100,0) -> 31.709924 | R56: =AVERAGEIF(E56:Q56,"<>0") -> 31.328821
C57: Intelligent Cloud % | F57: =IFERROR(F25/F$27*100,0) -> 25.030806 | G57: =IFERROR(G25/G$27*100,0) -> 25.341953 | H57: =IFERROR(H25/H$27*100,0) -> 27.373456 | I57: =IFERROR(I25/I$27*100,0) -> 28.380156 | J57: =IFERROR(J25/J$27*100,0) -> 29.194455 | K57: =IFERROR(K25/K$27*100,0) -> 30.979077 | L57: =IFERROR(L25/L$27*100,0) -> 33.81883 | M57: =IFERROR(M25/M$27*100,0) -> 35.533768 | ... P57: =IFERROR(P25/P$27*100,0) -> 42.983494 | R57: =AVERAGEIF(E57:Q57,"<>0") -> 32.538886
C58: More personal computing % | F58: =IFERROR(F26/F$27*100,0) -> 43.902664 | G58: =IFERROR(G26/G$27*100,0) -> 46.414832 | H58: =IFERROR(H26/H$27*100,0) -> 44.331571 | I58: =IFERROR(I26/I$27*100,0) -> 40.689234 | J58: =IFERROR(J26/J$27*100,0) -> 38.307358 | K58: =IFERROR(K26/K$27*100,0) -> 36.313502 | L58: =IFERROR(L26/L$27*100,0) -> 33.738419 | M58: =IFERROR(M26/M$27*100,0) -> 32.390772 | ... P58: =IFERROR(P26/P$27*100,0) -> 25.306582 | R58: =AVERAGEIF(E58:Q58,"<>0") -> 36.132293
F59: =SUM(F56:F58) -> 100 | G59: =SUM(G56:G58) -> 100 | H59: =SUM(H56:H58) -> 100 | I59: =SUM(I56:I58) -> 100 | J59: =SUM(J56:J58) -> 100 | K59: =SUM(K56:K58) -> 100 | L59: =SUM(L56:L58) -> 100 | M59: =SUM(M56:M58) -> 100 | ... P59: =SUM(P56:P58) -> 100
C61: Revenue Growth By Product / Service Offering (%)
C62: Server products & cloud services | G62: =IFERROR((G11-F11)/ABS(F11)*100,0) -> 9.1292876 | H62: =IFERROR((H11-G11)/ABS(G11)*100,0) -> 28.239845 | I62: =IFERROR((I11-H11)/ABS(H11)*100,0) -> -9.2969666 | J62: =IFERROR((J11-I11)/ABS(I11)*100,0) -> 20.693796 | K62: =IFERROR((K11-J11)/ABS(J11)*100,0) -> 24.849784 | L62: =IFERROR((L11-K11)/ABS(K11)*100,0) -> 26.843848 | M62: =IFERROR((M11-L11)/ABS(L11)*100,0) -> 27.091037 | N62: =IFERROR((N11-M11)/ABS(M11)*100,0) -> 28.068608 | ... P62: =IFERROR((P11-O11)/ABS(O11)*100,0) -> 22.203326 | R62: =AVERAGEIF(E62:Q62,"<>0") -> 19.65605 | U62: {=_xlfn.STDEV.S(IF(E62:Q62<>0,E62:Q62))} -> 11.718311
C63: Office products & cloud services | G63: =IFERROR((G12-F12)/ABS(F12)*100,0) -> -3.2273979 | H63: =IFERROR((H12-G12)/ABS(G12)*100,0) -> -19.016059 | I63: =IFERROR((I12-H12)/ABS(H12)*100,0) -> 34.156961 | J63: =IFERROR((J12-I12)/ABS(I12)*100,0) -> 10.726156 | K63: =IFERROR((K12-J12)/ABS(J12)*100,0) -> 12.194519 | L63: =IFERROR((L12-K12)/ABS(K12)*100,0) -> 11.164972 | M63: =IFERROR((M12-L12)/ABS(L12)*100,0) -> 12.900668 | N63: =IFERROR((N12-M12)/ABS(M12)*100,0) -> 12.785915 | ... P63: =IFERROR((P12-O12)/ABS(O12)*100,0) -> 12.338274 | R63: =AVERAGEIF(E63:Q63,"<>0") -> 9.2647536 | U63: {=_xlfn.STDEV.S(IF(E63:Q63<>0,E63:Q63))} -> 13.43828
C64: Windows | G64: =IFERROR((G13-F13)/ABS(F13)*100,0) -> -12.043189 | H64: =IFERROR((H13-G13)/ABS(G13)*100,0) -> 18.359638 | I64: =IFERROR((I13-H13)/ABS(H13)*100,0) -> 5.9550946 | J64: =IFERROR((J13-I13)/ABS(I13)*100,0) -> 4.9749906 | K64: =IFERROR((K13-J13)/ABS(J13)*100,0) -> 4.4932882 | L64: =IFERROR((L13-K13)/ABS(K13)*100,0) -> 5.4670262 | M64: =IFERROR((M13-L13)/ABS(L13)*100,0) -> 4.5467225 | N64: =IFERROR((N13-M13)/ABS(M13)*100,0) -> 9.9786553 | ... P64: =IFERROR((P13-O13)/ABS(O13)*100,0) -> 8.0764402 | R64: =AVERAGEIF(E64:Q64,"<>0") -> 3.676888 | U64: {=_xlfn.STDEV.S(IF(E64:Q64<>0,E64:Q64))} -> 9.502763
C65: Gaming | G65: =IFERROR((G14-F14)/ABS(F14)*100,0) -> 5.5304871 | H65: =IFERROR((H14-G14)/ABS(G14)*100,0) -> 0.88806052 | I65: =IFERROR((I14-H14)/ABS(H14)*100,0) -> -1.6409476 | J65: =IFERROR((J14-I14)/ABS(I14)*100,0) -> 14.385151 | K65: =IFERROR((K14-J14)/ABS(J14)*100,0) -> 9.9777842 | L65: =IFERROR((L14-K14)/ABS(K14)*100,0) -> 1.6599333 | M65: =IFERROR((M14-L14)/ABS(L14)*100,0) -> 32.786177 | N65: =IFERROR((N14-M14)/ABS(M14)*100,0) -> 5.5953155 | ... P65: =IFERROR((P14-O14)/ABS(O14)*100,0) -> 39.03401 | R65: =AVERAGEIF(E65:Q65,"<>0") -> 10.350864 | U65: {=_xlfn.STDEV.S(IF(E65:Q65<>0,E65:Q65))} -> 14.620996
C66: LinkedIn | G66: =IFERROR((G15-F15)/ABS(F15)*100,0) -> 0 | H66: =IFERROR((H15-G15)/ABS(G15)*100,0) -> 0 | I66: =IFERROR((I15-H15)/ABS(H15)*100,0) -> 0 | J66: =IFERROR((J15-I15)/ABS(I15)*100,0) -> -15.436565 | K66: =IFERROR((K15-J15)/ABS(J15)*100,0) -> 28.427458 | L66: =IFERROR((L15-K15)/ABS(K15)*100,0) -> 19.588392 | M66: =IFERROR((M15-L15)/ABS(L15)*100,0) -> 27.386406 | N66: =IFERROR((N15-M15)/ABS(M15)*100,0) -> 32.481291 | ... P66: =IFERROR((P15-O15)/ABS(O15)*100,0) -> 9.2267663 | R66: =AVERAGEIF(E66:Q66,"<>0") -> 15.948048 | U66: {=_xlfn.STDEV.S(IF(E66:Q66<>0,E66:Q66))} -> 16.528598
C67: Search & news advertising | G67: =IFERROR((G16-F16)/ABS(F16)*100,0) -> 13.471116 | H67: =IFERROR((H16-G16)/ABS(G16)*100,0) -> 19.113452 | I67: =IFERROR((I16-H16)/ABS(H16)*100,0) -> -58.161385 | J67: =IFERROR((J16-I16)/ABS(I16)*100,0) -> 208.76266 | K67: =IFERROR((K16-J16)/ABS(J16)*100,0) -> 8.7849401 | L67: =IFERROR((L16-K16)/ABS(K16)*100,0) -> 11.746198 | M67: =IFERROR((M16-L16)/ABS(L16)*100,0) -> 8.716565 | N67: =IFERROR((N16-M16)/ABS(M16)*100,0) -> 24.376821 | ... P67: =IFERROR((P16-O16)/ABS(O16)*100,0) -> 3.4380655 | R67: =AVERAGEIF(E67:Q67,"<>0") -> 24.573169 | U67: {=_xlfn.STDEV.S(IF(E67:Q67<>0,E67:Q67))} -> 68.637717
C68: Enterprise & partner services | G68: =IFERROR((G17-F17)/ABS(F17)*100,0) -> 6.7757499 | H68: =IFERROR((H17-G17)/ABS(G17)*100,0) -> 11.178782 | I68: =IFERROR((I17-H17)/ABS(H17)*100,0) -> -2.0675031 | J68: =IFERROR((J17-I17)/ABS(I17)*100,0) -> -7.3619632 | K68: =IFERROR((K17-J17)/ABS(J17)*100,0) -> 19.28321 | L68: =IFERROR((L17-K17)/ABS(K17)*100,0) -> 4.653821 | M68: =IFERROR((M17-L17)/ABS(L17)*100,0) -> 8.3320331 | N68: =IFERROR((N17-M17)/ABS(M17)*100,0) -> 9.5347832 | ... P68: =IFERROR((P17-O17)/ABS(O17)*100,0) -> -3.8734177 | R68: =AVERAGEIF(E68:Q68,"<>0") -> 5.0334522 | U68: {=_xlfn.STDEV.S(IF(E68:Q68<>0,E68:Q68))} -> 7.8872466
C69: Dynamics products & cloud services | G69: =IFERROR((G18-F18)/ABS(F18)*100,0) -> 0 | H69: =IFERROR((H18-G18)/ABS(G18)*100,0) -> 0 | I69: =IFERROR((I18-H18)/ABS(H18)*100,0) -> 0 | J69: =IFERROR((J18-I18)/ABS(I18)*100,0) -> 0 | K69: =IFERROR((K18-J18)/ABS(J18)*100,0) -> 0 | L69: =IFERROR((L18-K18)/ABS(K18)*100,0) -> 0 | M69: =IFERROR((M18-L18)/ABS(L18)*100,0) -> 0 | N69: =IFERROR((N18-M18)/ABS(M18)*100,0) -> -34.383312 | ... P69: =IFERROR((P18-O18)/ABS(O18)*100,0) -> 19.201766 | R69: =AVERAGEIF(E69:Q69,"<>0") -> 0.27338673 | U69: {=_xlfn.STDEV.S(IF(E69:Q69<>0,E69:Q69))} -> 30.0562
C70: Devices | G70: =IFERROR((G19-F19)/ABS(F19)*100,0) -> 134.10008 | H70: =IFERROR((H19-G19)/ABS(G19)*100,0) -> -32.011722 | I70: =IFERROR((I19-H19)/ABS(H19)*100,0) -> -35.826572 | J70: =IFERROR((J19-I19)/ABS(I19)*100,0) -> 15.487949 | K70: =IFERROR((K19-J19)/ABS(J19)*100,0) -> 4.2593226 | L70: =IFERROR((L19-K19)/ABS(K19)*100,0) -> 5.9392945 | M70: =IFERROR((M19-L19)/ABS(L19)*100,0) -> -41.861546 | N70: =IFERROR((N19-M19)/ABS(M19)*100,0) -> 94.619073 | ... P70: =IFERROR((P19-O19)/ABS(O19)*100,0) -> -14.761819 | R70: =AVERAGEIF(E70:Q70,"<>0") -> 10.551209 | U70: {=_xlfn.STDEV.S(IF(E70:Q70<>0,E70:Q70))} -> 58.680992
C71: Other | G71: =IFERROR((G20-F20)/ABS(F20)*100,0) -> 0.27344378 | H71: =IFERROR((H20-G20)/ABS(G20)*100,0) -> -59.913378 | I71: =IFERROR((I20-H20)/ABS(H20)*100,0) -> 4.4817927 | J71: =IFERROR((J20-I20)/ABS(I20)*100,0) -> 6.9705094 | K71: =IFERROR((K20-J20)/ABS(J20)*100,0) -> 9.9176513 | L71: =IFERROR((L20-K20)/ABS(K20)*100,0) -> 22.736156 | M71: =IFERROR((M20-L20)/ABS(L20)*100,0) -> -90.100849 | N71: =IFERROR((N20-M20)/ABS(M20)*100,0) -> -37.533512 | ... P71: =IFERROR((P20-O20)/ABS(O20)*100,0) -> -62.184874 | R71: =AVERAGEIF(E71:Q71,"<>0") -> -25.42801 | U71: {=_xlfn.STDEV.S(IF(E71:Q71<>0,E71:Q71))} -> 38.866665
C73: Revenue Growth By Segment (%)
C74: Productivity & business processes | G74: =(G24-F24)/ABS(F24)*100 -> -2.0240214 | H74: =(H24-G24)/ABS(G24)*100 -> -2.4139236 | I74: =(I24-H24)/ABS(H24)*100 -> 15.811104 | J74: =(J24-I24)/ABS(I24)*100 -> 20.070305 | K74: =(K24-J24)/ABS(J24)*100 -> 14.763697 | L74: =(L24-K24)/ABS(K24)*100 -> 12.725948 | M74: =(M24-L24)/ABS(L24)*100 -> 16.201129 | N74: =(N24-M24)/ABS(M24)*100 -> 17.525735 | ... P74: =(P24-O24)/ABS(O24)*100 -> 12.203713 | R74: =AVERAGE(E74:Q74) -> 11.419075
C75: Intelligent Cloud | G75: =(G25-F25)/ABS(F25)*100 -> 9.1097308 | H75: =(H25-G25)/ABS(G25)*100 -> 5.2161079 | I75: =(I25-H25)/ABS(H25)*100 -> 9.8388907 | J75: =(J25-I25)/ABS(I25)*100 -> 17.557558 | K75: =(K25-J25)/ABS(J25)*100 -> 21.000031 | L75: =(L25-K25)/ABS(K25)*100 -> 24.063101 | M75: =(M25-L25)/ABS(L25)*100 -> 23.491709 | N75: =(N25-M25)/ABS(M25)*100 -> 25.510648 | ... P75: =(P25-O25)/ABS(O25)*100 -> 19.856212 | R75: =AVERAGE(E75:Q75) -> 17.290805
C76: More personal computing | G76: =(G26-F26)/ABS(F26)*100 -> 13.936834 | H76: =(H26-G26)/ABS(G26)*100 -> -6.9644296 | I76: =(I26-H26)/ABS(H26)*100 -> -2.7616927 | J76: =(J26-I26)/ABS(I26)*100 -> 7.5889449 | K76: =(K26-J26)/ABS(J26)*100 -> 8.0944271 | L76: =(L26-K26)/ABS(K26)*100 -> 5.5866778 | M76: =(M26-L26)/ABS(L26)*100 -> 12.83704 | N76: =(N26-M26)/ABS(M26)*100 -> 10.094591 | ... P76: =(P26-O26)/ABS(O26)*100 -> 13.333577 | R76: =AVERAGE(E76:Q76) -> 5.3059094
C77: TOTAL REVENUE GROWTH (%) | G77: =(G27-F27)/ABS(F27)*100 -> 7.7700874 | H77: =(H27-G27)/ABS(G27)*100 -> -2.5924343 | I77: =(I27-H27)/ABS(H27)*100 -> 5.9426904 | J77: =(J27-I27)/ABS(I27)*100 -> 14.278614 | K77: =(K27-J27)/ABS(J27)*100 -> 14.02954 | L77: =(L27-K27)/ABS(K27)*100 -> 13.645574 | M77: =(M27-L27)/ABS(L27)*100 -> 17.531727 | N77: =(N27-M27)/ABS(M27)*100 -> 17.956071 | ... P77: =(P27-O27)/ABS(O27)*100 -> 15.669962 | R77: =AVERAGE(E77:Q77) -> 11.111386 | S77: =MEDIAN(E77:Q77) -> 13.837557 | U77: =_xlfn.STDEV.S(E77:Q77) -> 6.4754408 | V77: =R77-U77 -> 4.6359452
C79: Operating Income Growth (%)
C80: Google Services | G80: =(G30-F30)/ABS(F30)*100 -> -6.3430466 | H80: =(H30-G30)/ABS(G30)*100 -> -11.43589 | I80: =(I30-H30)/ABS(H30)*100 -> -3.1218101 | J80: =(J30-I30)/ABS(I30)*100 -> 13.477917 | K80: =(K30-J30)/ABS(J30)*100 -> 25.495203 | L80: =(L30-K30)/ABS(K30)*100 -> 15.444849 | M80: =(M30-L30)/ABS(L30)*100 -> 30.052339 | N80: =(N30-M30)/ABS(M30)*100 -> 21.925178 | ... P80: =(P30-O30)/ABS(O30)*100 -> 18.57615 | R80: =AVERAGE(E80:Q80) -> 11.922414 | U80: =_xlfn.STDEV.S(E80:Q80) -> 14.095207
C81: Google Cloud | G81: =(G31-F31)/ABS(F31)*100 -> 16.066777 | H81: =(H31-G31)/ABS(G31)*100 -> -5.6513312 | I81: =(I31-H31)/ABS(H31)*100 -> -1.3190615 | J81: =(J31-I31)/ABS(I31)*100 -> 26.262737 | K81: =(K31-J31)/ABS(J31)*100 -> 20.791392 | L81: =(L31-K31)/ABS(K31)*100 -> 31.637931 | M81: =(M31-L31)/ABS(L31)*100 -> 44.460816 | N81: =(N31-M31)/ABS(M31)*100 -> 25.431604 | ... P81: =(P31-O31)/ABS(O31)*100 -> 30.88375 | R81: =AVERAGE(E81:Q81) -> 20.266274 | U81: =_xlfn.STDEV.S(E81:Q81) -> 15.21573
C82: Other Bets | G82: =(G32-F32)/ABS(F32)*100 -> -9.0990187 | H82: =(H32-G32)/ABS(G32)*100 -> 21.354269 | I82: =(I32-H32)/ABS(H32)*100 -> 42.568333 | J82: =(J32-I32)/ABS(I32)*100 -> 20.363018 | K82: =(K32-J32)/ABS(J32)*100 -> 20.829406 | L82: =(L32-K32)/ABS(K32)*100 -> 24.110764 | M82: =(M32-L32)/ABS(L32)*100 -> 20.005028 | N82: =(N32-M32)/ABS(M32)*100 -> 7.3111972 | ... P82: =(P32-O32)/ABS(O32)*100 -> 17.379939 | R82: =AVERAGE(E82:Q82) -> 14.5106 | U82: =_xlfn.STDEV.S(E82:Q82) -> 17.699984
C83: OPERATING INCOME GROWTH (%) | G83: =(G34-F34)/ABS(F34)*100 -> -34.576173 | H83: =(H34-G34)/ABS(G34)*100 -> 43.593414 | I83: =(I34-H34)/ABS(H34)*100 -> 11.300713 | J83: =(J34-I34)/ABS(I34)*100 -> 20.78553 | K83: =(K34-J34)/ABS(J34)*100 -> 22.536939 | L83: =(L34-K34)/ABS(K34)*100 -> 23.278009 | M83: =(M34-L34)/ABS(L34)*100 -> 32.019109 | N83: =(N34-M34)/ABS(M34)*100 -> 19.261685 | ... P83: =(P34-O34)/ABS(O34)*100 -> 23.62098 | R83: =AVERAGE(E83:Q83) -> 16.798453 | S83: =MEDIAN(E83:Q83) -> 21.661234 | U83: =_xlfn.STDEV.S(E83:Q83) -> 20.751777
B87: P&L
B88: Revenue
C89: Product | F89: 72948 | G89: 75956 | H89: 67336 | I89: 63811 | J89: 64497 | K89: 66069 | L89: 68041 | M89: 71074 | N89: 72732 | O89: 64699 | P89: 64773
C90: Service & other | F90: 13885 | G90: 17624 | H90: 23818 | I90: 32760 | J90: 45863 | K90: 59774 | L90: 74974 | M90: 97014 | N90: 125538 | O90: 147216 | P90: 180349
F91: =SUM(F89:F90) -> 86833 | G91: =SUM(G89:G90) -> 93580 | H91: =SUM(H89:H90) -> 91154 | I91: =SUM(I89:I90) -> 96571 | J91: =SUM(J89:J90) -> 110360 | K91: =SUM(K89:K90) -> 125843 | L91: =SUM(L89:L90) -> 143015 | M91: =SUM(M89:M90) -> 168088 | ... P91: =SUM(P89:P90) -> 245122
B92: Cost of Revenue
C93: Product | F93: 16681 | G93: 21410 | H93: 17880 | I93: 15175 | J93: 15420 | K93: 16273 | L93: 16017 | M93: 18219 | N93: 19064 | O93: 17804 | P93: 15272
C94: Service & other | F94: 10397 | G94: 11628 | H94: 14900 | I94: 19086 | J94: 22933 | K94: 26637 | L94: 30061 | M94: 34013 | N94: 43586 | O94: 48059 | P94: 58842
F95: =SUM(F93:F94) -> 27078 | G95: =SUM(G93:G94) -> 33038 | H95: =SUM(H93:H94) -> 32780 | I95: =SUM(I93:I94) -> 34261 | J95: =SUM(J93:J94) -> 38353 | K95: =SUM(K93:K94) -> 42910 | L95: =SUM(L93:L94) -> 46078 | M95: =SUM(M93:M94) -> 52232 | ... P95: =SUM(P93:P94) -> 74114
B97: Gross Profit | F97: =F91-F95 -> 59755 | G97: =G91-G95 -> 60542 | H97: =H91-H95 -> 58374 | I97: =I91-I95 -> 62310 | J97: =J91-J95 -> 72007 | K97: =K91-K95 -> 82933 | L97: =L91-L95 -> 96937 | M97: =M91-M95 -> 115856 | ... P97: =P91-P95 -> 171008
C98: GP margin (%) | F98: =IFERROR(F97/F91*100,0) -> 68.816003 | G98: =IFERROR(G97/G91*100,0) -> 64.695448 | H98: =IFERROR(H97/H91*100,0) -> 64.038879 | I98: =IFERROR(I97/I91*100,0) -> 64.522476 | J98: =IFERROR(J97/J91*100,0) -> 65.247372 | K98: =IFERROR(K97/K91*100,0) -> 65.901957 | L98: =IFERROR(L97/L91*100,0) -> 67.781002 | M98: =IFERROR(M97/M91*100,0) -> 68.925801 | ... P98: =IFERROR(P97/P91*100,0) -> 69.764444 | R98: =AVERAGE(E98:Q98) -> 67.001377
B100: Research & Development | F100: 11381 | G100: 12046 | H100: 11988 | I100: 13037 | J100: 14726 | K100: 16876 | L100: 19269 | M100: 20716 | N100: 24512 | O100: 27195 | P100: 29510 | R100: =AVERAGE(E100:Q100)/AVERAGE($E$91:$Q$91)*100 -> 12.812725
B101: Sales & Marketing | F101: 15811 | G101: 15713 | H101: 14635 | I101: 15461 | J101: 17469 | K101: 18213 | L101: 19598 | M101: 20117 | N101: 21825 | O101: 22759 | P101: 24456 | R101: =AVERAGE(E101:Q101)/AVERAGE($E$91:$Q$91)*100 -> 13.118375
B102: General & Admin | F102: 4677 | G102: 4611 | H102: 4563 | I102: =4481 -> 4481 | J102: 4754 | K102: 4885 | L102: 5111 | M102: 5107 | N102: 5900 | O102: 7575 | P102: 7609 | R102: =AVERAGE(E102:Q102)/AVERAGE($E$91:$Q$91)*100 -> 3.7735453
B103: Impairment & restructuring | F103: 127 | G103: 10011 | H103: 1110 | I103: 306 | J103: 0 | K103: 0 | L103: 0 | M103: 0 | N103: 0 | O103: 0 | P103: 0 | R103: =AVERAGE(E103:Q103)/AVERAGE($E$91:$Q$91)*100 -> 0.73557171
B104: Total Cost & Expenses | F104: =SUM(F100:F103) -> 31996 | G104: =SUM(G100:G103) -> 42381 | H104: =SUM(H100:H103) -> 32296 | I104: =SUM(I100:I103) -> 33285 | J104: =SUM(J100:J103) -> 36949 | K104: =SUM(K100:K103) -> 39974 | L104: =SUM(L100:L103) -> 43978 | M104: =SUM(M100:M103) -> 45940 | ... P104: =SUM(P100:P103) -> 61575
B106: Operating Income | F106: =F97-F104 -> 27759 | G106: =G97-G104 -> 18161 | H106: =H97-H104 -> 26078 | I106: =I97-I104 -> 29025 | J106: =J97-J104 -> 35058 | K106: =K97-K104 -> 42959 | L106: =L97-L104 -> 52959 | M106: =M97-M104 -> 69916 | ... P106: =P97-P104 -> 109433
C107: Operating margin (%) | F107: =IFERROR(F106/F91*100,0) -> 31.968261 | G107: =IFERROR(G106/G91*100,0) -> 19.406925 | H107: =IFERROR(H106/H91*100,0) -> 28.608728 | I107: =IFERROR(I106/I91*100,0) -> 30.055607 | J107: =IFERROR(J106/J91*100,0) -> 31.766945 | K107: =IFERROR(K106/K91*100,0) -> 34.13698 | L107: =IFERROR(L106/L91*100,0) -> 37.030381 | M107: =IFERROR(M106/M91*100,0) -> 41.594879 | ... P107: =IFERROR(P106/P91*100,0) -> 44.6443 | R107: =AVERAGE(E107:Q107) -> 34.821924
B109: Other Income / (expense), Net | F109: 61 | G109: 346 | H109: -439 | I109: 876 | J109: 1416 | K109: 729 | L109: 77 | M109: 1186 | N109: 333 | O109: 788 | P109: -1646 | R109: =AVERAGE(E109:Q109)/AVERAGE(E91:Q91)*100 -> 0.23727504
B111: Income before taxation | F111: =F106+F109 -> 27820 | G111: =G106+G109 -> 18507 | H111: =H106+H109 -> 25639 | I111: =I106+I109 -> 29901 | J111: =J106+J109 -> 36474 | K111: =K106+K109 -> 43688 | L111: =L106+L109 -> 53036 | M111: =M106+M109 -> 71102 | ... P111: =P106+P109 -> 107787
B113: Provision for income taxes | F113: 5746 | G113: 6314 | H113: 5100 | I113: 4412 | J113: 19903 | K113: 4448 | L113: 8755 | M113: 9831 | N113: 10978 | O113: 16950 | P113: 19651 | R113: =AVERAGE(E113:Q113)/AVERAGE(E111:Q111)*100 -> 19.095678
B115: Net Income | F115: =F111-F113 -> 22074 | G115: =G111-G113 -> 12193 | H115: =H111-H113 -> 20539 | I115: =I111-I113 -> 25489 | J115: =J111-J113 -> 16571 | K115: =K111-K113 -> 39240 | L115: =L111-L113 -> 44281 | M115: =M111-M113 -> 61271 | ... P115: =P111-P113 -> 88136
C116: Net income margin (%) | F116: =IFERROR(F115/F91*100,0) -> 25.421211 | G116: =IFERROR(G115/G91*100,0) -> 13.029493 | H116: =IFERROR(H115/H91*100,0) -> 22.532198 | I116: =IFERROR(I115/I91*100,0) -> 26.394052 | J116: =IFERROR(J115/J91*100,0) -> 15.015404 | K116: =IFERROR(K115/K91*100,0) -> 31.181711 | L116: =IFERROR(L115/L91*100,0) -> 30.962486 | M116: =IFERROR(M115/M91*100,0) -> 36.45174 | ... P116: =IFERROR(P115/P91*100,0) -> 35.955973 | R116: =AVERAGE(E116:Q116) -> 27.979713
C119: Valuation Multiples / Shareholder ratios
C120: No. of Shares | F120: 8239 | G120: 8027 | H120: 7808 | I120: 7708 | J120: 7677 | K120: 7643 | L120: 7571 | M120: 7519 | N120: 7464 | O120: 7432 | P120: 7434
C121: Share Price | F121: 43.16 | G121: 46.7 | H121: 56.68 | I121: 72.7 | J121: 106.08 | K121: 136.27 | L121: 205.01 | M121: 284.91 | N121: 280.74 | O121: 335.92 | P121: 418.35 | T121: =((P121/F121)^(1/(P3-F3))-1)*100 -> 25.500609
C122: EPS | F122: =IFERROR(F115/F120,0) -> 2.6792086 | G122: =IFERROR(G115/G120,0) -> 1.5189984 | H122: =IFERROR(H115/H120,0) -> 2.6305072 | I122: =IFERROR(I115/I120,0) -> 3.3068241 | J122: =IFERROR(J115/J120,0) -> 2.1585255 | K122: =IFERROR(K115/K120,0) -> 5.1341096 | L122: =IFERROR(L115/L120,0) -> 5.848765 | M122: =IFERROR(M115/M120,0) -> 8.148823 | ... P122: =IFERROR(P115/P120,0) -> 11.855798
C123: P/E | F123: =F121/F122 -> 16.109234 | G123: =G121/G122 -> 30.743943 | H123: =H121/H122 -> 21.547176 | I123: =I121/I122 -> 21.984841 | J123: =J121/J122 -> 49.14466 | K123: =K121/K122 -> 26.54209 | L123: =L121/L122 -> 35.051844 | M123: =M121/M122 -> 34.963332 | ... P123: =P121/P122 -> 35.286533 | R123: =AVERAGE(E123:Q123) -> 30.425743 | U123: =_xlfn.STDEV.S(E123:Q123) -> 8.9747859 | V123: =R123-U123 -> 21.450957
...

Sheet Sharpe, Sortino
B3: MSFT Monthly Price Changes (5 years) | L3: United States 10-Year Bond Yield
B4: https://www.investing.com/equities/microsoft-corp-historical-data | L4: https://www.investing.com/rates-bonds/u.s.-10-year-bond-yield-historical-data
B5: Jul'19 - Jun'24 | L5: Risk free rate average | O5: =[1]Sheet1!$E$6 -> 0.0246945 | S5: TEST (Manual calculation of Monthly Std Dev of Excess Returns - 5 Years)
F7: [1] | G7: [2] | H7: [1] - [2] | J7: [1] - [2] | S7: Sharpe | X7: Sortino
B8: Date | C8: Price | D8: Change % | F8: Change | G8: Monthly Risk free rate | H8: Monthly Excess returns | J8: Monthly Excess negative returns | S8: Average Monthly Excess Returns | U8: Difference Squared | V8: Monthly Std Dev of excess returns (σ) | X8: Average Monthly Excess Negative Returns | Y8: Difference Squared | Z8: Monthly Std Dev of excess returns (σ)
A9: 1 | B9: 45444 | C9: 446.95 | D9: 0.0767 | F9: =D9 -> 0.0767 | G9: =O$5/12 -> 0.002057875 | H9: =F9-G9 -> 0.074642125 | J9: =IF(H9<0,H9,"") | L9: Sharpe Ratio | O9: 1 Year | P9: 3 Years | Q9: 5 Years | S9: =AVERAGE(H9:H68) -> 0.020137125 | T9: 1 | U9: =(H9-S$9)^2 -> 0.002970795 | V9: =(U70/T68)^(1/2) -> 0.06239792 | X9: =AVERAGE(J9:J68) -> -0.045007875 | Y9: =IF(J9="","",(J9-X$9)^2) | Z9: =(Y70/(COUNT(Y9:Y69)-1))^(1/2) -> 0.032023455
A10: 2 | B10: 45413 | C10: 415.13 | D10: 0.0663 | F10: =D10 -> 0.0663 | G10: =O$5/12 -> 0.002057875 | H10: =F10-G10 -> 0.064242125 | J10: =IF(H10<0,H10,"") | T10: 2 | U10: =(H10-S$9)^2 -> 0.001945251 | Y10: =IF(J10="","",(J10-X$9)^2)
A11: 3 | B11: 45383 | C11: 389.33 | D11: -0.0746 | F11: =D11 -> -0.0746 | G11: =O$5/12 -> 0.002057875 | H11: =F11-G11 -> -0.076657875 | J11: =IF(H11<0,H11,"") -> -0.076657875 | L11: Monthly Std Dev of excess returns (σ) | O11: =STDEV.P(H9:H20) -> 0.054521354 | P11: =STDEV.P(H9:H44) -> 0.069019254 | Q11: =STDEV.P(H9:H68) -> 0.06239792 | T11: 3 | U11: =(H11-S$9)^2 -> 0.009369272 | Y11: =IF(J11="","",(J11-X$9)^2) -> 0.0010017225
A12: 4 | B12: 45352 | C12: 420.72 | D12: 0.0171 | F12: =D12 -> 0.0171 | G12: =O$5/12 -> 0.002057875 | H12: =F12-G12 -> 0.015042125 | J12: =IF(H12<0,H12,"") | L12: Monthly Portfolio return (Rp) | O12: =(1+O19)^(1/12)-1 -> 0.024083235 | P12: =(1+P19)^(1/12)-1 -> 0.012586141 | Q12: =(1+Q19)^(1/12)-1 -> 0.019994065 | T12: 4 | U12: =(H12-S$9)^2 -> 2.5959025e-05 | Y12: =IF(J12="","",(J12-X$9)^2)
A13: 5 | B13: 45323 | C13: 413.64 | D13: 0.0404 | F13: =D13 -> 0.0404 | G13: =O$5/12 -> 0.002057875 | H13: =F13-G13 -> 0.038342125 | J13: =IF(H13<0,H13,"") | L13: Monthly Risk-free return - US 10Yr Yield (Rf) | O13: =O20/12 -> 0.002057875 | P13: =P20/12 -> 0.002057875 | Q13: =Q20/12 -> 0.002057875 | T13: 5 | U13: =(H13-S$9)^2 -> 0.00033142203 | Y13: =IF(J13="","",(J13-X$9)^2)
A14: 6 | B14: 45292 | C14: 397.58 | D14: 0.0573 | F14: =D14 -> 0.0573 | G14: =O$5/12 -> 0.002057875 | H14: =F14-G14 -> 0.055242125 | J14: =IF(H14<0,H14,"") | L14: Excess return (Rp - Rf) | O14: =O12-O13 -> 0.02202536 | P14: =P12-P13 -> 0.010528266 | Q14: =Q12-Q13 -> 0.01793619 | T14: 6 | U14: =(H14-S$9)^2 -> 0.001232361 | Y14: =IF(J14="","",(J14-X$9)^2)
A15: 7 | B15: 45261 | C15: 376.04 | D15: -0.0076 | F15: =D15 -> -0.0076 | G15: =O$5/12 -> 0.002057875 | H15: =F15-G15 -> -0.009657875 | J15: =IF(H15<0,H15,"") -> -0.009657875 | T15: 7 | U15: =(H15-S$9)^2 -> 0.00088774202 | Y15: =IF(J15="","",(J15-X$9)^2) -> 0.0012496225
A16: 8 | B16: 45231 | C16: 378.91 | D16: 0.1207 | F16: =D16 -> 0.1207 | G16: =O$5/12 -> 0.002057875 | H16: =F16-G16 -> 0.11864213 | J16: =IF(H16<0,H16,"") | L16: Monthly Sharpe Ratio ( [Rp - Rf] / σ ) | O16: =O14/O11 -> 0.40397677 | P16: =P14/P11 -> 0.152541 | Q16: =Q14/Q11 -> 0.28744852 | T16: 8 | U16: =(H16-S$9)^2 -> 0.009703235 | Y16: =IF(J16="","",(J16-X$9)^2)
A17: 9 | B17: 45200 | C17: 338.11 | D17: 0.0708 | F17: =D17 -> 0.0708 | G17: =O$5/12 -> 0.002057875 | H17: =F17-G17 -> 0.068742125 | J17: =IF(H17<0,H17,"") | T17: 9 | U17: =(H17-S$9)^2 -> 0.002362446 | Y17: =IF(J17="","",(J17-X$9)^2)
A18: 10 | B18: 45170 | C18: 315.75 | D18: -0.0366 | F18: =D18 -> -0.0366 | G18: =O$5/12 -> 0.002057875 | H18: =F18-G18 -> -0.038657875 | J18: =IF(H18<0,H18,"") -> -0.038657875 | L18: Annualized Std Dev of excess returns (σ) | O18: =O11*12^(1/2) -> 0.18886751 | P18: =P11*12^(1/2) -> 0.23908971 | Q18: =Q11*12^(1/2) -> 0.21615274 | T18: 10 | U18: =(H18-S$9)^2 -> 0.003456852 | Y18: =IF(J18="","",(J18-X$9)^2) -> 4.03225e-05
A19: 11 | B19: 45139 | C19: 327.76 | D19: -0.0243 | F19: =D19 -> -0.0243 | G19: =O$5/12 -> 0.002057875 | H19: =F19-G19 -> -0.026357875 | J19: =IF(H19<0,H19,"") -> -0.026357875 | L19: Annualized Portfolio return (Rp) | O19: =($C$9/$C$20)^(1/($A$20/12))-1 -> 0.33052513 | P19: =($C$9/$C$44)^(1/($A$44/12))-1 -> 0.16194013 | Q19: =($C$9/$C$68)^(1/($A$68/12))-1 -> 0.26815324 | T19: 11 | U19: =(H19-S$9)^2 -> 0.002161785 | Y19: =IF(J19="","",(J19-X$9)^2) -> 0.0003478225
A20: 12 | B20: 45108 | C20: 335.92 | D20: -0.0136 | F20: =D20 -> -0.0136 | G20: =O$5/12 -> 0.002057875 | H20: =F20-G20 -> -0.015657875 | J20: =IF(H20<0,H20,"") -> -0.015657875 | L20: Annualized Risk-free return - US 10Yr Yield (Rf) | O20: =$O$5 -> 0.0246945 | P20: =$O$5 -> 0.0246945 | Q20: =$O$5 -> 0.0246945 | T20: 12 | U20: =(H20-S$9)^2 -> 0.001281282 | Y20: =IF(J20="","",(J20-X$9)^2) -> 0.0008614225
A21: 13 | B21: 45078 | C21: 340.54 | D21: 0.037 | F21: =D21 -> 0.037 | G21: =O$5/12 -> 0.002057875 | H21: =F21-G21 -> 0.034942125 | J21: =IF(H21<0,H21,"") | L21: Excess return (Rp - Rf) | O21: =O19-O20 -> 0.30583063 | P21: =P19-P20 -> 0.13724563 | Q21: =Q19-Q20 -> 0.24345874 | T21: 13 | U21: =(H21-S$9)^2 -> 0.00021918802 | Y21: =IF(J21="","",(J21-X$9)^2)
A22: 14 | B22: 45047 | C22: 328.39 | D22: 0.0688 | F22: =D22 -> 0.0688 | G22: =O$5/12 -> 0.002057875 | H22: =F22-G22 -> 0.066742125 | J22: =IF(H22<0,H22,"") | T22: 14 | U22: =(H22-S$9)^2 -> 0.002172026 | Y22: =IF(J22="","",(J22-X$9)^2)
A23: 15 | B23: 45017 | C23: 307.26 | D23: 0.0658 | F23: =D23 -> 0.0658 | G23: =O$5/12 -> 0.002057875 | H23: =F23-G23 -> 0.063742125 | J23: =IF(H23<0,H23,"") | L23: Annualized Sharpe Ratio ( [Rp - Rf] / σ ) | O23: =O21/O18 -> 1.6192866 | P23: =P21/P18 -> 0.57403401 | Q23: =Q21/Q18 -> 1.1263274 | T23: 15 | U23: =(H23-S$9)^2 -> 0.001901396 | Y23: =IF(J23="","",(J23-X$9)^2)
A24: 16 | B24: 44986 | C24: 288.3 | D24: 0.1559 | F24: =D24 -> 0.1559 | G24: =O$5/12 -> 0.002057875 | H24: =F24-G24 -> 0.15384212 | J24: =IF(H24<0,H24,"") | T24: 16 | U24: =(H24-S$9)^2 -> 0.017877027 | Y24: =IF(J24="","",(J24-X$9)^2)
A25: 17 | B25: 44958 | C25: 249.42 | D25: 0.0065 | F25: =D25 -> 0.0065 | G25: =O$5/12 -> 0.002057875 | H25: =F25-G25 -> 0.004442125 | J25: =IF(H25<0,H25,"") | T25: 17 | U25: =(H25-S$9)^2 -> 0.00024633303 | Y25: =IF(J25="","",(J25-X$9)^2)
A26: 18 | B26: 44927 | C26: 247.81 | D26: 0.0333 | F26: =D26 -> 0.0333 | G26: =O$5/12 -> 0.002057875 | H26: =F26-G26 -> 0.031242125 | J26: =IF(H26<0,H26,"") | L26: Sortino Ratio | O26: 1 Year | P26: 3 Years | Q26: 5 Years | T26: 18 | U26: =(H26-S$9)^2 -> 0.00012332103 | Y26: =IF(J26="","",(J26-X$9)^2)
A27: 19 | B27: 44896 | C27: 239.82 | D27: -0.06 | F27: =D27 -> -0.06 | G27: =O$5/12 -> 0.002057875 | H27: =F27-G27 -> -0.062057875 | J27: =IF(H27<0,H27,"") -> -0.062057875 | T27: 19 | U27: =(H27-S$9)^2 -> 0.006756018 | Y27: =IF(J27="","",(J27-X$9)^2) -> 0.0002907025
A28: 20 | B28: 44866 | C28: 255.14 | D28: 0.0991 | F28: =D28 -> 0.0991 | G28: =O$5/12 -> 0.002057875 | H28: =F28-G28 -> 0.097042125 | J28: =IF(H28<0,H28,"") | L28: Monthly Std Dev of excess negative returns (σd) | O28: =_xlfn.STDEV.S(J9:J20) -> 0.026584544 | P28: =_xlfn.STDEV.S(J9:J44) -> 0.033868953 | Q28: =_xlfn.STDEV.S(J9:J68) -> 0.032023455 | T28: 20 | U28: =(H28-S$9)^2 -> 0.005914379 | Y28: =IF(J28="","",(J28-X$9)^2)
A29: 21 | B29: 44835 | C29: 232.13 | D29: -0.0033 | F29: =D29 -> -0.0033 | G29: =O$5/12 -> 0.002057875 | H29: =F29-G29 -> -0.005357875 | J29: =IF(H29<0,H29,"") -> -0.005357875 | L29: Monthly Portfolio return (Rp) | O29: =(1+O36)^(1/12)-1 -> 0.024083235 | P29: =(1+P36)^(1/12)-1 -> 0.012586141 | Q29: =(1+Q36)^(1/12)-1 -> 0.019994065 | T29: 21 | U29: =(H29-S$9)^2 -> 0.00064999503 | Y29: =IF(J29="","",(J29-X$9)^2) -> 0.0015721225
A30: 22 | B30: 44805 | C30: 232.9 | D30: -0.1093 | F30: =D30 -> -0.1093 | G30: =O$5/12 -> 0.002057875 | H30: =F30-G30 -> -0.11135787 | J30: =IF(H30<0,H30,"") -> -0.11135787 | L30: Monthly Risk-free return - US 10Yr Yield (Rf) | O30: =O37/12 -> 0.002057875 | P30: =P37/12 -> 0.002057875 | Q30: =Q37/12 -> 0.002057875 | T30: 22 | U30: =(H30-S$9)^2 -> 0.017290935 | Y30: =IF(J30="","",(J30-X$9)^2) -> 0.0044023225
A31: 23 | B31: 44774 | C31: 261.47 | D31: -0.0686 | F31: =D31 -> -0.0686 | G31: =O$5/12 -> 0.002057875 | H31: =F31-G31 -> -0.070657875 | J31: =IF(H31<0,H31,"") -> -0.070657875 | L31: Excess return (Rp - Rf) | O31: =O29-O30 -> 0.02202536 | P31: =P29-P30 -> 0.010528266 | Q31: =Q29-Q30 -> 0.01793619 | T31: 23 | U31: =(H31-S$9)^2 -> 0.008243732 | Y31: =IF(J31="","",(J31-X$9)^2) -> 0.0006579225
A32: 24 | B32: 44743 | C32: 280.74 | D32: 0.0931 | F32: =D32 -> 0.0931 | G32: =O$5/12 -> 0.002057875 | H32: =F32-G32 -> 0.091042125 | J32: =IF(H32<0,H32,"") | T32: 24 | U32: =(H32-S$9)^2 -> 0.005027519 | Y32: =IF(J32="","",(J32-X$9)^2)
A33: 25 | B33: 44713 | C33: 256.83 | D33: -0.0553 | F33: =D33 -> -0.0553 | G33: =O$5/12 -> 0.002057875 | H33: =F33-G33 -> -0.057357875 | J33: =IF(H33<0,H33,"") -> -0.057357875 | L33: Monthly Sortino Ratio ( [Rp - Rf] / σ ) | O33: =O31/O28 -> 0.82850246 | P33: =P31/P28 -> 0.31085302 | Q33: =Q31/Q28 -> 0.56009541 | T33: 25 | U33: =(H33-S$9)^2 -> 0.006005475 | Y33: =IF(J33="","",(J33-X$9)^2) -> 0.0001525225
A34: 26 | B34: 44682 | C34: 271.87 | D34: -0.0204 | F34: =D34 -> -0.0204 | G34: =O$5/12 -> 0.002057875 | H34: =F34-G34 -> -0.022457875 | J34: =IF(H34<0,H34,"") -> -0.022457875 | T34: 26 | U34: =(H34-S$9)^2 -> 0.001814334 | Y34: =IF(J34="","",(J34-X$9)^2) -> 0.0005085025
A35: 27 | B35: 44652 | C35: 277.52 | D35: -0.0999 | F35: =D35 -> -0.0999 | G35: =O$5/12 -> 0.002057875 | H35: =F35-G35 -> -0.10195788 | J35: =IF(H35<0,H35,"") -> -0.10195788 | L35: Annualized Std Dev of excess negative returns (σ) | O35: =O28*12^(1/2) -> 0.092091563 | P35: =P28*12^(1/2) -> 0.1173255 | Q35: =Q28*12^(1/2) -> 0.1109325 | T35: 27 | U35: =(H35-S$9)^2 -> 0.014907189 | Y35: =IF(J35="","",(J35-X$9)^2) -> 0.0032433025
A36: 28 | B36: 44621 | C36: 308.31 | D36: 0.0319 | F36: =D36 -> 0.0319 | G36: =O$5/12 -> 0.002057875 | H36: =F36-G36 -> 0.029842125 | J36: =IF(H36<0,H36,"") | L36: Annualized Portfolio return (Rp) | O36: =($C$9/$C$20)^(1/($A$20/12))-1 -> 0.33052513 | P36: =($C$9/$C$44)^(1/($A$44/12))-1 -> 0.16194013 | Q36: =($C$9/$C$68)^(1/($A$68/12))-1 -> 0.26815324 | T36: 28 | U36: =(H36-S$9)^2 -> 9.4187025e-05 | Y36: =IF(J36="","",(J36-X$9)^2)
A37: 29 | B37: 44593 | C37: 298.79 | D37: -0.0392 | F37: =D37 -> -0.0392 | G37: =O$5/12 -> 0.002057875 | H37: =F37-G37 -> -0.041257875 | J37: =IF(H37<0,H37,"") -> -0.041257875 | L37: Annualized Risk-free return - US 10Yr Yield (Rf) | O37: =$O$5 -> 0.0246945 | P37: =$O$5 -> 0.0246945 | Q37: =$O$5 -> 0.0246945 | T37: 29 | U37: =(H37-S$9)^2 -> 0.003769346 | Y37: =IF(J37="","",(J37-X$9)^2) -> 1.40625e-05
A38: 30 | B38: 44562 | C38: 310.98 | D38: -0.0753 | F38: =D38 -> -0.0753 | G38: =O$5/12 -> 0.002057875 | H38: =F38-G38 -> -0.077357875 | J38: =IF(H38<0,H38,"") -> -0.077357875 | L38: Excess return (Rp - Rf) | O38: =O36-O37 -> 0.30583063 | P38: =P36-P37 -> 0.13724563 | Q38: =Q36-Q37 -> 0.24345874 | T38: 30 | U38: =(H38-S$9)^2 -> 0.009505275 | Y38: =IF(J38="","",(J38-X$9)^2) -> 0.0010465225
A39: 31 | B39: 44531 | C39: 336.32 | D39: 0.0173 | F39: =D39 -> 0.0173 | G39: =O$5/12 -> 0.002057875 | H39: =F39-G39 -> 0.015242125 | J39: =IF(H39<0,H39,"") | T39: 31 | U39: =(H39-S$9)^2 -> 2.3961025e-05 | Y39: =IF(J39="","",(J39-X$9)^2)
A40: 32 | B40: 44501 | C40: 330.59 | D40: -0.0031 | F40: =D40 -> -0.0031 | G40: =O$5/12 -> 0.002057875 | H40: =F40-G40 -> -0.005157875 | J40: =IF(H40<0,H40,"") -> -0.005157875 | L40: Annualized Sortino Ratio ( [Rp - Rf] / σd ) | O40: =O38/O35 -> 3.3209408 | P40: =P38/P35 -> 1.1697852 | Q40: =Q38/Q35 -> 2.1946566 | T40: 32 | U40: =(H40-S$9)^2 -> 0.00063983702 | Y40: =IF(J40="","",(J40-X$9)^2) -> 0.0015880225
A41: 33 | B41: 44470 | C41: 331.62 | D41: 0.1763 | F41: =D41 -> 0.1763 | G41: =O$5/12 -> 0.002057875 | H41: =F41-G41 -> 0.17424212 | J41: =IF(H41<0,H41,"") | T41: 33 | U41: =(H41-S$9)^2 -> 0.023748351 | Y41: =IF(J41="","",(J41-X$9)^2)
A42: 34 | B42: 44440 | C42: 281.92 | D42: -0.0661 | F42: =D42 -> -0.0661 | G42: =O$5/12 -> 0.002057875 | H42: =F42-G42 -> -0.068157875 | J42: =IF(H42<0,H42,"") -> -0.068157875 | T42: 34 | U42: =(H42-S$9)^2 -> 0.007796007 | Y42: =IF(J42="","",(J42-X$9)^2) -> 0.0005359225
A43: 35 | B43: 44409 | C43: 301.88 | D43: 0.0596 | F43: =D43 -> 0.0596 | G43: =O$5/12 -> 0.002057875 | H43: =F43-G43 -> 0.057542125 | J43: =IF(H43<0,H43,"") | T43: 35 | U43: =(H43-S$9)^2 -> 0.001399134 | Y43: =IF(J43="","",(J43-X$9)^2)
A44: 36 | B44: 44378 | C44: 284.91 | D44: 0.0517 | F44: =D44 -> 0.0517 | G44: =O$5/12 -> 0.002057875 | H44: =F44-G44 -> 0.049642125 | J44: =IF(H44<0,H44,"") | T44: 36 | U44: =(H44-S$9)^2 -> 0.00087054503 | Y44: =IF(J44="","",(J44-X$9)^2)
A45: 37 | B45: 44348 | C45: 270.9 | D45: 0.085 | F45: =D45 -> 0.085 | G45: =O$5/12 -> 0.002057875 | H45: =F45-G45 -> 0.082942125 | J45: =IF(H45<0,H45,"") | T45: 37 | U45: =(H45-S$9)^2 -> 0.003944468 | Y45: =IF(J45="","",(J45-X$9)^2)
A46: 38 | B46: 44317 | C46: 249.68 | D46: -0.0099 | F46: =D46 -> -0.0099 | G46: =O$5/12 -> 0.002057875 | H46: =F46-G46 -> -0.011957875 | J46: =IF(H46<0,H46,"") -> -0.011957875 | T46: 38 | U46: =(H46-S$9)^2 -> 0.001030089 | Y46: =IF(J46="","",(J46-X$9)^2) -> 0.0010923025
A47: 39 | B47: 44287 | C47: 252.18 | D47: 0.0696 | F47: =D47 -> 0.0696 | G47: =O$5/12 -> 0.002057875 | H47: =F47-G47 -> 0.067542125 | J47: =IF(H47<0,H47,"") | T47: 39 | U47: =(H47-S$9)^2 -> 0.002247234 | Y47: =IF(J47="","",(J47-X$9)^2)
A48: 40 | B48: 44256 | C48: 235.77 | D48: 0.0146 | F48: =D48 -> 0.0146 | G48: =O$5/12 -> 0.002057875 | H48: =F48-G48 -> 0.012542125 | J48: =IF(H48<0,H48,"") | T48: 40 | U48: =(H48-S$9)^2 -> 5.7684025e-05 | Y48: =IF(J48="","",(J48-X$9)^2)
A49: 41 | B49: 44228 | C49: 232.38 | D49: 0.0018 | F49: =D49 -> 0.0018 | G49: =O$5/12 -> 0.002057875 | H49: =F49-G49 -> -0.000257875 | J49: =IF(H49<0,H49,"") -> -0.000257875 | T49: 41 | U49: =(H49-S$9)^2 -> 0.00041595602 | Y49: =IF(J49="","",(J49-X$9)^2) -> 0.0020025625
A50: 42 | B50: 44197 | C50: 231.96 | D50: 0.0429 | F50: =D50 -> 0.0429 | G50: =O$5/12 -> 0.002057875 | H50: =F50-G50 -> 0.040842125 | J50: =IF(H50<0,H50,"") | T50: 42 | U50: =(H50-S$9)^2 -> 0.00042869702 | Y50: =IF(J50="","",(J50-X$9)^2)
A51: 43 | B51: 44166 | C51: 222.42 | D51: 0.039 | F51: =D51 -> 0.039 | G51: =O$5/12 -> 0.002057875 | H51: =F51-G51 -> 0.036942125 | J51: =IF(H51<0,H51,"") | T51: 43 | U51: =(H51-S$9)^2 -> 0.00028240803 | Y51: =IF(J51="","",(J51-X$9)^2)
A52: 44 | B52: 44136 | C52: 214.07 | D52: 0.0573 | F52: =D52 -> 0.0573 | G52: =O$5/12 -> 0.002057875 | H52: =F52-G52 -> 0.055242125 | J52: =IF(H52<0,H52,"") | T52: 44 | U52: =(H52-S$9)^2 -> 0.001232361 | Y52: =IF(J52="","",(J52-X$9)^2)
... A68: 60 | B68: 43647 | C68: 136.27 | D68: 0.0172 | F68: =D68 -> 0.0172 | G68: =O$5/12 -> 0.002057875 | H68: =F68-G68 -> 0.015142125 | J68: =IF(H68<0,H68,"") | T68: 60 | U68: =(H68-S$9)^2 -> 2.4950025e-05 | Y68: =IF(J68="","",(J68-X$9)^2)
U70: =SUM(U9:U69) -> 0.23361003 | Y70: =SUM(Y9:Y69) -> 0.021535535

Sheet Projection
F1: < Figures are in millions >
F2: Y/E 30/06
F3: 2014 | G3: 2015 | H3: 2016 | I3: 2017 | J3: 2018 | K3: 2019 | L3: 2020 | M3: 2021 | N3: 2022 | O3: 2023 | P3: 2024 | Q3: 2025 | R3: 2026 | S3: 2027 | T3: 2028 | U3: 2029 | V3: 2030 | W3: 2031 | X3: 2032 | Y3: 2033 | Z3: 2034 | AB3: CAGR
B7: P&L | V7: Average Revenue Growth Rate = | W7: =FS!R77 -> 11.111386 | X7: %
B8: Revenue
C9: Product | F9: 72948 | G9: 75956 | H9: 67336 | I9: 63811 | J9: 64497 | K9: 66069 | L9: 68041 | M9: 71074 | N9: 72732 | O9: 64699 | P9: 64773
C10: Service & other | F10: 13885 | G10: 17624 | H10: 23818 | I10: 32760 | J10: 45863 | K10: 59774 | L10: 74974 | M10: 97014 | N10: 125538 | O10: 147216 | P10: 180349
F11: =SUM(F9:F10) -> 86833 | G11: =SUM(G9:G10) -> 93580 | H11: =SUM(H9:H10) -> 91154 | I11: =SUM(I9:I10) -> 96571 | J11: =SUM(J9:J10) -> 110360 | K11: =SUM(K9:K10) -> 125843 | L11: =SUM(L9:L10) -> 143015 | M11: =SUM(M9:M10) -> 168088 | ... P11: =SUM(P9:P10) -> 245122 | Q11: =(1+$W7/100)*P11 -> 272358.45 | R11: =(1+$W7/100)*Q11 -> 302621.25 | S11: =(1+$W7/100)*R11 -> 336246.67 | T11: =(1+$W7/100)*S11 -> 373608.33 | U11: =(1+$W7/100)*T11 -> 415121.4 | V11: =(1+$W7/100)*U11 -> 461247.14 | W11: =(1+$W7/100)*V11 -> 512498.09 | X11: =(1+$W7/100)*W11 -> 569443.73 | ... Z11: =(1+$W7/100)*Y11 -> 703020.43
B12: Cost of Revenue
C13: Product | F13: 16681 | G13: 21410 | H13: 17880 | I13: 15175 | J13: 15420 | K13: 16273 | L13: 16017 | M13: 18219 | N13: 19064 | O13: 17804 | P13: 15272
C14: Service & other | F14: 10397 | G14: 11628 | H14: 14900 | I14: 19086 | J14: 22933 | K14: 26637 | L14: 30061 | M14: 34013 | N14: 43586 | O14: 48059 | P14: 58842
F15: =SUM(F13:F14) -> 27078 | G15: =SUM(G13:G14) -> 33038 | H15: =SUM(H13:H14) -> 32780 | I15: =SUM(I13:I14) -> 34261 | J15: =SUM(J13:J14) -> 38353 | K15: =SUM(K13:K14) -> 42910 | L15: =SUM(L13:L14) -> 46078 | M15: =SUM(M13:M14) -> 52232 | ... P15: =SUM(P13:P14) -> 74114 | Q15: =Q11-Q17 -> 89874.54 | R15: =R11-R17 -> 99860.847 | S15: =S11-S17 -> 110956.77 | T15: =T11-T17 -> 123285.61 | U15: =U11-U17 -> 136984.35 | V15: =V11-V17 -> 152205.21 | W15: =W11-W17 -> 169117.31 | X15: =X11-X17 -> 187908.59 | ... Z15: =Z11-Z17 -> 231987.06
B17: Gross Profit | F17: =F11-F15 -> 59755 | G17: =G11-G15 -> 60542 | H17: =H11-H15 -> 58374 | I17: =I11-I15 -> 62310 | J17: =J11-J15 -> 72007 | K17: =K11-K15 -> 82933 | L17: =L11-L15 -> 96937 | M17: =M11-M15 -> 115856 | ... P17: =P11-P15 -> 171008 | Q17: =Q11*($Q18/100) -> 182483.91 | R17: =R11*($Q18/100) -> 202760.4 | S17: =S11*($Q18/100) -> 225289.9 | T17: =T11*($Q18/100) -> 250322.73 | U17: =U11*($Q18/100) -> 278137.05 | V17: =V11*($Q18/100) -> 309041.93 | W17: =W11*($Q18/100) -> 343380.77 | X17: =X11*($Q18/100) -> 381535.14 | ... Z17: =Z11*($Q18/100) -> 471033.36
C18: GP margin (%) | F18: =IFERROR(F17/F11*100,0) -> 68.816003 | G18: =IFERROR(G17/G11*100,0) -> 64.695448 | H18: =IFERROR(H17/H11*100,0) -> 64.038879 | I18: =IFERROR(I17/I11*100,0) -> 64.522476 | J18: =IFERROR(J17/J11*100,0) -> 65.247372 | K18: =IFERROR(K17/K11*100,0) -> 65.901957 | L18: =IFERROR(L17/L11*100,0) -> 67.781002 | M18: =IFERROR(M17/M11*100,0) -> 68.925801 | ... P18: =IFERROR(P17/P11*100,0) -> 69.764444 | Q18: =AVERAGE(E18:P18) -> 67.001377
B20: Research & Development | F20: 11381 | G20: 12046 | H20: 11988 | I20: 13037 | J20: 14726 | K20: 16876 | L20: 19269 | M20: 20716 | N20: 24512 | O20: 27195 | P20: 29510
B21: Sales & Marketing | F21: 15811 | G21: 15713 | H21: 14635 | I21: 15461 | J21: 17469 | K21: 18213 | L21: 19598 | M21: 20117 | N21: 21825 | O21: 22759 | P21: 24456
B22: General & Admin | F22: 4677 | G22: 4611 | H22: 4563 | I22: =4481 -> 4481 | J22: 4754 | K22: 4885 | L22: 5111 | M22: 5107 | N22: 5900 | O22: 7575 | P22: 7609
B23: Impairment & restructuring | F23: 127 | G23: 10011 | H23: 1110 | I23: 306 | J23: 0 | K23: 0 | L23: 0 | M23: 0 | N23: 0 | O23: 0 | P23: 0
B24: Total Cost & Expenses | F24: =SUM(F20:F23) -> 31996 | G24: =SUM(G20:G23) -> 42381 | H24: =SUM(H20:H23) -> 32296 | I24: =SUM(I20:I23) -> 33285 | J24: =SUM(J20:J23) -> 36949 | K24: =SUM(K20:K23) -> 39974 | L24: =SUM(L20:L23) -> 43978 | M24: =SUM(M20:M23) -> 45940 | ... P24: =SUM(P20:P23) -> 61575 | Q24: =Q17-Q26 -> 87643.459 | R24: =R17-R26 -> 97381.862 | S24: =S17-S26 -> 108202.34 | T24: =T17-T26 -> 120225.12 | U24: =U17-U26 -> 133583.79 | V24: =V17-V26 -> 148426.8 | W24: =W17-W26 -> 164919.08 | X24: =X17-X26 -> 183243.87 | ... Z24: =Z17-Z26 -> 226228.13
B26: Operating Income | F26: =F17-F24 -> 27759 | G26: =G17-G24 -> 18161 | H26: =H17-H24 -> 26078 | I26: =I17-I24 -> 29025 | J26: =J17-J24 -> 35058 | K26: =K17-K24 -> 42959 | L26: =L17-L24 -> 52959 | M26: =M17-M24 -> 69916 | ... P26: =P17-P24 -> 109433 | Q26: =Q11*($Q27/100) -> 94840.453 | R26: =R11*($Q27/100) -> 105378.54 | S26: =S11*($Q27/100) -> 117087.56 | T26: =T11*($Q27/100) -> 130097.61 | U26: =U11*($Q27/100) -> 144553.26 | V26: =V11*($Q27/100) -> 160615.13 | W26: =W11*($Q27/100) -> 178461.69 | X26: =X11*($Q27/100) -> 198291.26 | ... Z26: =Z11*($Q27/100) -> 244805.24
C27: Operating margin (%) | F27: =IFERROR(F26/F11*100,0) -> 31.968261 | G27: =IFERROR(G26/G11*100,0) -> 19.406925 | H27: =IFERROR(H26/H11*100,0) -> 28.608728 | I27: =IFERROR(I26/I11*100,0) -> 30.055607 | J27: =IFERROR(J26/J11*100,0) -> 31.766945 | K27: =IFERROR(K26/K11*100,0) -> 34.13698 | L27: =IFERROR(L26/L11*100,0) -> 37.030381 | M27: =IFERROR(M26/M11*100,0) -> 41.594879 | ... P27: =IFERROR(P26/P11*100,0) -> 44.6443 | Q27: =AVERAGE(E27:P27) -> 34.821924
B29: Other Income / (expense), Net | F29: 61 | G29: 346 | H29: -439 | I29: 876 | J29: 1416 | K29: 729 | L29: 77 | M29: 1186 | N29: 333 | O29: 788 | P29: -1646 | Q29: =Q11*(FS!$R$109/100) -> 646.23861 | R29: =R11*(FS!$R$109/100) -> 718.04468 | S29: =S11*(FS!$R$109/100) -> 797.8294 | T29: =T11*(FS!$R$109/100) -> 886.4793 | U29: =U11*(FS!$R$109/100) -> 984.97944 | V29: =V11*(FS!$R$109/100) -> 1094.4243 | W29: =W11*(FS!$R$109/100) -> 1216.03 | X29: =X11*(FS!$R$109/100) -> 1351.1478 | ... Z29: =Z11*(FS!$R$109/100) -> 1668.092
B31: Income before taxation | F31: =F26+F29 -> 27820 | G31: =G26+G29 -> 18507 | H31: =H26+H29 -> 25639 | I31: =I26+I29 -> 29901 | J31: =J26+J29 -> 36474 | K31: =K26+K29 -> 43688 | L31: =L26+L29 -> 53036 | M31: =M26+M29 -> 71102 | ... Z31: =Z26+Z29 -> 246473.33
B33: Provision for income taxes | F33: 5746 | G33: 6314 | H33: 5100 | I33: 4412 | J33: 19903 | K33: 4448 | L33: 8755 | M33: 9831 | N33: 10978 | O33: 16950 | P33: 19651 | Q33: =Q31-Q35 -> 19281.579 | R33: =R31-R35 -> 21424.029 | S33: =S31-S35 -> 23804.536 | T33: =T31-T35 -> 26449.55 | U33: =U31-U35 -> 29388.461 | V33: =V31-V35 -> 32653.927 | W33: =W31-W35 -> 36282.23 | X33: =X31-X35 -> 40313.689 | ... Z33: =Z31-Z35 -> 49770.233
B35: Net Income | F35: =F31-F33 -> 22074 | G35: =G31-G33 -> 12193 | H35: =H31-H33 -> 20539 | I35: =I31-I33 -> 25489 | J35: =J31-J33 -> 16571 | K35: =K31-K33 -> 39240 | L35: =L31-L33 -> 44281 | M35: =M31-M33 -> 61271 | ... P35: =P31-P33 -> 88136 | Q35: =Q11*($Q36/100) -> 76205.113 | R35: =R11*($Q36/100) -> 84672.557 | S35: =S11*($Q36/100) -> 94080.852 | T35: =T11*($Q36/100) -> 104534.54 | U35: =U11*($Q36/100) -> 116149.78 | V35: =V11*($Q36/100) -> 129055.63 | W35: =W11*($Q36/100) -> 143395.49 | X35: =X11*($Q36/100) -> 159328.72 | ... Z35: =Z11*($Q36/100) -> 196703.1
C36: Net income margin (%) | F36: =IFERROR(F35/F11*100,0) -> 25.421211 | G36: =IFERROR(G35/G11*100,0) -> 13.029493 | H36: =IFERROR(H35/H11*100,0) -> 22.532198 | I36: =IFERROR(I35/I11*100,0) -> 26.394052 | J36: =IFERROR(J35/J11*100,0) -> 15.015404 | K36: =IFERROR(K35/K11*100,0) -> 31.181711 | L36: =IFERROR(L35/L11*100,0) -> 30.962486 | M36: =IFERROR(M35/M11*100,0) -> 36.45174 | ... P36: =IFERROR(P35/P11*100,0) -> 35.955973 | Q36: =AVERAGE(E36:P36) -> 27.979713
C39: Valuation Multiples / Shareholder ratios
C40: No. of Shares | F40: 8239 | G40: 8027 | H40: 7808 | I40: 7708 | J40: 7677 | K40: 7643 | L40: 7571 | M40: 7519 | N40: 7464 | O40: 7432 | P40: 7434 | Q40: 7434 | R40: 7434 | S40: 7434 | T40: 7434 | U40: 7434 | V40: 7434 | W40: 7434 | X40: 7434 | Y40: 7434 | Z40: 7434
C41: Share Price | F41: 43.16 | G41: 46.7 | H41: 56.68 | I41: 72.7 | J41: 106.08 | K41: 136.27 | L41: 205.01 | M41: 284.91 | N41: 280.74 | O41: 335.92 | P41: 418.35 | Q41: =Q42*$Q43 -> 311.89093 | R41: =R42*$Q43 -> 346.54634 | S41: =S42*$Q43 -> 385.05244 | T41: =T42*$Q43 -> 427.8371 | U41: =U42*$Q43 -> 475.37573 | V41: =V42*$Q43 -> 528.19657 | W41: =W42*$Q43 -> 586.88653 | X41: =X42*$Q43 -> 652.09775 | ... Z41: =Z42*$Q43 -> 805.06294 | AB41: =((Z41/P41)^(1/($Z$3-$P$3))-1)*100 -> 6.765025
C42: EPS | F42: =IFERROR(F35/F40,0) -> 2.6792086 | G42: =IFERROR(G35/G40,0) -> 1.5189984 | H42: =IFERROR(H35/H40,0) -> 2.6305072 | I42: =IFERROR(I35/I40,0) -> 3.3068241 | J42: =IFERROR(J35/J40,0) -> 2.1585255 | K42: =IFERROR(K35/K40,0) -> 5.1341096 | L42: =IFERROR(L35/L40,0) -> 5.848765 | M42: =IFERROR(M35/M40,0) -> 8.148823 | ... P42: =IFERROR(P35/P40,0) -> 11.855798 | Q42: =Q35/Q40 -> 10.25089 | R42: =R35/R40 -> 11.389905 | S42: =S35/S40 -> 12.655482 | T42: =T35/T40 -> 14.061681 | U42: =U35/U40 -> 15.624129 | V42: =V35/V40 -> 17.360186 | W42: =W35/W40 -> 19.289144 | X42: =X35/X40 -> 21.432435 | ... Z42: =Z35/Z40 -> 26.459927
C43: P/E | F43: =F41/F42 -> 16.109234 | G43: =G41/G42 -> 30.743943 | H43: =H41/H42 -> 21.547176 | I43: =I41/I42 -> 21.984841 | J43: =J41/J42 -> 49.14466 | K43: =K41/K42 -> 26.54209 | L43: =L41/L42 -> 35.051844 | M43: =M41/M42 -> 34.963332 | ... P43: =P41/P42 -> 35.286533 | Q43: =AVERAGE(E43:P43) -> 30.425743

Sheet SWOT
O2: Notes
B3: Strengths
C4: Productivity & business processes
D5: Office Commercial | O5: - Microsoft 365, Microsoft Teams, Office apps, Copilot AI assistant
D7: LinkedIn
D9: Dynamics 365 | O9: - cloud-based applications across ERP, CRM, Power Apps, and Power Automate; and on-premises ERP and CRM applications
O10: - integrated suite of enterprise resource planning and customer relationship management applications offered by Microsoft. Combines various functions such as sales, customer service, field service, operations, finance, marketing, and project service automation into a single platform
C12: Intelligent Cloud
D13: Azure | O13: - VMs, servers, databases, cloud services
O14: - As OpenAI’s exclusive cloud provider, Azure powers all of OpenAI's workloads
D16: Azure AI Studio | O16: - full lifecycle toolchain customers can use to ground these models on their own data, create prompt workflows, and help ensure they are deployed and used safely
D18: Github Copilot
D20: Nuance | O20: - Leader in conversational AI and ambient intelligence across industries, including healthcare, financial services, retail, and telecommunications
O21: - Ambient intelligence is the concept of capturing and processing data through sensors, processors, and actuators unobtrusively embedded throughout the environment
C23: Personal Computing
D24: Windows | O24: - Copilot+ PCs are a new class of Windows 11 PCs that are powered by a neural processing unit
D26: Surface devices
D28: Edge browser, Bing search | O28: - The AI-powered Bing search engine with Copilot delivers better search, more complete answers, and the ability to generate content.
D30: Gaming | O30: - Xbox Game Pass
O31: - Activision Blizzard Inc.
B34: Weaknesses
B42: Opportunities
C43: OpenAI
B52: Threats
C53: Productivity & business processes
D54: Office
E55: - Apple, Cisco Systems, Google, Meta, Proofpoint, Slack, Symantec, Zoom
E57: - Apple distributes versions of its pre-installed application software, such as email and calendar products, through its PCs, tablets, and phones
E59: - Cisco Systems is using its position in enterprise communications equipment to grow its unified communications business
E61: - Google provides a hosted messaging and productivity suite
E63: - Meta offers communication tools to enable productivity and engagement within organizations
E65: - Proofpoint and Symantec provide security solutions across email security, information protection, and governance
E67: - Slack provides teamwork and collaboration software
E69: - Zoom offers videoconferencing and cloud phone solutions
D72: LinkedIn
E73: - Marketing Solutions | O73: - B2B Marketing Communications
O74: - competes with online and offline outlets that generate revenue from advertisers and marketers
E76: - Sales Solutions | O76: - competes with online and offline outlets for companies with lead generation and customer intelligence and insights
D79: Dynamics
E80: - competes with cloud-based and on-premises business solution providers such as Oracle, Salesforce, SAP, Service Now, UI Path, and WorkDay
C83: Intelligent Cloud
D84: Azure
E85: - Amazon, Broadcom, Google, IBM, Oracle
E86: - Our AI offerings compete with AI products from hyperscalers such as Amazon (AWS) and Google (GCP)
E88: - Our database, business intelligence, and data warehousing solutions offerings compete with products from Databricks, IBM, Oracle, SAP, Snowflake
E90: - Our system management solutions compete with server management and server virtualization platform providers, such as BMC, Broadcom, Hewlett-Packard, and IBM
E92: - Our products for software developers compete against offerings from Adobe, IBM, Oracle, and other companies, and also against open source projects, including Eclipse (sponsored by IBM, Oracle, and SAP), PHP, and Ruby on Rails
C95: Personal Computing
D96: - various software products and from alternative platforms and devices, mainly from Apple and Google
D97: - various online gaming ecosystems and game streaming services, including those operated by Amazon, Apple, Meta, and Tencent
D98: - gaming platform competes with console platforms from Nintendo and Sony
