Workbook

Sheet Overall
B2: SUMMARY
H3: Share price | K3: Profit Margins | T3: Valuations Multiples | AC3: Solvency | AL3: Efficiency | AU3: Risk
H4: CAGR | K4: GPM | N4: OM | Q4: NPM | T4: PE | W4: EPS | Z4: Dividend Yield | AC4: Debt Ratio | AF4: Debt - Equity | AI4: Debt - Revenue | AL4: IT | AO4: RT | AR4: PT | AU4: Sharpe Ratio | AX4: Sortino Ratio
B5: Base year | D5: Y/E | E5: Updated As At | F5: MC | G5: Share price at Y/E | H5: Current | I5: 3 years | J5: 5 years | K5: Current | L5: 3 years | M5: 5 years | N5: Current | O5: 3 years | P5: 5 years | Q5: Current | R5: 3 years | S5: 5 years | T5: Current | U5: 3 years | V5: 5 years | W5: Current | X5: 3 years | Y5: 5 years | Z5: Current | AA5: 3 years | AB5: 5 years | AC5: Current | AD5: 3 years | AE5: 5 years | AF5: Current | AG5: 3 years | AH5: 5 years | AI5: Current | AJ5: 3 years | AK5: 5 years | AL5: Current | AM5: 3 years | AN5: 5 years | AO5: Current | AP5: 3 years | AQ5: 5 years | AR5: Current | AS5: 3 years | AT5: 5 years | AU5: Current | AV5: 3 years | AW5: 5 years | AX5: Current | AY5: 3 years | AZ5: 5 years
B6: 2024 | D6: 31/01 | E6: 2024 | F6: =OFFSET(FS!P111,0,E$6-B$6) -> 1516099.2 | G6: =OFFSET(FS!P105,0,E$6-B$6) -> 61.53 | H6: =((OFFSET(FS!P105,0,E$6-B$6)/OFFSET(FS!P105,0,-1+E$6-B$6))^(1/1)-1)*100 -> 214.89253 | I6: =((OFFSET(FS!P105,0,E$6-B$6)/OFFSET(FS!P105,0,-2+E$6-B$6))^(1/3)-1)*100 -> 35.945878 | J6: =((OFFSET(FS!P105,0,E$6-B$6)/OFFSET(FS!P105,0,-4+E$6-B$6))^(1/5)-1)*100 -> 59.771711 | K6: =OFFSET(FS!P80,0,0+E$6-B$6) -> 72.717573 | L6: =AVERAGE(OFFSET(FS!P80,0,-2+E$6-B$6):OFFSET(FS!P80,0,E$6-B$6)) -> 64.8585 | M6: =AVERAGE(OFFSET(FS!P80,0,-4+E$6-B$6):OFFSET(FS!P80,0,E$6-B$6)) -> 63.781941 | N6: =OFFSET(FS!P89,0,0+E$6-B$6) -> 54.121664 | O6: =AVERAGE(OFFSET(FS!P89,0,-2+E$6-B$6):OFFSET(FS!P89,0,E$6-B$6)) -> 35.696303 | P6: =AVERAGE(OFFSET(FS!P89,0,-4+E$6-B$6):OFFSET(FS!P89,0,E$6-B$6)) -> 32.066873 | Q6: =OFFSET(FS!P98,0,0+E$6-B$6) -> 48.849348 | R6: =AVERAGE(OFFSET(FS!P98,0,-2+E$6-B$6):OFFSET(FS!P98,0,E$6-B$6)) -> 33.758883 | S6: =AVERAGE(OFFSET(FS!P98,0,-4+E$6-B$6):OFFSET(FS!P98,0,E$6-B$6)) -> 30.572949 | T6: =OFFSET(FS!P107,0,0+E$6-B$6) -> 50.944194 | U6: =AVERAGE(OFFSET(FS!P107,0,-2+E$6-B$6):OFFSET(FS!P107,0,E$6-B$6)) -> 74.730658 | V6: =AVERAGE(OFFSET(FS!P107,0,-4+E$6-B$6):OFFSET(FS!P107,0,E$6-B$6)) -> 70.062824 | W6: =OFFSET(FS!P106,0,0+E$6-B$6) -> 1.2077922 | X6: =AVERAGE(OFFSET(FS!P106,0,-2+E$6-B$6):OFFSET(FS!P106,0,E$6-B$6)) -> 0.59135574 | Y6: =AVERAGE(OFFSET(FS!P106,0,-4+E$6-B$6):OFFSET(FS!P106,0,E$6-B$6)) -> 0.41258751 | Z6: =OFFSET(FS!P117,0,0+E$6-B$6) -> 0.00026053704 | AA6: =AVERAGE(OFFSET(FS!P117,0,-2+E$6-B$6):OFFSET(FS!P117,0,E$6-B$6)) -> 0.00057888117 | AB6: =AVERAGE(OFFSET(FS!P117,0,-4+E$6-B$6):OFFSET(FS!P117,0,E$6-B$6)) -> 0.0011313461 | AC6: =OFFSET(FS!P166,0,0+E$6-B$6) -> 0.34612342 | AD6: =AVERAGE(OFFSET(FS!P166,0,-2+E$6-B$6):OFFSET(FS!P166,0,E$6-B$6)) -> 0.40239944 | AE6: =AVERAGE(OFFSET(FS!P166,0,-4+E$6-B$6):OFFSET(FS!P166,0,E$6-B$6)) -> 0.38312601 | AF6: =OFFSET(FS!P167,0,0+E$6-B$6) -> 0.52934059 | AG6: =AVERAGE(OFFSET(FS!P167,0,-2+E$6-B$6):OFFSET(FS!P167,0,E$6-B$6)) -> 0.68437052 | AH6: =AVERAGE(OFFSET(FS!P167,0,-4+E$6-B$6):OFFSET(FS!P167,0,E$6-B$6)) -> 0.63524481 | AI6: =OFFSET(FS!P168,0,0+E$6-B$6) -> 0.37342832 | AJ6: =AVERAGE(OFFSET(FS!P168,0,-2+E$6-B$6):OFFSET(FS!P168,0,E$6-B$6)) -> 0.57793969 | AK6: =AVERAGE(OFFSET(FS!P168,0,-4+E$6-B$6):OFFSET(FS!P168,0,E$6-B$6)) -> 0.58309367 | AL6: =OFFSET(FS!P171,0,0+E$6-B$6) -> 3.1467247 | AM6: =AVERAGE(OFFSET(FS!P171,0,-2+E$6-B$6):OFFSET(FS!P171,0,E$6-B$6)) -> 3.007376 | AN6: =AVERAGE(OFFSET(FS!P171,0,-4+E$6-B$6):OFFSET(FS!P171,0,E$6-B$6)) -> 3.3399622 | AO6: =OFFSET(FS!P172,0,0+E$6-B$6) -> 6.0928093 | AP6: =AVERAGE(OFFSET(FS!P172,0,-2+E$6-B$6):OFFSET(FS!P172,0,E$6-B$6)) -> 6.3097023 | AQ6: =AVERAGE(OFFSET(FS!P172,0,-4+E$6-B$6):OFFSET(FS!P172,0,E$6-B$6)) -> 6.4766177 | AR6: =OFFSET(FS!P173,0,0+E$6-B$6) -> 6.1582067 | AS6: =AVERAGE(OFFSET(FS!P173,0,-2+E$6-B$6):OFFSET(FS!P173,0,E$6-B$6)) -> 7.0635226 | AT6: =AVERAGE(OFFSET(FS!P173,0,-4+E$6-B$6):OFFSET(FS!P173,0,E$6-B$6)) -> 6.5392154 | AU6: ='Sharpe, Sortino'!O23 -> 3.6648618 | AV6: ='Sharpe, Sortino'!P23 -> 1.1029148 | AW6: ='Sharpe, Sortino'!Q23 -> 1.4409924 | AX6: ='Sharpe, Sortino'!O40 -> 7.9692357 | AY6: ='Sharpe, Sortino'!P40 -> 1.9982805 | AZ6: ='Sharpe, Sortino'!Q40 -> 2.2423037

Sheet FS
F1: < Figures are in millions >
F2: Y/E 31/01 | U2: Annualized
F3: 2014 | G3: 2015 | H3: 2016 | I3: 2017 | J3: 2018 | K3: 2019 | L3: 2020 | M3: 2021 | N3: 2022 | O3: 2023 | P3: 2024 | R3: Average | S3: Median | T3: CAGR | U3: Std Dev
B5: Revenue By Geography
C6: United States | F6: 727 | G6: 791 | H6: 643 | I6: 904 | J6: 1274 | K6: 1506 | L6: 886 | M6: 3214 | N6: 4349 | O6: 8292 | P6: 26966
C7: Taiwan | F7: 1321 | G7: 1594 | H7: 1912 | I7: 2546 | J7: 2991 | K7: 3360 | L7: 3025 | M7: 4531 | N7: 8544 | O7: 6986 | P7: 13405
C8: China (inc. HK) | F8: 794 | G8: 922 | H8: 806 | I8: 1305 | J8: 1896 | K8: 2801 | L8: 2731 | M8: 3886 | N8: 7111 | O8: 5785 | P8: 10306
C9: Other countries | F9: =675+295+318 -> 1288 | G9: =638+369+368 -> 1375 | H9: =749+482+418 -> 1649 | I9: =1010+659+486 -> 2155 | J9: =2066+768+719 -> 3553 | K9: =2368+914+767 -> 4049 | L9: 4276 | M9: 5044 | N9: 6910 | O9: 5911 | P9: 10245
B10: Total Revenues | F10: =SUM(F6:F9) -> 4130 | G10: =SUM(G6:G9) -> 4682 | H10: =SUM(H6:H9) -> 5010 | I10: =SUM(I6:I9) -> 6910 | J10: =SUM(J6:J9) -> 9714 | K10: =SUM(K6:K9) -> 11716 | L10: =SUM(L6:L9) -> 10918 | M10: =SUM(M6:M9) -> 16675 | ... P10: =SUM(P6:P9) -> 60922
B12: Revenue By Specific Segments
C13: Data Center | F13: 199 | G13: 317 | H13: 339 | I13: 830 | J13: 1932 | K13: 2932 | L13: 2983 | M13: 6696 | N13: 10613 | O13: 15005 | P13: 47525
C14: Gaming | F14: 1511 | G14: 2058 | H14: 2818 | I14: 4060 | J14: 5513 | K14: 6246 | L14: 5518 | M14: 7759 | N14: 12462 | O14: 9067 | P14: 10447
C15: Professional Visualization | F15: 789 | G15: 795 | H15: 750 | I15: 835 | J15: 934 | K15: 1130 | L15: 1212 | M15: 1053 | N15: 2111 | O15: 1544 | P15: 1553
C16: Automotive | F16: 99 | G16: 183 | H16: 320 | I16: 487 | J16: 558 | K16: 641 | L16: 700 | M16: 536 | N16: 566 | O16: 903 | P16: 1091
C17: OEM & Other | F17: 1532 | G17: 1329 | H17: 783 | I17: 698 | J17: 777 | K17: 767 | L17: 505 | M17: 631 | N17: 1162 | O17: 455 | P17: 306
B18: Total Revenues | F18: =SUM(F13:F17) -> 4130 | G18: =SUM(G13:G17) -> 4682 | H18: =SUM(H13:H17) -> 5010 | I18: =SUM(I13:I17) -> 6910 | J18: =SUM(J13:J17) -> 9714 | K18: =SUM(K13:K17) -> 11716 | L18: =SUM(L13:L17) -> 10918 | M18: =SUM(M13:M17) -> 16675 | ... P18: =SUM(P13:P17) -> 60922
B20: Revenue by Segments
C21: Compute & Networking | F21: 398 | G21: 579 | H21: 559 | I21: 824 | J21: 1534 | K21: 3557 | L21: 3279 | M21: 6841 | N21: 11046 | O21: 15068 | P21: 47405
C22: Graphics | F22: 3468 | G22: 3839 | H22: 4187 | I22: 5822 | J22: 8137 | K22: 8159 | L22: 7639 | M22: 9834 | N22: 15868 | O22: 11906 | P22: 13517
C23: All Other | F23: 264 | G23: 264 | H23: 264 | I23: 264 | J23: 43 | K23: 0 | L23: 0 | M23: 0 | N23: 0 | O23: 0 | P23: 0
B24: Total Revenues | F24: =SUM(F21:F23) -> 4130 | G24: =SUM(G21:G23) -> 4682 | H24: =SUM(H21:H23) -> 5010 | I24: =SUM(I21:I23) -> 6910 | J24: =SUM(J21:J23) -> 9714 | K24: =SUM(K21:K23) -> 11716 | L24: =SUM(L21:L23) -> 10918 | M24: =SUM(M21:M23) -> 16675 | ... P24: =SUM(P21:P23) -> 60922
B26: Operating Income/(loss) Breakdown
C27: Compute & Networking | F27: -268 | G27: -254 | H27: -239 | I27: -9 | J27: 303 | K27: 1251 | L27: 751 | M27: 2548 | N27: 4598 | O27: 5083 | P27: 32016
C28: Graphics | F28: 835 | G28: 1113 | H28: 1344 | I28: 2180 | J28: 3507 | K28: 3417 | L28: 3267 | M28: 4612 | N28: 8492 | O28: 4552 | P28: 5846
C29: All Other | F29: -71 | G29: -100 | H29: -358 | I29: -237 | J29: -600 | K29: -864 | L29: -1172 | M29: -2628 | N29: -3049 | O29: -5411 | P29: -4890
B30: Total Operating Income | F30: =SUM(F27:F29) -> 496 | G30: =SUM(G27:G29) -> 759 | H30: =SUM(H27:H29) -> 747 | I30: =SUM(I27:I29) -> 1934 | J30: =SUM(J27:J29) -> 3210 | K30: =SUM(K27:K29) -> 3804 | L30: =SUM(L27:L29) -> 2846 | M30: =SUM(M27:M29) -> 4532 | ... P30: =SUM(P27:P29) -> 32972
C33: Composition By Geography
C34: United States | F34: =F6/F$10*100 -> 17.602906 | G34: =G6/G$10*100 -> 16.89449 | H34: =H6/H$10*100 -> 12.834331 | I34: =I6/I$10*100 -> 13.082489 | J34: =J6/J$10*100 -> 13.115092 | K34: =K6/K$10*100 -> 12.854216 | L34: =L6/L$10*100 -> 8.1150394 | M34: =M6/M$10*100 -> 19.274363 | ... P34: =P6/P$10*100 -> 44.263156 | R34: =AVERAGEIF(E34:Q34,"<>0") -> 18.630516
C35: Taiwan | F35: =F7/F$10*100 -> 31.985472 | G35: =G7/G$10*100 -> 34.04528 | H35: =H7/H$10*100 -> 38.163673 | I35: =I7/I$10*100 -> 36.845152 | J35: =J7/J$10*100 -> 30.790611 | K35: =K7/K$10*100 -> 28.67873 | L35: =L7/L$10*100 -> 27.70654 | M35: =M7/M$10*100 -> 27.172414 | ... P35: =P7/P$10*100 -> 22.003546 | R35: =AVERAGEIF(E35:Q35,"<>0") -> 30.457817
C36: China (including HK) | F36: =F8/F$10*100 -> 19.225182 | G36: =G8/G$10*100 -> 19.692439 | H36: =H8/H$10*100 -> 16.087824 | I36: =I8/I$10*100 -> 18.885673 | J36: =J8/J$10*100 -> 19.518221 | K36: =K8/K$10*100 -> 23.907477 | L36: =L8/L$10*100 -> 25.013739 | M36: =M8/M$10*100 -> 23.304348 | ... P36: =P8/P$10*100 -> 16.916713 | R36: =AVERAGEIF(E36:Q36,"<>0") -> 20.947217
C37: Other countries | F37: =F9/F$10*100 -> 31.186441 | G37: =G9/G$10*100 -> 29.367792 | H37: =H9/H$10*100 -> 32.914172 | I37: =I9/I$10*100 -> 31.186686 | J37: =J9/J$10*100 -> 36.576076 | K37: =K9/K$10*100 -> 34.559577 | L37: =L9/L$10*100 -> 39.164682 | M37: =M9/M$10*100 -> 30.248876 | ... P37: =P9/P$10*100 -> 16.816585 | R37: =AVERAGEIF(E37:Q37,"<>0") -> 29.96445
F38: =SUM(F34:F37) -> 100 | G38: =SUM(G34:G37) -> 100 | H38: =SUM(H34:H37) -> 100 | I38: =SUM(I34:I37) -> 100 | J38: =SUM(J34:J37) -> 100 | K38: =SUM(K34:K37) -> 100 | L38: =SUM(L34:L37) -> 100 | M38: =SUM(M34:M37) -> 100 | ... P38: =SUM(P34:P37) -> 100
C40: Composition By Specific Segments
C41: Data Center | F41: =F13/F$18*100 -> 4.8184019 | G41: =G13/G$18*100 -> 6.7706109 | H41: =H13/H$18*100 -> 6.7664671 | I41: =I13/I$18*100 -> 12.011577 | J41: =J13/J$18*100 -> 19.88882 | K41: =K13/K$18*100 -> 25.025606 | L41: =L13/L$18*100 -> 27.321854 | M41: =M13/M$18*100 -> 40.155922 | ... P41: =P13/P$18*100 -> 78.009586 | R41: =AVERAGEIF(E41:Q41,"<>0") -> 28.711772
C42: Gaming | F42: =F14/F$18*100 -> 36.585956 | G42: =G14/G$18*100 -> 43.955575 | H42: =H14/H$18*100 -> 56.247505 | I42: =I14/I$18*100 -> 58.755427 | J42: =J14/J$18*100 -> 56.75314 | K42: =K14/K$18*100 -> 53.31171 | L42: =L14/L$18*100 -> 50.540392 | M42: =M14/M$18*100 -> 46.530735 | ... P42: =P14/P$18*100 -> 17.148157 | R42: =AVERAGEIF(E42:Q42,"<>0") -> 45.431408
C43: Professional Visualization | F43: =F15/F$18*100 -> 19.104116 | G43: =G15/G$18*100 -> 16.979923 | H43: =H15/H$18*100 -> 14.97006 | I43: =I15/I$18*100 -> 12.083936 | J43: =J15/J$18*100 -> 9.6149887 | K43: =K15/K$18*100 -> 9.64493 | L43: =L15/L$18*100 -> 11.100934 | M43: =M15/M$18*100 -> 6.3148426 | ... P43: =P15/P$18*100 -> 2.5491612 | R43: =AVERAGEIF(E43:Q43,"<>0") -> 10.539129
C44: Automotive | F44: =F16/F$18*100 -> 2.3970944 | G44: =G16/G$18*100 -> 3.9085861 | H44: =H16/H$18*100 -> 6.3872255 | I44: =I16/I$18*100 -> 7.0477569 | J44: =J16/J$18*100 -> 5.7442866 | K44: =K16/K$18*100 -> 5.4711506 | L44: =L16/L$18*100 -> 6.4114307 | M44: =M16/M$18*100 -> 3.2143928 | ... P44: =P16/P$18*100 -> 1.7908145 | R44: =AVERAGEIF(E44:Q44,"<>0") -> 4.3475819
C45: OEM & Other | F45: =F17/F$18*100 -> 37.094431 | G45: =G17/G$18*100 -> 28.385305 | H45: =H17/H$18*100 -> 15.628743 | I45: =I17/I$18*100 -> 10.101302 | J45: =J17/J$18*100 -> 7.9987647 | K45: =K17/K$18*100 -> 6.5466029 | L45: =L17/L$18*100 -> 4.6253893 | M45: =M17/M$18*100 -> 3.7841079 | ... P45: =P17/P$18*100 -> 0.50228161 | R45: =AVERAGEIF(E45:Q45,"<>0") -> 10.970108
F46: =SUM(F41:F45) -> 100 | G46: =SUM(G41:G45) -> 100 | H46: =SUM(H41:H45) -> 100 | I46: =SUM(I41:I45) -> 100 | J46: =SUM(J41:J45) -> 100 | K46: =SUM(K41:K45) -> 100 | L46: =SUM(L41:L45) -> 100 | M46: =SUM(M41:M45) -> 100 | ... P46: =SUM(P41:P45) -> 100
C48: Composition By Segments
C49: Compute & Networking | F49: =F21/F$24*100 -> 9.6368039 | G49: =G21/G$24*100 -> 12.36651 | H49: =H21/H$24*100 -> 11.157685 | I49: =I21/I$24*100 -> 11.924747 | J49: =J21/J$24*100 -> 15.791641 | K49: =K21/K$24*100 -> 30.360191 | L49: =L21/L$24*100 -> 30.032973 | M49: =M21/M$24*100 -> 41.025487 | ... P49: =P21/P$24*100 -> 77.812613 | R49: =AVERAGEIF(E49:Q49,"<>0") -> 30.637426
C50: Graphics | F50: =F22/F$24*100 -> 83.970944 | G50: =G22/G$24*100 -> 81.994874 | H50: =H22/H$24*100 -> 83.572854 | I50: =I22/I$24*100 -> 84.254703 | J50: =J22/J$24*100 -> 83.765699 | K50: =K22/K$24*100 -> 69.639809 | L50: =L22/L$24*100 -> 69.967027 | M50: =M22/M$24*100 -> 58.974513 | ... P50: =P22/P$24*100 -> 22.187387 | R50: =AVERAGEIF(E50:Q50,"<>0") -> 67.402252
C51: All Other | F51: =F23/F$24*100 -> 6.3922518 | G51: =G23/G$24*100 -> 5.638616 | H51: =H23/H$24*100 -> 5.2694611 | I51: =I23/I$24*100 -> 3.8205499 | J51: =J23/J$24*100 -> 0.44266008 | K51: =K23/K$24*100 -> 0 | L51: =L23/L$24*100 -> 0 | M51: =M23/M$24*100 -> 0 | ... P51: =P23/P$24*100 -> 0 | R51: =AVERAGEIF(E51:Q51,"<>0") -> 4.3127078
F52: =SUM(F49:F51) -> 100 | G52: =SUM(G49:G51) -> 100 | H52: =SUM(H49:H51) -> 100 | I52: =SUM(I49:I51) -> 100 | J52: =SUM(J49:J51) -> 100 | K52: =SUM(K49:K51) -> 100 | L52: =SUM(L49:L51) -> 100 | M52: =SUM(M49:M51) -> 100 | ... P52: =SUM(P49:P51) -> 100
C54: Revenue Growth By Specific Segments (%)
C55: Data Center | G55: =(G13-F13)/ABS(F13)*100 -> 59.296482 | H55: =(H13-G13)/ABS(G13)*100 -> 6.9400631 | I55: =(I13-H13)/ABS(H13)*100 -> 144.83776 | J55: =(J13-I13)/ABS(I13)*100 -> 132.77108 | K55: =(K13-J13)/ABS(J13)*100 -> 51.759834 | L55: =(L13-K13)/ABS(K13)*100 -> 1.739427 | M55: =(M13-L13)/ABS(L13)*100 -> 124.47201 | N55: =(N13-M13)/ABS(M13)*100 -> 58.497611 | ... P55: =(P13-O13)/ABS(O13)*100 -> 216.72776 | R55: =AVERAGEIF(E55:Q55,"<>0") -> 83.842523
C56: Gaming | G56: =(G14-F14)/ABS(F14)*100 -> 36.201191 | H56: =(H14-G14)/ABS(G14)*100 -> 36.929057 | I56: =(I14-H14)/ABS(H14)*100 -> 44.073811 | J56: =(J14-I14)/ABS(I14)*100 -> 35.788177 | K56: =(K14-J14)/ABS(J14)*100 -> 13.295846 | L56: =(L14-K14)/ABS(K14)*100 -> -11.655459 | M56: =(M14-L14)/ABS(L14)*100 -> 40.612541 | N56: =(N14-M14)/ABS(M14)*100 -> 60.613481 | ... P56: =(P14-O14)/ABS(O14)*100 -> 15.220029 | R56: =AVERAGEIF(E56:Q56,"<>0") -> 24.383586
C57: Professional Visualization | G57: =(G15-F15)/ABS(F15)*100 -> 0.76045627 | H57: =(H15-G15)/ABS(G15)*100 -> -5.6603774 | I57: =(I15-H15)/ABS(H15)*100 -> 11.333333 | J57: =(J15-I15)/ABS(I15)*100 -> 11.856287 | K57: =(K15-J15)/ABS(J15)*100 -> 20.985011 | L57: =(L15-K15)/ABS(K15)*100 -> 7.2566372 | M57: =(M15-L15)/ABS(L15)*100 -> -13.118812 | N57: =(N15-M15)/ABS(M15)*100 -> 100.47483 | ... P57: =(P15-O15)/ABS(O15)*100 -> 0.58290155 | R57: =AVERAGEIF(E57:Q57,"<>0") -> 10.761096
C58: Automotive | G58: =(G16-F16)/ABS(F16)*100 -> 84.848485 | H58: =(H16-G16)/ABS(G16)*100 -> 74.863388 | I58: =(I16-H16)/ABS(H16)*100 -> 52.1875 | J58: =(J16-I16)/ABS(I16)*100 -> 14.579055 | K58: =(K16-J16)/ABS(J16)*100 -> 14.874552 | L58: =(L16-K16)/ABS(K16)*100 -> 9.2043682 | M58: =(M16-L16)/ABS(L16)*100 -> -23.428571 | N58: =(N16-M16)/ABS(M16)*100 -> 5.5970149 | ... P58: =(P16-O16)/ABS(O16)*100 -> 20.819491 | R58: =AVERAGEIF(E58:Q58,"<>0") -> 31.308592
C59: OEM & Other | G59: =(G17-F17)/ABS(F17)*100 -> -13.250653 | H59: =(H17-G17)/ABS(G17)*100 -> -41.083521 | I59: =(I17-H17)/ABS(H17)*100 -> -10.855683 | J59: =(J17-I17)/ABS(I17)*100 -> 11.318052 | K59: =(K17-J17)/ABS(J17)*100 -> -1.2870013 | L59: =(L17-K17)/ABS(K17)*100 -> -34.159061 | M59: =(M17-L17)/ABS(L17)*100 -> 24.950495 | N59: =(N17-M17)/ABS(M17)*100 -> 84.152139 | ... P59: =(P17-O17)/ABS(O17)*100 -> -32.747253 | R59: =AVERAGEIF(E59:Q59,"<>0") -> -7.380586
C61: Revenue Growth by Segments (%)
C62: Compute & Networking | G62: =(G21-F21)/ABS(F21)*100 -> 45.477387 | H62: =(H21-G21)/ABS(G21)*100 -> -3.4542314 | I62: =(I21-H21)/ABS(H21)*100 -> 47.406082 | J62: =(J21-I21)/ABS(I21)*100 -> 86.165049 | K62: =(K21-J21)/ABS(J21)*100 -> 131.87744 | L62: =(L21-K21)/ABS(K21)*100 -> -7.8155749 | M62: =(M21-L21)/ABS(L21)*100 -> 108.63068 | N62: =(N21-M21)/ABS(M21)*100 -> 61.467622 | ... P62: =(P21-O21)/ABS(O21)*100 -> 214.60711 | R62: =AVERAGEIF(E62:Q62,"<>0") -> 72.077294 | U62: {=_xlfn.STDEV.S(IF(E62:Q62<>0,E62:Q62))} -> 66.844888
C63: Graphics | G63: =(G22-F22)/ABS(F22)*100 -> 10.697809 | H63: =(H22-G22)/ABS(G22)*100 -> 9.0648606 | I63: =(I22-H22)/ABS(H22)*100 -> 39.049439 | J63: =(J22-I22)/ABS(I22)*100 -> 39.762968 | K63: =(K22-J22)/ABS(J22)*100 -> 0.27036992 | L63: =(L22-K22)/ABS(K22)*100 -> -6.3733301 | M63: =(M22-L22)/ABS(L22)*100 -> 28.734128 | N63: =(N22-M22)/ABS(M22)*100 -> 61.358552 | ... P63: =(P22-O22)/ABS(O22)*100 -> 13.530993 | R63: =AVERAGEIF(E63:Q63,"<>0") -> 17.11273 | U63: {=_xlfn.STDEV.S(IF(E63:Q63<>0,E63:Q63))} -> 25.411807
C64: All Other | G64: =(G23-F23)/ABS(F23)*100 -> 0 | H64: =(H23-G23)/ABS(G23)*100 -> 0 | I64: =(I23-H23)/ABS(H23)*100 -> 0 | J64: =(J23-I23)/ABS(I23)*100 -> -83.712121 | K64: =(K23-J23)/ABS(J23)*100 -> -100 | L64: =(L23-K23)/ABS(K23)*100 -> #DIV/0! | M64: =(M23-L23)/ABS(L23)*100 -> #DIV/0! | N64: =(N23-M23)/ABS(M23)*100 -> #DIV/0! | ... P64: =(P23-O23)/ABS(O23)*100 -> #DIV/0! | R64: =AVERAGEIF(E64:Q64,"<>0") -> #DIV/0! | U64: {=_xlfn.STDEV.S(IF(E64:Q64<>0,E64:Q64))} -> #DIV/0!
C65: TOTAL REVENUE GROWTH (%) | G65: =(G24-F24)/ABS(F24)*100 -> 13.365617 | H65: =(H24-G24)/ABS(G24)*100 -> 7.0055532 | I65: =(I24-H24)/ABS(H24)*100 -> 37.924152 | J65: =(J24-I24)/ABS(I24)*100 -> 40.578871 | K65: =(K24-J24)/ABS(J24)*100 -> 20.60943 | L65: =(L24-K24)/ABS(K24)*100 -> -6.8111984 | M65: =(M24-L24)/ABS(L24)*100 -> 52.729438 | N65: =(N24-M24)/ABS(M24)*100 -> 61.403298 | ... P65: =(P24-O24)/ABS(O24)*100 -> 125.85453 | R65: =AVERAGEIF(E65:Q65,"<>0") -> 35.288262 | S65: =MEDIAN(E65:Q65) -> 29.266791 | U65: {=_xlfn.STDEV.S(IF(E65:Q65<>0,E65:Q65))} -> 39.045985 | V65: =R65-U65 -> -3.757723
C68: Operating Income Growth (%)
C69: Compute & Networking | G69: =(G27-F27)/ABS(F27)*100 -> 5.2238806 | H69: =(H27-G27)/ABS(G27)*100 -> 5.9055118 | I69: =(I27-H27)/ABS(H27)*100 -> 96.23431 | J69: =(J27-I27)/ABS(I27)*100 -> 3466.6667 | K69: =(K27-J27)/ABS(J27)*100 -> 312.87129 | L69: =(L27-K27)/ABS(K27)*100 -> -39.968026 | M69: =(M27-L27)/ABS(L27)*100 -> 239.28096 | N69: =(N27-M27)/ABS(M27)*100 -> 80.455259 | ... P69: =(P27-O27)/ABS(O27)*100 -> 529.86425 | R69: =AVERAGEIF(E69:Q69,"<>0") -> 470.70822 | U69: {=_xlfn.STDEV.S(IF(E69:Q69<>0,E69:Q69))} -> 1067.4747
C70: Graphics | G70: =(G28-F28)/ABS(F28)*100 -> 33.293413 | H70: =(H28-G28)/ABS(G28)*100 -> 20.754717 | I70: =(I28-H28)/ABS(H28)*100 -> 62.202381 | J70: =(J28-I28)/ABS(I28)*100 -> 60.87156 | K70: =(K28-J28)/ABS(J28)*100 -> -2.566296 | L70: =(L28-K28)/ABS(K28)*100 -> -4.3898156 | M70: =(M28-L28)/ABS(L28)*100 -> 41.169268 | N70: =(N28-M28)/ABS(M28)*100 -> 84.128361 | ... P70: =(P28-O28)/ABS(O28)*100 -> 28.427065 | R70: =AVERAGEIF(E70:Q70,"<>0") -> 27.749404 | U70: {=_xlfn.STDEV.S(IF(E70:Q70<>0,E70:Q70))} -> 38.257153
C71: All Other | G71: =(G29-F29)/ABS(F29)*100 -> -40.84507 | H71: =(H29-G29)/ABS(G29)*100 -> -258 | I71: =(I29-H29)/ABS(H29)*100 -> 33.798883 | J71: =(J29-I29)/ABS(I29)*100 -> -153.16456 | K71: =(K29-J29)/ABS(J29)*100 -> -44 | L71: =(L29-K29)/ABS(K29)*100 -> -35.648148 | M71: =(M29-L29)/ABS(L29)*100 -> -124.23208 | N71: =(N29-M29)/ABS(M29)*100 -> -16.019787 | ... P71: =(P29-O29)/ABS(O29)*100 -> 9.6285345 | R71: =AVERAGEIF(E71:Q71,"<>0") -> -70.595025 | U71: {=_xlfn.STDEV.S(IF(E71:Q71<>0,E71:Q71))} -> 86.915366
C72: OPERATING INCOME GROWTH (%) | G72: =(G30-F30)/ABS(F30)*100 -> 53.024194 | H72: =(H30-G30)/ABS(G30)*100 -> -1.5810277 | I72: =(I30-H30)/ABS(H30)*100 -> 158.90228 | J72: =(J30-I30)/ABS(I30)*100 -> 65.977249 | K72: =(K30-J30)/ABS(J30)*100 -> 18.504673 | L72: =(L30-K30)/ABS(K30)*100 -> -25.184017 | M72: =(M30-L30)/ABS(L30)*100 -> 59.24104 | N72: =(N30-M30)/ABS(M30)*100 -> 121.55781 | ... P72: =(P30-O30)/ABS(O30)*100 -> 680.58712 | R72: =AVERAGEIF(E72:Q72,"<>0") -> 107.30968 | S72: =MEDIAN(E72:Q72) -> 56.132617 | U72: {=_xlfn.STDEV.S(IF(E72:Q72<>0,E72:Q72))} -> 211.62881
B76: P&L
B77: Revenue | F77: 4130 | G77: 4682 | H77: 5010 | I77: 6910 | J77: 9714 | K77: 11716 | L77: 10918 | M77: 16675 | N77: 26914 | O77: 26974 | P77: 60922
B78: Cost of Revenue | F78: 1862 | G78: 2083 | H78: 2199 | I78: 2847 | J78: 3892 | K78: 4545 | L78: 4150 | M78: 6279 | N78: 9439 | O78: 11618 | P78: 16621
B79: Gross Profit | F79: =F77-F78 -> 2268 | G79: =G77-G78 -> 2599 | H79: =H77-H78 -> 2811 | I79: =I77-I78 -> 4063 | J79: =J77-J78 -> 5822 | K79: =K77-K78 -> 7171 | L79: =L77-L78 -> 6768 | M79: =M77-M78 -> 10396 | ... P79: =P77-P78 -> 44301
C80: GP margin (%) | F80: =IFERROR(F79/F77*100,0) -> 54.915254 | G80: =IFERROR(G79/G77*100,0) -> 55.510466 | H80: =IFERROR(H79/H77*100,0) -> 56.107784 | I80: =IFERROR(I79/I77*100,0) -> 58.798842 | J80: =IFERROR(J79/J77*100,0) -> 59.934116 | K80: =IFERROR(K79/K77*100,0) -> 61.206897 | L80: =IFERROR(L79/L77*100,0) -> 61.989375 | M80: =IFERROR(M79/M77*100,0) -> 62.344828 | ... P80: =IFERROR(P79/P77*100,0) -> 72.717573 | R80: =AVERAGE(E80:Q80) -> 60.489369
B82: Research & Development | F82: 1336 | G82: 1360 | H82: 1331 | I82: 1463 | J82: 1797 | K82: 2376 | L82: 2829 | M82: 3924 | N82: 5268 | O82: 7339 | P82: 8675 | R82: =AVERAGE(E82:Q82)/AVERAGE($E$77:$Q$77)*100 -> 20.425324
B83: Sales, general & admin | F83: 436 | G83: 480 | H83: 602 | I83: 663 | J83: 815 | K83: 991 | L83: 1093 | M83: 1940 | N83: 2166 | O83: =2440 -> 2440 | P83: 2654 | R83: =AVERAGE(E83:Q83)/AVERAGE($E$77:$Q$77)*100 -> 7.7371116
B84: Restructuring & other charges | F84: 0 | G84: 0 | H84: 131 | I84: 3 | J84: 0 | K84: 0 | L84: 0 | M84: 0 | N84: 0 | O84: 0 | P84: 0
B85: Acquisition termination cost | F85: 0 | G85: 0 | H85: 0 | I85: 0 | J85: 0 | K85: 0 | L85: 0 | M85: 0 | N85: 0 | O85: 1353 | P85: 0
B86: Total Cost & Expenses | F86: =SUM(F82:F85) -> 1772 | G86: =SUM(G82:G85) -> 1840 | H86: =SUM(H82:H85) -> 2064 | I86: =SUM(I82:I85) -> 2129 | J86: =SUM(J82:J85) -> 2612 | K86: =SUM(K82:K85) -> 3367 | L86: =SUM(L82:L85) -> 3922 | M86: =SUM(M82:M85) -> 5864 | ... P86: =SUM(P82:P85) -> 11329
B88: Operating Income | F88: =F79-F86 -> 496 | G88: =G79-G86 -> 759 | H88: =H79-H86 -> 747 | I88: =I79-I86 -> 1934 | J88: =J79-J86 -> 3210 | K88: =K79-K86 -> 3804 | L88: =L79-L86 -> 2846 | M88: =M79-M86 -> 4532 | ... P88: =P79-P86 -> 32972
C89: Operating margin (%) | F89: =IFERROR(F88/F77*100,0) -> 12.009685 | G89: =IFERROR(G88/G77*100,0) -> 16.211021 | H89: =IFERROR(H88/H77*100,0) -> 14.91018 | I89: =IFERROR(I88/I77*100,0) -> 27.988423 | J89: =IFERROR(J88/J77*100,0) -> 33.04509 | K89: =IFERROR(K88/K77*100,0) -> 32.468419 | L89: =IFERROR(L88/L77*100,0) -> 26.067045 | M89: =IFERROR(M88/M77*100,0) -> 27.178411 | ... P89: =IFERROR(P88/P77*100,0) -> 54.121664 | R89: =AVERAGE(E89:Q89) -> 26.997017
B91: Other Income / (expense), Net | F91: =17-10+7 -> 14 | G91: =28-46+14 -> -4 | H91: =39-47+4 -> -4 | I91: =54-58-25 -> -29 | J91: =69-61-22 -> -14 | K91: =136-58+14 -> 92 | L91: =178-52-2 -> 124 | M91: =57-184+4 -> -123 | N91: =29-236+107 -> -100 | O91: =267-262-48 -> -43 | P91: =866-257+237 -> 846 | R91: =AVERAGE(E91:Q91)/AVERAGE(E77:Q77)*100 -> 0.41123723
B93: Income before taxation | F93: =F88+F91 -> 510 | G93: =G88+G91 -> 755 | H93: =H88+H91 -> 743 | I93: =I88+I91 -> 1905 | J93: =J88+J91 -> 3196 | K93: =K88+K91 -> 3896 | L93: =L88+L91 -> 2970 | M93: =M88+M91 -> 4409 | ... P93: =P88+P91 -> 33818
B95: Income tax expense / (benefit) | F95: 70 | G95: 124 | H95: 129 | I95: 239 | J95: 149 | K95: -245 | L95: 174 | M95: 77 | N95: 189 | O95: -187 | P95: 4058 | R95: =AVERAGE(E95:Q95)/AVERAGE(E93:Q93)*100 -> 7.202521
B97: Net Income | F97: =F93-F95 -> 440 | G97: =G93-G95 -> 631 | H97: =H93-H95 -> 614 | I97: =I93-I95 -> 1666 | J97: =J93-J95 -> 3047 | K97: =K93-K95 -> 4141 | L97: =L93-L95 -> 2796 | M97: =M93-M95 -> 4332 | ... P97: =P93-P95 -> 29760
C98: Net income margin (%) | F98: =IFERROR(F97/F77*100,0) -> 10.653753 | G98: =IFERROR(G97/G77*100,0) -> 13.477147 | H98: =IFERROR(H97/H77*100,0) -> 12.255489 | I98: =IFERROR(I97/I77*100,0) -> 24.109986 | J98: =IFERROR(J97/J77*100,0) -> 31.367099 | K98: =IFERROR(K97/K77*100,0) -> 35.344828 | L98: =IFERROR(L97/L77*100,0) -> 25.609086 | M98: =IFERROR(M97/M77*100,0) -> 25.97901 | ... P98: =IFERROR(P97/P77*100,0) -> 48.849348 | R98: =AVERAGE(E98:Q98) -> 25.461186
C102: Valuation Multiples / Shareholder ratios
C103: No. of Shares (Pre-Split) | F103: =568 -> 568 | G103: =545 -> 545 | H103: =539 -> 539 | I103: =585 -> 585 | J103: =606 -> 606 | K103: =2423 -> 2423 | L103: =2450 -> 2450 | M103: =2479 -> 2479 | N103: =2506 -> 2506 | O103: =2466 -> 2466 | P103: =2464 -> 2464
C104: No. of Shares (Splited) | F104: =F103*10*4 -> 22720 | G104: =G103*10*4 -> 21800 | H104: =H103*10*4 -> 21560 | I104: =I103*10*4 -> 23400 | J104: =J103*10*4 -> 24240 | K104: =K103*10 -> 24230 | L104: =L103*10 -> 24500 | M104: =M103*10 -> 24790 | N104: =N103*10 -> 25060 | O104: =O103*10 -> 24660 | P104: =P103*10 -> 24640
C105: Share Price | F105: 0.39 | G105: 0.48 | H105: 0.73 | I105: 2.73 | J105: 6.14 | K105: 3.59 | L105: 5.91 | M105: 12.99 | N105: 24.49 | O105: 19.54 | P105: 61.53 | T105: =((P105/F105)^(1/4)-1)*100 -> 254.40968
C106: EPS | F106: =IFERROR(F97/F104,0) -> 0.019366197 | G106: =IFERROR(G97/G104,0) -> 0.028944954 | H106: =IFERROR(H97/H104,0) -> 0.028478664 | I106: =IFERROR(I97/I104,0) -> 0.071196581 | J106: =IFERROR(J97/J104,0) -> 0.12570132 | K106: =IFERROR(K97/K104,0) -> 0.17090384 | L106: =IFERROR(L97/L104,0) -> 0.11412245 | M106: =IFERROR(M97/M104,0) -> 0.17474788 | ... P106: =IFERROR(P97/P104,0) -> 1.2077922
C107: P/E | F107: =F105/F106 -> 20.138182 | G107: =G105/G106 -> 16.583201 | H107: =H105/H106 -> 25.633225 | I107: =I105/I106 -> 38.344538 | J107: =J105/J106 -> 48.845947 | K107: =K105/K106 -> 21.005965 | L107: =L105/L106 -> 51.786481 | M107: =M105/M106 -> 74.335665 | ... P107: =P105/P106 -> 50.944194 | R107: =AVERAGE(E107:Q107) -> 47.35138 | U107: =_xlfn.STDEV.S(E107:Q107) -> 28.114575 | V107: =R107-U107 -> 19.236805
C108: Sales per share | F108: =F77/F104 -> 0.18177817 | G108: =G77/G104 -> 0.21477064 | H108: =H77/H104 -> 0.23237477 | I108: =I77/I104 -> 0.29529915 | J108: =J77/J104 -> 0.40074257 | K108: =K77/K104 -> 0.48353281 | L108: =L77/L104 -> 0.44563265 | M108: =M77/M104 -> 0.67265026 | ... P108: =P77/P104 -> 2.4724838
C109: Price / Sales | F109: =F105/F108 -> 2.1454722 | G109: =G105/G108 -> 2.2349423 | H109: =H105/H108 -> 3.141477 | I109: =I105/I108 -> 9.2448625 | J109: =J105/J108 -> 15.321557 | K109: =K105/K108 -> 7.424522 | L109: =L105/L108 -> 13.262044 | M109: =M105/M108 -> 19.31167 | ... P109: =P105/P108 -> 24.885907 | R109: =AVERAGE(E109:Q109) -> 12.512652 | U109: =_xlfn.STDEV.S(E109:Q109) -> 8.2449786 | V109: =R109-U109 -> 4.2676731
C111: Market Cap | F111: =F104*F105 -> 8860.8 | G111: =G104*G105 -> 10464 | H111: =H104*H105 -> 15738.8 | I111: =I104*I105 -> 63882 | J111: =J104*J105 -> 148833.6 | K111: =K104*K105 -> 86985.7 | L111: =L104*L105 -> 144795 | M111: =M104*M105 -> 322022.1 | ... P111: =P104*P105 -> 1516099.2
C112: Enterprise Value (EV) MC+Debt-Cash | F112: =F111+(F144+F148)-(F123+F124) -> 5544.8 | G112: =G111+(G144+G148)-(G123+G124) -> 7225 | H112: =H111+(H144+H148)-(H123+H124) -> 12114.8 | I112: =I111+(I144+I148)-(I123+I124) -> 59863 | J112: =J111+(J144+J148)-(J123+J124) -> 143725.6 | K112: =K111+(K144+K148)-(K123+K124) -> 81551.7 | L112: =L111+(L144+L148)-(L123+L124) -> 135889 | M112: =M111+(M144+M148)-(M123+M124) -> 317424.1 | ... P112: =P111+(P144+P148)-(P123+P124) -> 1499824.2
C113: EV / EBITDA | F113: =F112/(F179+F181+F95) -> 7.4029372 | G113: =G112/(G179+G181+G95) -> 7.4102564 | H113: =H112/(H179+H181+H95) -> 12.888085 | I113: =I112/(I179+I181+I95) -> 28.615201 | J113: =J112/(J179+J181+J95) -> 42.334492 | K113: =K112/(K179+K181+K95) -> 19.613203 | L113: =L112/(L179+L181+L95) -> 40.551776 | M113: =M112/(M179+M181+M95) -> 57.640113 | ... P113: =P112/(P179+P181+P95) -> 42.456666 | R113: =AVERAGE(E113:Q113) -> 36.087517
C114: EV / Revenue | F114: =F112/F77 -> 1.3425666 | G114: =G112/G77 -> 1.543144 | H114: =H112/H77 -> 2.4181238 | I114: =I112/I77 -> 8.6632417 | J114: =J112/J77 -> 14.795718 | K114: =K112/K77 -> 6.9607118 | L114: =L112/L77 -> 12.446327 | M114: =M112/M77 -> 19.035928 | ... P114: =P112/P77 -> 24.618762 | R114: =AVERAGE(E114:Q114) -> 12.002099
C116: Dividend / Share | F116: =ABS(F200/F104) -> 0.0079665493 | G116: =ABS(G200/G104) -> 0.0085321101 | H116: =ABS(H200/H104) -> 0.0098794063 | I116: =ABS(I200/I104) -> 0.011153846 | J116: =ABS(J200/J104) -> 0.014067657 | K116: =ABS(K200/K104) -> 0.015311597 | L116: =ABS(L200/L104) -> 0.015918367 | M116: =ABS(M200/M104) -> 0.015933844 | ... P116: =ABS(P200/P104) -> 0.016030844 | R116: =AVERAGE(E116:Q116) -> 0.013350501 | S116: =MEDIAN(E116:Q116) -> 0.015311597
C117: Dividend yield | F117: =F116/F105 -> 0.020427049 | G117: =G116/G105 -> 0.017775229 | H117: =H116/H105 -> 0.013533433 | I117: =I116/I105 -> 0.0040856579 | J117: =J116/J105 -> 0.0022911493 | K117: =K116/K105 -> 0.0042650689 | L117: =L116/L105 -> 0.0026934632 | M117: =M116/M105 -> 0.0012266239 | ... P117: =P116/P105 -> 0.00026053704 | R117: =AVERAGE(E117:Q117) -> 0.0061849381 | S117: =MEDIAN(E117:Q117) -> 0.0026934632
B121: Balance Sheet
B122: Current Assets
C123: Cash & Cash Equivalents | F123: 1152 | G123: 497 | H123: 596 | I123: 1766 | J123: 4002 | K123: 782 | L123: 10896 | M123: 847 | N123: 1990 | O123: 3389 | P123: 7280
C124: Marketable Securities | F124: 3520 | G124: 4126 | H124: 4441 | I124: 5032 | J124: 3106 | K124: 6640 | L124: 1 | M124: 10714 | N124: 19218 | O124: 9907 | P124: 18704
C125: Accounts Receivables | F125: 426 | G125: 474 | H125: 505 | I125: 826 | J125: 1265 | K125: 1424 | L125: 1657 | M125: 2429 | N125: 4650 | O125: 3827 | P125: 9999
C126: Inventories | F126: 388 | G126: 483 | H126: 418 | I126: 794 | J126: 796 | K126: 1575 | L126: 979 | M126: 1826 | N126: 2605 | O126: 5159 | P126: 5282
C127: Prepayments & other current assets | F127: 70 | G127: 70 | H127: 93 | I127: 118 | J127: 86 | K127: 136 | L127: 157 | M127: 239 | N127: 366 | O127: 791 | P127: 3080
B128: Total Current Assets | F128: =SUM(F123:F127) -> 5556 | G128: =SUM(G123:G127) -> 5650 | H128: =SUM(H123:H127) -> 6053 | I128: =SUM(I123:I127) -> 8536 | J128: =SUM(J123:J127) -> 9255 | K128: =SUM(K123:K127) -> 10557 | L128: =SUM(L123:L127) -> 13690 | M128: =SUM(M123:M127) -> 16055 | ... P128: =SUM(P123:P127) -> 44345
B130: Non-Current Assets
...

Sheet Sharpe, Sortino
B3: NVDA Monthly Price Changes (5 years) | L3: United States 10-Year Bond Yield
B4: https://www.investing.com/equities/nvidia-corp-historical-data | L4: https://www.investing.com/rates-bonds/u.s.-10-year-bond-yield-historical-data
B5: Feb'20 - Jan'24 | L5: Risk free rate average | O5: =[1]Sheet1!$E$6 -> 0.0246945 | S5: TEST (Manual calculation of Monthly Std Dev of Excess Returns - 5 Years)
F7: [1] | G7: [2] | H7: [1] - [2] | J7: [1] - [2] | S7: Sharpe | X7: Sortino
B8: Date | C8: Price | D8: Change % | F8: Change | G8: Monthly Risk free rate | H8: Monthly Excess returns | J8: Monthly Excess negative returns | S8: Average Monthly Excess Returns | U8: Difference Squared | V8: Monthly Std Dev of excess returns (σ) | X8: Average Monthly Excess Negative Returns | Y8: Difference Squared | Z8: Monthly Std Dev of excess returns (σ)
A9: 1 | B9: 45292 | C9: 61.53 | D9: 0.2424 | F9: =D9 -> 0.2424 | G9: =O$5/12 -> 0.002057875 | H9: =F9-G9 -> 0.24034212 | J9: =IF(H9<0,H9,"") | L9: Sharpe Ratio | O9: 1 Year | P9: 3 Years | Q9: 5 Years | S9: =AVERAGE(H9:H68) -> 0.056620458 | T9: 1 | U9: =(H9-S$9)^2 -> 0.033753651 | V9: =(U70/T68)^(1/2) -> 0.14325812 | X9: =AVERAGE(J9:J68) -> -0.10091287 | Y9: =IF(J9="","",(J9-X$9)^2) | Z9: =(Y70/(COUNT(Y9:Y69)-1))^(1/2) -> 0.092063293
A10: 2 | B10: 45261 | C10: 49.52 | D10: 0.0588 | F10: =D10 -> 0.0588 | G10: =O$5/12 -> 0.002057875 | H10: =F10-G10 -> 0.056742125 | J10: =IF(H10<0,H10,"") | T10: 2 | U10: =(H10-S$9)^2 -> 1.4802778e-08 | Y10: =IF(J10="","",(J10-X$9)^2)
A11: 3 | B11: 45231 | C11: 46.77 | D11: 0.1469 | F11: =D11 -> 0.1469 | G11: =O$5/12 -> 0.002057875 | H11: =F11-G11 -> 0.14484212 | J11: =IF(H11<0,H11,"") | L11: Monthly Std Dev of excess returns (σ) | O11: =STDEV.P(H9:H20) -> 0.12801246 | P11: =STDEV.P(H9:H44) -> 0.16353309 | Q11: =STDEV.P(H9:H68) -> 0.14325812 | T11: 3 | U11: =(H11-S$9)^2 -> 0.0077830625 | Y11: =IF(J11="","",(J11-X$9)^2)
A12: 4 | B12: 45200 | C12: 40.78 | D12: -0.0625 | F12: =D12 -> -0.0625 | G12: =O$5/12 -> 0.002057875 | H12: =F12-G12 -> -0.064557875 | J12: =IF(H12<0,H12,"") -> -0.064557875 | L12: Monthly Portfolio return (Rp) | O12: =(1+O19)^(1/12)-1 -> 0.084597814 | P12: =(1+P19)^(1/12)-1 -> 0.042587431 | Q12: =(1+Q19)^(1/12)-1 -> 0.047229 | T12: 4 | U12: =(H12-S$9)^2 -> 0.014684188 | Y12: =IF(J12="","",(J12-X$9)^2) -> 0.001321686
A13: 5 | B13: 45170 | C13: 43.5 | D13: -0.1187 | F13: =D13 -> -0.1187 | G13: =O$5/12 -> 0.002057875 | H13: =F13-G13 -> -0.12075788 | J13: =IF(H13<0,H13,"") -> -0.12075788 | L13: Monthly Risk-free return - US 10Yr Yield (Rf) | O13: =O20/12 -> 0.002057875 | P13: =P20/12 -> 0.002057875 | Q13: =Q20/12 -> 0.002057875 | T13: 5 | U13: =(H13-S$9)^2 -> 0.031463073 | Y13: =IF(J13="","",(J13-X$9)^2) -> 0.00039382402
A14: 6 | B14: 45139 | C14: 49.35 | D14: 0.0562 | F14: =D14 -> 0.0562 | G14: =O$5/12 -> 0.002057875 | H14: =F14-G14 -> 0.054142125 | J14: =IF(H14<0,H14,"") | L14: Excess return (Rp - Rf) | O14: =O12-O13 -> 0.082539939 | P14: =P12-P13 -> 0.040529556 | Q14: =Q12-Q13 -> 0.045171125 | T14: 6 | U14: =(H14-S$9)^2 -> 6.1421361e-06 | Y14: =IF(J14="","",(J14-X$9)^2)
A15: 7 | B15: 45108 | C15: 46.73 | D15: 0.1047 | F15: =D15 -> 0.1047 | G15: =O$5/12 -> 0.002057875 | H15: =F15-G15 -> 0.10264213 | J15: =IF(H15<0,H15,"") | T15: 7 | U15: =(H15-S$9)^2 -> 0.0021179938 | Y15: =IF(J15="","",(J15-X$9)^2)
A16: 8 | B16: 45078 | C16: 42.3 | D16: 0.1181 | F16: =D16 -> 0.1181 | G16: =O$5/12 -> 0.002057875 | H16: =F16-G16 -> 0.11604212 | J16: =IF(H16<0,H16,"") | L16: Monthly Sharpe Ratio ( [Rp - Rf] / σ ) | O16: =O14/O11 -> 0.6447805 | P16: =P14/P11 -> 0.24783704 | Q16: =Q14/Q11 -> 0.31531283 | T16: 8 | U16: =(H16-S$9)^2 -> 0.0035309345 | Y16: =IF(J16="","",(J16-X$9)^2)
A17: 9 | B17: 45047 | C17: 37.83 | D17: 0.3634 | F17: =D17 -> 0.3634 | G17: =O$5/12 -> 0.002057875 | H17: =F17-G17 -> 0.36134213 | J17: =IF(H17<0,H17,"") | T17: 9 | U17: =(H17-S$9)^2 -> 0.092855294 | Y17: =IF(J17="","",(J17-X$9)^2)
A18: 10 | B18: 45017 | C18: 27.75 | D18: -0.001 | F18: =D18 -> -0.001 | G18: =O$5/12 -> 0.002057875 | H18: =F18-G18 -> -0.003057875 | J18: =IF(H18<0,H18,"") -> -0.003057875 | L18: Annualized Std Dev of excess returns (σ) | O18: =O11*12^(1/2) -> 0.44344818 | P18: =P11*12^(1/2) -> 0.56649524 | Q18: =Q11*12^(1/2) -> 0.4962607 | T18: 10 | U18: =(H18-S$9)^2 -> 0.0035615035 | Y18: =IF(J18="","",(J18-X$9)^2) -> 0.009575601
A19: 11 | B19: 44986 | C19: 27.78 | D19: 0.1965 | F19: =D19 -> 0.1965 | G19: =O$5/12 -> 0.002057875 | H19: =F19-G19 -> 0.19444212 | J19: =IF(H19<0,H19,"") | L19: Annualized Portfolio return (Rp) | O19: =($C$9/$C$20)^(1/($A$20/12))-1 -> 1.6498708 | P19: =($C$9/$C$44)^(1/($A$44/12))-1 -> 0.64949051 | Q19: =($C$9/$C$68)^(1/($A$68/12))-1 -> 0.73980239 | T19: 11 | U19: =(H19-S$9)^2 -> 0.018994812 | Y19: =IF(J19="","",(J19-X$9)^2)
A20: 12 | B20: 44958 | C20: 23.22 | D20: 0.1883 | F20: =D20 -> 0.1883 | G20: =O$5/12 -> 0.002057875 | H20: =F20-G20 -> 0.18624213 | J20: =IF(H20<0,H20,"") | L20: Annualized Risk-free return - US 10Yr Yield (Rf) | O20: =$O$5 -> 0.0246945 | P20: =$O$5 -> 0.0246945 | Q20: =$O$5 -> 0.0246945 | T20: 12 | U20: =(H20-S$9)^2 -> 0.016801776 | Y20: =IF(J20="","",(J20-X$9)^2)
A21: 13 | B21: 44927 | C21: 19.54 | D21: 0.3369 | F21: =D21 -> 0.3369 | G21: =O$5/12 -> 0.002057875 | H21: =F21-G21 -> 0.33484212 | J21: =IF(H21<0,H21,"") | L21: Excess return (Rp - Rf) | O21: =O19-O20 -> 1.6251763 | P21: =P19-P20 -> 0.62479601 | Q21: =Q19-Q20 -> 0.71510789 | T21: 13 | U21: =(H21-S$9)^2 -> 0.077407296 | Y21: =IF(J21="","",(J21-X$9)^2)
A22: 14 | B22: 44896 | C22: 14.61 | D22: -0.1364 | F22: =D22 -> -0.1364 | G22: =O$5/12 -> 0.002057875 | H22: =F22-G22 -> -0.13845788 | J22: =IF(H22<0,H22,"") -> -0.13845788 | T22: 14 | U22: =(H22-S$9)^2 -> 0.038055556 | Y22: =IF(J22="","",(J22-X$9)^2) -> 0.001409627
A23: 15 | B23: 44866 | C23: 16.92 | D23: 0.2538 | F23: =D23 -> 0.2538 | G23: =O$5/12 -> 0.002057875 | H23: =F23-G23 -> 0.25174212 | J23: =IF(H23<0,H23,"") | L23: Annualized Sharpe Ratio ( [Rp - Rf] / σ ) | O23: =O21/O18 -> 3.6648618 | P23: =P21/P18 -> 1.1029148 | Q23: =Q21/Q18 -> 1.4409924 | T23: 15 | U23: =(H23-S$9)^2 -> 0.038072465 | Y23: =IF(J23="","",(J23-X$9)^2)
A24: 16 | B24: 44835 | C24: 13.5 | D24: 0.1119 | F24: =D24 -> 0.1119 | G24: =O$5/12 -> 0.002057875 | H24: =F24-G24 -> 0.10984212 | J24: =IF(H24<0,H24,"") | T24: 16 | U24: =(H24-S$9)^2 -> 0.0028325458 | Y24: =IF(J24="","",(J24-X$9)^2)
A25: 17 | B25: 44805 | C25: 12.14 | D25: -0.1958 | F25: =D25 -> -0.1958 | G25: =O$5/12 -> 0.002057875 | H25: =F25-G25 -> -0.19785787 | J25: =IF(H25<0,H25,"") -> -0.19785787 | T25: 17 | U25: =(H25-S$9)^2 -> 0.064759222 | Y25: =IF(J25="","",(J25-X$9)^2) -> 0.009398333
A26: 18 | B26: 44774 | C26: 15.09 | D26: -0.169 | F26: =D26 -> -0.169 | G26: =O$5/12 -> 0.002057875 | H26: =F26-G26 -> -0.17105787 | J26: =IF(H26<0,H26,"") -> -0.17105787 | L26: Sortino Ratio | O26: 1 Year | P26: 3 Years | Q26: 5 Years | T26: 18 | U26: =(H26-S$9)^2 -> 0.051837423 | Y26: =IF(J26="","",(J26-X$9)^2) -> 0.004920321
A27: 19 | B27: 44743 | C27: 18.16 | D27: 0.1982 | F27: =D27 -> 0.1982 | G27: =O$5/12 -> 0.002057875 | H27: =F27-G27 -> 0.19614213 | J27: =IF(H27<0,H27,"") | T27: 19 | U27: =(H27-S$9)^2 -> 0.019466295 | Y27: =IF(J27="","",(J27-X$9)^2)
A28: 20 | B28: 44713 | C28: 15.16 | D28: -0.1881 | F28: =D28 -> -0.1881 | G28: =O$5/12 -> 0.002057875 | H28: =F28-G28 -> -0.19015788 | J28: =IF(H28<0,H28,"") -> -0.19015788 | L28: Monthly Std Dev of excess negative returns (σd) | O28: =_xlfn.STDEV.S(J9:J20) -> 0.058869885 | P28: =_xlfn.STDEV.S(J9:J44) -> 0.090259137 | Q28: =_xlfn.STDEV.S(J9:J68) -> 0.092063293 | T28: 20 | U28: =(H28-S$9)^2 -> 0.060899546 | Y28: =IF(J28="","",(J28-X$9)^2) -> 0.00796467
A29: 21 | B29: 44682 | C29: 18.67 | D29: 0.0067 | F29: =D29 -> 0.0067 | G29: =O$5/12 -> 0.002057875 | H29: =F29-G29 -> 0.004642125 | J29: =IF(H29<0,H29,"") | L29: Monthly Portfolio return (Rp) | O29: =(1+O36)^(1/12)-1 -> 0.084597814 | P29: =(1+P36)^(1/12)-1 -> 0.042587431 | Q29: =(1+Q36)^(1/12)-1 -> 0.047229 | T29: 21 | U29: =(H29-S$9)^2 -> 0.0027017471 | Y29: =IF(J29="","",(J29-X$9)^2)
A30: 22 | B30: 44652 | C30: 18.55 | D30: -0.3203 | F30: =D30 -> -0.3203 | G30: =O$5/12 -> 0.002057875 | H30: =F30-G30 -> -0.32235788 | J30: =IF(H30<0,H30,"") -> -0.32235788 | L30: Monthly Risk-free return - US 10Yr Yield (Rf) | O30: =O37/12 -> 0.002057875 | P30: =P37/12 -> 0.002057875 | Q30: =Q37/12 -> 0.002057875 | T30: 22 | U30: =(H30-S$9)^2 -> 0.14362458 | Y30: =IF(J30="","",(J30-X$9)^2) -> 0.049037888
A31: 23 | B31: 44621 | C31: 27.29 | D31: 0.119 | F31: =D31 -> 0.119 | G31: =O$5/12 -> 0.002057875 | H31: =F31-G31 -> 0.11694212 | J31: =IF(H31<0,H31,"") | L31: Excess return (Rp - Rf) | O31: =O29-O30 -> 0.082539939 | P31: =P29-P30 -> 0.040529556 | Q31: =Q29-Q30 -> 0.045171125 | T31: 23 | U31: =(H31-S$9)^2 -> 0.0036387035 | Y31: =IF(J31="","",(J31-X$9)^2)
A32: 24 | B32: 44593 | C32: 24.39 | D32: -0.0041 | F32: =D32 -> -0.0041 | G32: =O$5/12 -> 0.002057875 | H32: =F32-G32 -> -0.006157875 | J32: =IF(H32<0,H32,"") -> -0.006157875 | T32: 24 | U32: =(H32-S$9)^2 -> 0.0039411191 | Y32: =IF(J32="","",(J32-X$9)^2) -> 0.00897851
A33: 25 | B33: 44562 | C33: 24.49 | D33: -0.1675 | F33: =D33 -> -0.1675 | G33: =O$5/12 -> 0.002057875 | H33: =F33-G33 -> -0.16955787 | J33: =IF(H33<0,H33,"") -> -0.16955787 | L33: Monthly Sortino Ratio ( [Rp - Rf] / σ ) | O33: =O31/O28 -> 1.4020741 | P33: =P31/P28 -> 0.44903549 | Q33: =Q31/Q28 -> 0.49065293 | T33: 25 | U33: =(H33-S$9)^2 -> 0.051156638 | Y33: =IF(J33="","",(J33-X$9)^2) -> 0.004712136
A34: 26 | B34: 44531 | C34: 29.41 | D34: -0.0999 | F34: =D34 -> -0.0999 | G34: =O$5/12 -> 0.002057875 | H34: =F34-G34 -> -0.10195788 | J34: =IF(H34<0,H34,"") -> -0.10195788 | T34: 26 | U34: =(H34-S$9)^2 -> 0.025147088 | Y34: =IF(J34="","",(J34-X$9)^2) -> 1.092025e-06
A35: 27 | B35: 44501 | C35: 32.68 | D35: 0.2781 | F35: =D35 -> 0.2781 | G35: =O$5/12 -> 0.002057875 | H35: =F35-G35 -> 0.27604213 | J35: =IF(H35<0,H35,"") | L35: Annualized Std Dev of excess negative returns (σ) | O35: =O28*12^(1/2) -> 0.20393126 | P35: =P28*12^(1/2) -> 0.31266682 | Q35: =Q28*12^(1/2) -> 0.3189166 | T35: 27 | U35: =(H35-S$9)^2 -> 0.048145868 | Y35: =IF(J35="","",(J35-X$9)^2)
A36: 28 | B36: 44470 | C36: 25.57 | D36: 0.2342 | F36: =D36 -> 0.2342 | G36: =O$5/12 -> 0.002057875 | H36: =F36-G36 -> 0.23214213 | J36: =IF(H36<0,H36,"") | L36: Annualized Portfolio return (Rp) | O36: =($C$9/$C$20)^(1/($A$20/12))-1 -> 1.6498708 | P36: =($C$9/$C$44)^(1/($A$44/12))-1 -> 0.64949051 | Q36: =($C$9/$C$68)^(1/($A$68/12))-1 -> 0.73980239 | T36: 28 | U36: =(H36-S$9)^2 -> 0.030807855 | Y36: =IF(J36="","",(J36-X$9)^2)
A37: 29 | B37: 44440 | C37: 20.72 | D37: -0.0746 | F37: =D37 -> -0.0746 | G37: =O$5/12 -> 0.002057875 | H37: =F37-G37 -> -0.076657875 | J37: =IF(H37<0,H37,"") -> -0.076657875 | L37: Annualized Risk-free return - US 10Yr Yield (Rf) | O37: =$O$5 -> 0.0246945 | P37: =$O$5 -> 0.0246945 | Q37: =$O$5 -> 0.0246945 | T37: 29 | U37: =(H37-S$9)^2 -> 0.017763114 | Y37: =IF(J37="","",(J37-X$9)^2) -> 0.00058830503
A38: 30 | B38: 44409 | C38: 22.39 | D38: 0.148 | F38: =D38 -> 0.148 | G38: =O$5/12 -> 0.002057875 | H38: =F38-G38 -> 0.14594213 | J38: =IF(H38<0,H38,"") | L38: Excess return (Rp - Rf) | O38: =O36-O37 -> 1.6251763 | P38: =P36-P37 -> 0.62479601 | Q38: =Q36-Q37 -> 0.71510789 | T38: 30 | U38: =(H38-S$9)^2 -> 0.0079783601 | Y38: =IF(J38="","",(J38-X$9)^2)
A39: 31 | B39: 44378 | C39: 19.5 | D39: -0.0252 | F39: =D39 -> -0.0252 | G39: =O$5/12 -> 0.002057875 | H39: =F39-G39 -> -0.027257875 | J39: =IF(H39<0,H39,"") -> -0.027257875 | T39: 31 | U39: =(H39-S$9)^2 -> 0.0070355748 | Y39: =IF(J39="","",(J39-X$9)^2) -> 0.005425059
A40: 32 | B40: 44348 | C40: 20 | D40: 0.2313 | F40: =D40 -> 0.2313 | G40: =O$5/12 -> 0.002057875 | H40: =F40-G40 -> 0.22924212 | J40: =IF(H40<0,H40,"") | L40: Annualized Sortino Ratio ( [Rp - Rf] / σd ) | O40: =O38/O35 -> 7.9692357 | P40: =P38/P35 -> 1.9982805 | Q40: =Q38/Q35 -> 2.2423037 | T40: 32 | U40: =(H40-S$9)^2 -> 0.02979824 | Y40: =IF(J40="","",(J40-X$9)^2)
A41: 33 | B41: 44317 | C41: 16.24 | D41: 0.0823 | F41: =D41 -> 0.0823 | G41: =O$5/12 -> 0.002057875 | H41: =F41-G41 -> 0.080242125 | J41: =IF(H41<0,H41,"") | T41: 33 | U41: =(H41-S$9)^2 -> 0.00055798314 | Y41: =IF(J41="","",(J41-X$9)^2)
A42: 34 | B42: 44287 | C42: 15.01 | D42: 0.1245 | F42: =D42 -> 0.1245 | G42: =O$5/12 -> 0.002057875 | H42: =F42-G42 -> 0.12244212 | J42: =IF(H42<0,H42,"") | T42: 34 | U42: =(H42-S$9)^2 -> 0.0043324918 | Y42: =IF(J42="","",(J42-X$9)^2)
A43: 35 | B43: 44256 | C43: 13.35 | D43: -0.0267 | F43: =D43 -> -0.0267 | G43: =O$5/12 -> 0.002057875 | H43: =F43-G43 -> -0.028757875 | J43: =IF(H43<0,H43,"") -> -0.028757875 | T43: 35 | U43: =(H43-S$9)^2 -> 0.0072894598 | Y43: =IF(J43="","",(J43-X$9)^2) -> 0.005206344
A44: 36 | B44: 44228 | C44: 13.71 | D44: 0.0558 | F44: =D44 -> 0.0558 | G44: =O$5/12 -> 0.002057875 | H44: =F44-G44 -> 0.053742125 | J44: =IF(H44<0,H44,"") | T44: 36 | U44: =(H44-S$9)^2 -> 8.2848028e-06 | Y44: =IF(J44="","",(J44-X$9)^2)
A45: 37 | B45: 44197 | C45: 12.99 | D45: -0.005 | F45: =D45 -> -0.005 | G45: =O$5/12 -> 0.002057875 | H45: =F45-G45 -> -0.007057875 | J45: =IF(H45<0,H45,"") -> -0.007057875 | T45: 37 | U45: =(H45-S$9)^2 -> 0.0040549301 | Y45: =IF(J45="","",(J45-X$9)^2) -> 0.008808761
A46: 38 | B46: 44166 | C46: 13.06 | D46: -0.0259 | F46: =D46 -> -0.0259 | G46: =O$5/12 -> 0.002057875 | H46: =F46-G46 -> -0.027957875 | J46: =IF(H46<0,H46,"") -> -0.027957875 | T46: 38 | U46: =(H46-S$9)^2 -> 0.0071534945 | Y46: =IF(J46="","",(J46-X$9)^2) -> 0.005322432
A47: 39 | B47: 44136 | C47: 13.4 | D47: 0.0692 | F47: =D47 -> 0.0692 | G47: =O$5/12 -> 0.002057875 | H47: =F47-G47 -> 0.067142125 | J47: =IF(H47<0,H47,"") | T47: 39 | U47: =(H47-S$9)^2 -> 0.00011070547 | Y47: =IF(J47="","",(J47-X$9)^2)
A48: 40 | B48: 44105 | C48: 12.53 | D48: -0.0736 | F48: =D48 -> -0.0736 | G48: =O$5/12 -> 0.002057875 | H48: =F48-G48 -> -0.075657875 | J48: =IF(H48<0,H48,"") -> -0.075657875 | T48: 40 | U48: =(H48-S$9)^2 -> 0.017497557 | Y48: =IF(J48="","",(J48-X$9)^2) -> 0.00063781503
A49: 41 | B49: 44075 | C49: 13.53 | D49: 0.0117 | F49: =D49 -> 0.0117 | G49: =O$5/12 -> 0.002057875 | H49: =F49-G49 -> 0.009642125 | J49: =IF(H49<0,H49,"") | T49: 41 | U49: =(H49-S$9)^2 -> 0.0022069638 | Y49: =IF(J49="","",(J49-X$9)^2)
A50: 42 | B50: 44044 | C50: 13.37 | D50: 0.26 | F50: =D50 -> 0.26 | G50: =O$5/12 -> 0.002057875 | H50: =F50-G50 -> 0.25794213 | J50: =IF(H50<0,H50,"") | T50: 42 | U50: =(H50-S$9)^2 -> 0.040530413 | Y50: =IF(J50="","",(J50-X$9)^2)
A51: 43 | B51: 44013 | C51: 10.61 | D51: 0.1176 | F51: =D51 -> 0.1176 | G51: =O$5/12 -> 0.002057875 | H51: =F51-G51 -> 0.11554212 | J51: =IF(H51<0,H51,"") | T51: 43 | U51: =(H51-S$9)^2 -> 0.0034717628 | Y51: =IF(J51="","",(J51-X$9)^2)
A52: 44 | B52: 43983 | C52: 9.5 | D52: 0.0701 | F52: =D52 -> 0.0701 | G52: =O$5/12 -> 0.002057875 | H52: =F52-G52 -> 0.068042125 | J52: =IF(H52<0,H52,"") | T52: 44 | U52: =(H52-S$9)^2 -> 0.00013045447 | Y52: =IF(J52="","",(J52-X$9)^2)
... A68: 60 | B68: 43497 | C68: 3.86 | D68: 0.0731 | F68: =D68 -> 0.0731 | G68: =O$5/12 -> 0.002057875 | H68: =F68-G68 -> 0.071042125 | J68: =IF(H68<0,H68,"") | T68: 60 | U68: =(H68-S$9)^2 -> 0.00020798447 | Y68: =IF(J68="","",(J68-X$9)^2)
U70: =SUM(U9:U69) -> 1.2313734 | Y70: =SUM(Y9:Y69) -> 0.16103735

Sheet Projection
F1: < Figures are in millions >
F2: Y/E 31/01
F3: 2014 | G3: 2015 | H3: 2016 | I3: 2017 | J3: 2018 | K3: 2019 | L3: 2020 | M3: 2021 | N3: 2022 | O3: 2023 | P3: 2024 | Q3: 2025 | R3: 2026 | S3: 2027 | T3: 2028 | U3: 2029 | V3: 2030 | W3: 2031 | X3: 2032 | Y3: 2033 | Z3: 2034 | AA3: 2035 | AC3: CAGR
T6: Average Growth Rate = | U6: =FS!R65 -> 35.288262 | V6: %
B7: P&L
B8: Revenue | F8: 4130 | G8: 4682 | H8: 5010 | I8: 6910 | J8: 9714 | K8: 11716 | L8: 10918 | M8: 16675 | N8: 26914 | O8: 26974 | P8: 60922 | Q8: =P8*(1+$U6/100) -> 82420.315 | R8: =Q8*(1+$U6/100) -> 111505.01 | S8: =R8*(1+$U6/100) -> 150853.19 | T8: =S8*(1+$U6/100) -> 204086.66 | U8: =T8*(1+$U6/100) -> 276105.3 | V8: =U8*(1+$U6/100) -> 373538.06 | W8: =V8*(1+$U6/100) -> 505353.15 | X8: =W8*(1+$U6/100) -> 683683.49 | ... AA8: =Z8*(1+$U6/100) -> 1692916.1
B9: Cost of Revenue | F9: 1862 | G9: 2083 | H9: 2199 | I9: 2847 | J9: 3892 | K9: 4545 | L9: 4150 | M9: 6279 | N9: 9439 | O9: 11618 | P9: 16621 | Q9: =Q8-Q10 -> 32564.786 | R9: =R8-R10 -> 44056.333 | S9: =S8-S10 -> 59603.048 | T9: =T8-T10 -> 80635.927 | U9: =U8-U10 -> 109090.94 | V9: =V8-V10 -> 147587.24 | W9: =W8-W10 -> 199668.22 | X9: =X8-X10 -> 270127.66 | ... AA9: =AA8-AA10 -> 668881.84
B10: Gross Profit | F10: =F8-F9 -> 2268 | G10: =G8-G9 -> 2599 | H10: =H8-H9 -> 2811 | I10: =I8-I9 -> 4063 | J10: =J8-J9 -> 5822 | K10: =K8-K9 -> 7171 | L10: =L8-L9 -> 6768 | M10: =M8-M9 -> 10396 | ... P10: =P8-P9 -> 44301 | Q10: =Q8*($Q11/100) -> 49855.529 | R10: =R8*($Q11/100) -> 67448.678 | S10: =S8*($Q11/100) -> 91250.145 | T10: =T8*($Q11/100) -> 123450.73 | U10: =U8*($Q11/100) -> 167014.35 | V10: =V8*($Q11/100) -> 225950.82 | W10: =W8*($Q11/100) -> 305684.93 | X10: =X8*($Q11/100) -> 413555.83 | ... AA10: =AA8*($Q11/100) -> 1024034.3
C11: GP margin (%) | F11: =IFERROR(F10/F8*100,0) -> 54.915254 | G11: =IFERROR(G10/G8*100,0) -> 55.510466 | H11: =IFERROR(H10/H8*100,0) -> 56.107784 | I11: =IFERROR(I10/I8*100,0) -> 58.798842 | J11: =IFERROR(J10/J8*100,0) -> 59.934116 | K11: =IFERROR(K10/K8*100,0) -> 61.206897 | L11: =IFERROR(L10/L8*100,0) -> 61.989375 | M11: =IFERROR(M10/M8*100,0) -> 62.344828 | ... P11: =IFERROR(P10/P8*100,0) -> 72.717573 | Q11: =AVERAGE(E11:P11) -> 60.489369
B13: Research & Development | F13: 1336 | G13: 1360 | H13: 1331 | I13: 1463 | J13: 1797 | K13: 2376 | L13: 2829 | M13: 3924 | N13: 5268 | O13: 7339 | P13: 8675
B14: Sales, general & admin | F14: 436 | G14: 480 | H14: 602 | I14: 663 | J14: 815 | K14: 991 | L14: 1093 | M14: 1940 | N14: 2166 | O14: =2440 -> 2440 | P14: 2654
B15: Restructuring & other charges | F15: 0 | G15: 0 | H15: 131 | I15: 3 | J15: 0 | K15: 0 | L15: 0 | M15: 0 | N15: 0 | O15: 0 | P15: 0
B16: Acquisition termination cost | F16: 0 | G16: 0 | H16: 0 | I16: 0 | J16: 0 | K16: 0 | L16: 0 | M16: 0 | N16: 0 | O16: 1353 | P16: 0
B17: Total Cost & Expenses | F17: =SUM(F13:F16) -> 1772 | G17: =SUM(G13:G16) -> 1840 | H17: =SUM(H13:H16) -> 2064 | I17: =SUM(I13:I16) -> 2129 | J17: =SUM(J13:J16) -> 2612 | K17: =SUM(K13:K16) -> 3367 | L17: =SUM(L13:L16) -> 3922 | M17: =SUM(M13:M16) -> 5864 | ... P17: =SUM(P13:P16) -> 11329 | Q17: =Q10-Q19 -> 27604.503 | R17: =R10-R19 -> 37345.652 | S17: =S10-S19 -> 50524.283 | T17: =T10-T19 -> 68353.425 | U17: =U10-U19 -> 92474.16 | V17: =V10-V19 -> 125106.68 | W17: =W10-W19 -> 169254.66 | X17: =X10-X19 -> 228981.69 | ... AA17: =AA10-AA19 -> 566997.45
B19: Operating Income | F19: =F10-F17 -> 496 | G19: =G10-G17 -> 759 | H19: =H10-H17 -> 747 | I19: =I10-I17 -> 1934 | J19: =J10-J17 -> 3210 | K19: =K10-K17 -> 3804 | L19: =L10-L17 -> 2846 | M19: =M10-M17 -> 4532 | ... P19: =P10-P17 -> 32972 | Q19: =Q8*($Q20/100) -> 22251.026 | R19: =R8*($Q20/100) -> 30103.026 | S19: =S8*($Q20/100) -> 40725.861 | T19: =T8*($Q20/100) -> 55097.31 | U19: =U8*($Q20/100) -> 74540.193 | V19: =V8*($Q20/100) -> 100844.13 | W19: =W8*($Q20/100) -> 136430.27 | X19: =X8*($Q20/100) -> 184574.14 | ... AA19: =AA8*($Q20/100) -> 457036.85
C20: Operating margin (%) | F20: =IFERROR(F19/F8*100,0) -> 12.009685 | G20: =IFERROR(G19/G8*100,0) -> 16.211021 | H20: =IFERROR(H19/H8*100,0) -> 14.91018 | I20: =IFERROR(I19/I8*100,0) -> 27.988423 | J20: =IFERROR(J19/J8*100,0) -> 33.04509 | K20: =IFERROR(K19/K8*100,0) -> 32.468419 | L20: =IFERROR(L19/L8*100,0) -> 26.067045 | M20: =IFERROR(M19/M8*100,0) -> 27.178411 | ... P20: =IFERROR(P19/P8*100,0) -> 54.121664 | Q20: =AVERAGE(E20:P20) -> 26.997017
B22: Other Income / (expense), Net | F22: =17-10+7 -> 14 | G22: =28-46+14 -> -4 | H22: =39-47+4 -> -4 | I22: =54-58-25 -> -29 | J22: =69-61-22 -> -14 | K22: =136-58+14 -> 92 | L22: =178-52-2 -> 124 | M22: =57-184+4 -> -123 | N22: =29-236+107 -> -100 | O22: =267-262-48 -> -43 | P22: =866-257+237 -> 846 | Q22: =Q8*(FS!$R$91/100) -> 338.94302 | R22: =R8*(FS!$R$91/100) -> 458.55012 | S22: =S8*(FS!$R$91/100) -> 620.36449 | T22: =T8*(FS!$R$91/100) -> 839.28034 | U22: =U8*(FS!$R$91/100) -> 1135.4478 | V22: =V8*(FS!$R$91/100) -> 1536.1276 | W22: =W8*(FS!$R$91/100) -> 2078.2003 | X22: =X8*(FS!$R$91/100) -> 2811.5611 | ... AA22: =AA8*(FS!$R$91/100) -> 6961.9015
B24: Income before taxation | F24: =F19+F22 -> 510 | G24: =G19+G22 -> 755 | H24: =H19+H22 -> 743 | I24: =I19+I22 -> 1905 | J24: =J19+J22 -> 3196 | K24: =K19+K22 -> 3896 | L24: =L19+L22 -> 2970 | M24: =M19+M22 -> 4409 | ... AA24: =AA19+AA22 -> 463998.75
B26: Income tax expense / (benefit) | F26: 70 | G26: 124 | H26: 129 | I26: 239 | J26: 149 | K26: -245 | L26: 174 | M26: 77 | N26: 189 | O26: -187 | P26: 4058 | Q26: =Q24-Q28 -> 1604.7793 | R26: =R24-R28 -> 2171.078 | S26: =S24-S28 -> 2937.2137 | T26: =T24-T28 -> 3973.7054 | U26: =U24-U28 -> 5375.957 | V26: =V24-V28 -> 7273.0387 | W26: =W24-W28 -> 9839.5677 | X26: =X24-X28 -> 13311.78 | ... AA26: =AA24-AA28 -> 32962.223
B28: Net Income | F28: =F24-F26 -> 440 | G28: =G24-G26 -> 631 | H28: =H24-H26 -> 614 | I28: =I24-I26 -> 1666 | J28: =J24-J26 -> 3047 | K28: =K24-K26 -> 4141 | L28: =L24-L26 -> 2796 | M28: =M24-M26 -> 4332 | ... P28: =P24-P26 -> 29760 | Q28: =Q8*($Q29/100) -> 20985.19 | R28: =R8*($Q29/100) -> 28390.499 | S28: =S8*($Q29/100) -> 38409.012 | T28: =T8*($Q29/100) -> 51962.885 | U28: =U8*($Q29/100) -> 70299.684 | V28: =V8*($Q29/100) -> 95107.22 | W28: =W8*($Q29/100) -> 128668.91 | X28: =X8*($Q29/100) -> 174073.93 | ... AA28: =AA8*($Q29/100) -> 431036.53
C29: Net income margin (%) | F29: =IFERROR(F28/F8*100,0) -> 10.653753 | G29: =IFERROR(G28/G8*100,0) -> 13.477147 | H29: =IFERROR(H28/H8*100,0) -> 12.255489 | I29: =IFERROR(I28/I8*100,0) -> 24.109986 | J29: =IFERROR(J28/J8*100,0) -> 31.367099 | K29: =IFERROR(K28/K8*100,0) -> 35.344828 | L29: =IFERROR(L28/L8*100,0) -> 25.609086 | M29: =IFERROR(M28/M8*100,0) -> 25.97901 | ... P29: =IFERROR(P28/P8*100,0) -> 48.849348 | Q29: =AVERAGE(E29:P29) -> 25.461186
C33: Valuation Multiples / Shareholder ratios
C34: No. of Shares | F34: =568*10*4 -> 22720 | G34: =545*10*4 -> 21800 | H34: =539*10*4 -> 21560 | I34: =585*10*4 -> 23400 | J34: =606*10*4 -> 24240 | K34: =2423*10 -> 24230 | L34: =2450*10 -> 24500 | M34: =2479*10 -> 24790 | N34: =2506*10 -> 25060 | O34: =2466*10 -> 24660 | P34: =2464*10 -> 24640 | Q34: =2464*10 -> 24640 | R34: =2464*10 -> 24640 | S34: =2464*10 -> 24640 | T34: =2464*10 -> 24640 | U34: =2464*10 -> 24640 | V34: =2464*10 -> 24640 | W34: =2464*10 -> 24640 | ... AA34: =2464*10 -> 24640
C35: Share Price | F35: 0.39 | G35: 0.48 | H35: 0.73 | I35: 2.73 | J35: 6.14 | K35: 3.59 | L35: 5.91 | M35: 12.99 | N35: 24.49 | O35: 19.54 | P35: 61.53 | Q35: =Q36*$Q37 -> 40.327828 | R35: =R36*$Q37 -> 54.558818 | S35: =S36*$Q37 -> 73.811677 | T35: =T36*$Q37 -> 99.858534 | U35: =U36*$Q37 -> 135.09688 | V35: =V36*$Q37 -> 182.77021 | W35: =W36*$Q37 -> 247.26665 | X35: =X36*$Q37 -> 334.52275 | ... AA35: =AA36*$Q37 -> 828.335 | AC35: =((AA35/P35)^(1/($AA$3-$P$3))-1)*100 -> 26.662248
C36: EPS | F36: =IFERROR(F28/F34,0) -> 0.019366197 | G36: =IFERROR(G28/G34,0) -> 0.028944954 | H36: =IFERROR(H28/H34,0) -> 0.028478664 | I36: =IFERROR(I28/I34,0) -> 0.071196581 | J36: =IFERROR(J28/J34,0) -> 0.12570132 | K36: =IFERROR(K28/K34,0) -> 0.17090384 | L36: =IFERROR(L28/L34,0) -> 0.11412245 | M36: =IFERROR(M28/M34,0) -> 0.17474788 | ... AA36: =IFERROR(AA28/AA34,0) -> 17.493366
C37: P/E | F37: =F35/F36 -> 20.138182 | G37: =G35/G36 -> 16.583201 | H37: =H35/H36 -> 25.633225 | I37: =I35/I36 -> 38.344538 | J37: =J35/J36 -> 48.845947 | K37: =K35/K36 -> 21.005965 | L37: =L35/L36 -> 51.786481 | M37: =M35/M36 -> 74.335665 | ... P37: =P35/P36 -> 50.944194 | Q37: =AVERAGE(E37:P37) -> 47.35138

Sheet SWOT
O2: Notes
B3: Strengths
C4: Data Center
D5: - Handles compute-intensive workloads (AI, data analytics, graphics & scientific computing)
D6: - compute offerings (supercomputing platforms & servers)
E7: -- GPUs, DPUs
E8: -- NVIDIA AI Enterprise software | O8: Comprehensive suite of enterprise-grade AI software
E9: -- NVIDIA vGPU
E10: -- NVIDIA DGX cloud service
D11: - network offerings
E12: -- end to end platforms for InfiniBand & ethernet
C14: Gaming
D15: - RTX & GTX GPUs
D16: - NVIDIA DLSS (Deep Learning Super Sampling)
D17: - GeForce NOW cloud gaming
D18: - NVIDIA Tegra SoCs | O18: - SoCs (system-on-a-chip) & development services for game consoles
C20: Professional Visualization
D21: - NVIDIA Omniverse
C23: Automotive
D24: - DRIVE Hyperion
C26: Manufacturing
D27: - Fabless and contracting manufacturing strategy | O27: Partner with key suppliers on all phases of manufacturing process (wafer fabrication, assembly, testing & packaging)
D28: - Focus on product design, quality control, reliability, marketing & customer support
D29: - May place inventory orders for product components to secure future supply (in growth periods)
D30: - Supply chain is concentrated in Asia-Pacific region
E31: Foundries to produce semiconductor wafers
F32: -- Taiwan Semiconductor Manufacturing Co Ltd (TSMC) | O32: Utilize CoWoS technology for semiconductor packaging
F33: -- Samsung Electronics Co. Ltd
E34: Purchase of Memory
F35: -- Micron Technology Inc
F36: -- SK Hynix Inc | O36: South korea
E37: Assembly , Testing and packaging of final products
F38: -- Hon Hai Precision Industry Co Ltd
F39: -- Wistron Corporation
F40: -- Fabrinet
B43: Weaknesses
B47: Opportunities
C48: Artificial Intelligence
D49: - NVIDIA DGX cloud service
D50: - NVIDIA NeMo
B53: Threats
C54: Suppliers/Licensors of hardware/software for GPUs, Custom Chips and other accelerated computing solutions (including AI)
D55: -- Advanced Micro Devices Inc (AMD)
D56: -- Huawei Technologies Co Ltd
D57: -- Intel Corporation
C59: Large Cloud Services
D60: -- Amazon Inc
D61: -- Alphabet Inc (Google)
D62: -- Microsoft
D63: -- Alibaba Group
D64: -- Baidu Inc
D65: -- Huawei
C67: Suppliers of hardware/software for SoC products (used in servers, automobiles, autonomous machines, and gaming devices)
D68: -- Ambarella Inc
D69: -- AMD
D70: -- Broadcom Inc
D71: -- Intel Corporation
D72: -- Qualcomm Incorporated
D73: -- Renesas Electronics Corporation
D74: -- Samsung
C76: Networking products (switches, network adapters, DPUs, cable solutions - incl. optical modules)
D77: -- AMD
D78: -- Arista Networks
D79: -- Broadcom Inc
D80: -- Cisco Systems
D81: -- Hewlett Packard Enterprise
D82: -- Huawei
D83: -- Intel Corporation
D84: -- Lumentum Holdings
D85: -- Marvell Technology Group
